Workbook

Sheet Dashboard
A1: FINANCIAL DASHBOARD - CUMULATIVE SUMMARY
A3: CURRENT STATUS | F3: YEAR-TO-DATE SUMMARY
A4: Latest Month: | B4: =IFERROR(__xludf.DUMMYFUNCTION("RIGHT(INDEX(SORT(FILTER(INDIRECT(""Banks_Comparison!3:3""),INDIRECT(""Banks_Comparison!3:3"")<>"""")),1,COLUMNS(FILTER(INDIRECT(""Banks_Comparison!3:3""),INDIRECT(""Banks_Comparison!3:3"")<>""""))),8)"),"45962") -> 45962 | F4: Total Received: | H4: =SUM(Banks_Comparison!5:5) -> 28577792
A5: Bank Balance: | B5: {=INDEX(Banks_Comparison!8:8,1,COUNTA(Banks_Comparison!3:3))} -> 2498320.6 | F5: Total Payments: | H5: =SUM(Banks_Comparison!7:7) -> 27400972
A6: Total Outstanding: | B6: {=INDEX(Outstanding_Comparison!15:15,1,COUNTA(Outstanding_Comparison!3:3))} -> 0 | F6: Net Cash Flow: | H6: =H4-H5 -> 1176820
A7: Advance Balance: | B7: {=INDEX(Advances_Comparison!7:7,1,COUNTA(Advances_Comparison!3:3))} -> 0 | F7: Avg Outstanding: | H7: =AVERAGE(Outstanding_Comparison!15:15) -> 0
A8: Suspense Balance: | B8: {=INDEX(Suspense_Comparison!7:7,1,COUNTA(Suspense_Comparison!3:3))} -> 0
A10: KEY PERFORMANCE INDICATORS
A11: Months Tracked | C11: Highest Bank Balance | E11: Lowest Bank Balance | G11: Average Monthly Revenue
A12: =COUNTA(Banks_Comparison!3:3)-1 -> 11 | C12: =MAX(Banks_Comparison!8:8) -> 3850313.6 | E12: =MIN(Banks_Comparison!8:8) -> 1143292.7 | G12: =AVERAGE(Banks_Comparison!5:5) -> 2597981.1
A13: Total Advances Given | C13: Total Advances Settled | E13: Outstanding Growth Rate | G13: Cash Position
A14: =SUM(Advances_Comparison!5:5) -> 6020817.6 | C14: =SUM(Advances_Comparison!6:6) -> 0 | E14: {=IFERROR((INDEX(Outstanding_Comparison!15:15,1,COUNTA(Outstanding_Comparison!3:3))-INDEX(Outstanding_Comparison!15:15,1,2))/INDEX(Outstanding_Comparison!15:15,1,2)*100,0)&"%"} -> 0% | G14: =B5-B6 -> 2498320.6

Sheet Banks_Comparison
A1: BANKS - MONTHLY COMPARISON
A3: Metric | B3: 45658 | C3: 45689 | D3: 45717 | E3: 45748 | F3: 45778 | G3: 45809 | H3: 45839 | I3: 45870 | J3: 45901 | K3: 45931 | L3: 45962
A4: Opening Balance | B4: =IFERROR('Banks_JAN-2025'!B9,0) -> 1355020 | C4: =IFERROR('Banks_FEB-2025'!B9,0) -> 1141022.6 | D4: =IFERROR('Banks_MAR-2025'!B9,0) -> 2258424.8 | E4: =IFERROR('Banks_APR-2025'!B9,0) -> 1719247.4 | F4: =IFERROR('Banks_MAY-2025'!B9,0) -> 1870886.3 | G4: =IFERROR('Banks_JUN-2025'!B9,0) -> 2485212.9 | H4: =IFERROR('Banks_JUL-2025'!B9,0) -> 1925336.9 | I4: =IFERROR('Banks_AUG-2025'!B9,0) -> 2629726.3 | J4: =IFERROR('Banks_SEP-2025'!B9,0) -> 2448776.9 | K4: =IFERROR('Banks_OCT-2025'!B9,0) -> 3838867.4 | L4: =IFERROR('Banks_NOV-2025'!B9,0) -> 2497819.7
A5: Total Received | B5: =IFERROR('Banks_JAN-2025'!C9,0) -> 3674582 | C5: =IFERROR('Banks_FEB-2025'!C9,0) -> 2714430.9 | D5: =IFERROR('Banks_MAR-2025'!C9,0) -> 2578455.9 | E5: =IFERROR('Banks_APR-2025'!C9,0) -> 1997152.5 | F5: =IFERROR('Banks_MAY-2025'!C9,0) -> 2829237.9 | G5: =IFERROR('Banks_JUN-2025'!C9,0) -> 2824082.1 | H5: =IFERROR('Banks_JUL-2025'!C9,0) -> 2202032.4 | I5: =IFERROR('Banks_AUG-2025'!C9,0) -> 3137664.5 | J5: =IFERROR('Banks_SEP-2025'!C9,0) -> 2231502.5 | K5: =IFERROR('Banks_OCT-2025'!C9,0) -> 4388651.4 | L5: =IFERROR('Banks_NOV-2025'!C9,0) -> 0
A6: Bank Charges | B6: =IFERROR('Banks_JAN-2025'!D9,0) -> 2415.86 | C6: =IFERROR('Banks_FEB-2025'!D9,0) -> 3176.7 | D6: =IFERROR('Banks_MAR-2025'!D9,0) -> 2938.5 | E6: =IFERROR('Banks_APR-2025'!D9,0) -> 2944.07 | F6: =IFERROR('Banks_MAY-2025'!D9,0) -> 3564.49 | G6: =IFERROR('Banks_JUN-2025'!D9,0) -> 3758.16 | H6: =IFERROR('Banks_JUL-2025'!D9,0) -> 3200.98 | I6: =IFERROR('Banks_AUG-2025'!D9,0) -> 3646.93 | J6: =IFERROR('Banks_SEP-2025'!D9,0) -> 4046.1 | K6: =IFERROR('Banks_OCT-2025'!D9,0) -> 4329.87 | L6: =IFERROR('Banks_NOV-2025'!D9,0) -> 0
A7: Total Payments | B7: =IFERROR('Banks_JAN-2025'!E9,0) -> 3886163.6 | C7: =IFERROR('Banks_FEB-2025'!E9,0) -> 1593852 | D7: =IFERROR('Banks_MAR-2025'!E9,0) -> 3114694.8 | E7: =IFERROR('Banks_APR-2025'!E9,0) -> 1842569.6 | F7: =IFERROR('Banks_MAY-2025'!E9,0) -> 2211346.8 | G7: =IFERROR('Banks_JUN-2025'!E9,0) -> 3380199.9 | H7: =IFERROR('Banks_JUL-2025'!E9,0) -> 1494442.1 | I7: =IFERROR('Banks_AUG-2025'!E9,0) -> 3314968.4 | J7: =IFERROR('Banks_SEP-2025'!E9,0) -> 837365.86 | K7: =IFERROR('Banks_OCT-2025'!E9,0) -> 5725369.1 | L7: =IFERROR('Banks_NOV-2025'!E9,0) -> 0
A8: Closing Balance | B8: =IFERROR('Banks_JAN-2025'!F17,0) -> 1143292.7 | C8: =IFERROR('Banks_FEB-2025'!F17,0) -> 2260694.9 | D8: =IFERROR('Banks_MAR-2025'!F17,0) -> 1722677.3 | E8: =IFERROR('Banks_APR-2025'!F17,0) -> 1875053.6 | F8: =IFERROR('Banks_MAY-2025'!F17,0) -> 2489314 | G8: =IFERROR('Banks_JUN-2025'!F17,0) -> 1926729.1 | H8: =IFERROR('Banks_JUL-2025'!F17,0) -> 2631118.5 | I8: =IFERROR('Banks_AUG-2025'!F17,0) -> 2450363.6 | J8: =IFERROR('Banks_SEP-2025'!F17,0) -> 3850313.6 | K8: =IFERROR('Banks_OCT-2025'!F17,0) -> 2498320.6 | L8: =IFERROR('Banks_NOV-2025'!F17,0) -> 2498320.6
A9: Net Cash Flow | B9: =B5-B7 -> -211581.6 | C9: =C5-C7 -> 1120578.9 | D9: =D5-D7 -> -536238.85 | E9: =E5-E7 -> 154582.91 | F9: =F5-F7 -> 617891.08 | G9: =G5-G7 -> -556117.74 | H9: =H5-H7 -> 707590.32 | I9: =I5-I7 -> -177303.81 | ... L9: =L5-L7 -> 0
A10: Month-over-Month % | C10: =IFERROR((C8-B8)/B8,0) -> 0.97735447 | D10: =IFERROR((D8-C8)/C8,0) -> -0.23798769 | E10: =IFERROR((E8-D8)/D8,0) -> 0.088453153 | F10: =IFERROR((F8-E8)/E8,0) -> 0.32759623 | G10: =IFERROR((G8-F8)/F8,0) -> -0.22599997 | H10: =IFERROR((H8-G8)/G8,0) -> 0.36558815 | I10: =IFERROR((I8-H8)/H8,0) -> -0.068698874 | J10: =IFERROR((J8-I8)/I8,0) -> 0.57132338 | ... L10: =IFERROR((L8-K8)/K8,0) -> 0

Sheet Advances_Comparison
A1: ADVANCES - MONTHLY COMPARISON
A3: Metric | B3: 45658 | C3: 45689 | D3: 45717 | E3: 45748 | F3: 45778 | G3: 45809 | H3: 45839 | I3: 45870 | J3: 45901 | K3: 45931 | L3: 45962
A4: Opening Balance | B4: =IFERROR('Advances_JAN-2025'!B3,0) -> 163800.84 | C4: =IFERROR('Advances_FEB-2025'!B3,0) -> 479608.52 | D4: =IFERROR('Advances_MAR-2025'!B3,0) -> 489038.28 | E4: =IFERROR('Advances_APR-2025'!B3,0) -> 491564.28 | F4: =IFERROR('Advances_MAY-2025'!B3,0) -> 541048.28 | G4: =IFERROR('Advances_JUN-2025'!B3,0) -> 472788.43 | H4: =IFERROR('Advances_JUL-2025'!B3,0) -> 504240.98 | I4: =IFERROR('Advances_AUG-2025'!B3,0) -> 452575.39 | J4: =IFERROR('Advances_SEP-2025'!B3,0) -> 473840.39 | K4: =IFERROR('Advances_OCT-2025'!B3,0) -> 504511.39 | L4: =IFERROR('Advances_NOV-2025'!B3,0) -> 540959.39
A5: Advances Given | B5: =IFERROR(SUM('Advances_JAN-2025'!E7:E1000),0) -> 629615.36 | C5: =IFERROR(SUM('Advances_FEB-2025'!E7:E1000),0) -> 813275.72 | D5: =IFERROR(SUM('Advances_MAR-2025'!E7:E1000),0) -> 653526.88 | E5: =IFERROR(SUM('Advances_APR-2025'!E7:E1000),0) -> 752494.88 | F5: =IFERROR(SUM('Advances_MAY-2025'!E7:E1000),0) -> 615975.18 | G5: =IFERROR(SUM('Advances_JUN-2025'!E7:E1000),0) -> 678880.28 | H5: =IFERROR(SUM('Advances_JUL-2025'!E7:E1000),0) -> 577549.1 | I5: =IFERROR(SUM('Advances_AUG-2025'!E7:E1000),0) -> 618079.1 | J5: =IFERROR(SUM('Advances_SEP-2025'!E7:E1000),0) -> 681421.1 | K5: =IFERROR(SUM('Advances_OCT-2025'!E7:E1000),0) -> 0 | L5: =IFERROR(SUM('Advances_NOV-2025'!E7:E1000),0) -> 0
A6: Advances Settled | B6: 0 | C6: 0 | D6: 0 | E6: 0 | F6: 0 | G6: 0 | H6: 0 | I6: 0 | J6: 0 | K6: 0 | L6: 0
A7: Closing Balance | B7: =IFERROR('Advances_JAN-2025'!E3,0) -> 479608.52 | C7: =IFERROR('Advances_FEB-2025'!E3,0) -> 489038.28 | D7: =IFERROR('Advances_MAR-2025'!E3,0) -> 491564.28 | E7: =IFERROR('Advances_APR-2025'!E3,0) -> 541048.28 | F7: =IFERROR('Advances_MAY-2025'!E3,0) -> 472788.43 | G7: =IFERROR('Advances_JUN-2025'!E3,0) -> 504240.98 | H7: =IFERROR('Advances_JUL-2025'!E3,0) -> 453575.39 | I7: =IFERROR('Advances_AUG-2025'!E3,0) -> 473840.39 | J7: =IFERROR('Advances_SEP-2025'!E3,0) -> 504511.39 | K7: =IFERROR('Advances_OCT-2025'!E3,0) -> 540959.39 | L7: =IFERROR('Advances_NOV-2025'!E3,0) -> 0
A8: Settlement Rate %
A9: Average Advance

Sheet Suspense_Comparison
A1: SUSPENSE - MONTHLY COMPARISON
A3: Metric | B3: 45658 | C3: 45689 | D3: 45717 | E3: 45748 | F3: 45778 | G3: 45809 | H3: 45839 | I3: 45870 | J3: 45901 | K3: 45931 | L3: 45962
A4: Opening Balance | B4: =IFERROR('Suspense_JAN-2025'!B3,0) -> -7420.48 | C4: =IFERROR('Suspense_FEB-2025'!B3,0) -> -62065.42 | D4: =IFERROR('Suspense_MAR-2025'!B3,0) -> -162101.8 | E4: =IFERROR('Suspense_APR-2025'!B3,0) -> -105635.53 | F4: =IFERROR('Suspense_MAY-2025'!B3,0) -> -109186.92 | G4: =IFERROR('Suspense_JUN-2025'!B3,0) -> -156614.8 | H4: =IFERROR('Suspense_JUL-2025'!B3,0) -> -149060.68 | I4: =IFERROR('Suspense_AUG-2025'!B3,0) -> -289792.79 | J4: =IFERROR('Suspense_SEP-2025'!B3,0) -> -22235.07 | K4: =IFERROR('Suspense_OCT-2025'!B3,0) -> -59758.42 | L4: =IFERROR('Suspense_NOV-2025'!B3,0) -> -186506.88
A5: Total Debits | B5: =IFERROR(SUM('Suspense_JAN-2025'!E7:E1000)-SUM('Suspense_JAN-2025'!F7:F1000),0) -> -44797.78 | C5: =IFERROR(SUM('Suspense_FEB-2025'!E7:E1000)-SUM('Suspense_FEB-2025'!F7:F1000),0) -> -144834.16 | D5: =IFERROR(SUM('Suspense_MAR-2025'!E7:E1000)-SUM('Suspense_MAR-2025'!F7:F1000),0) -> -96035.42 | E5: =IFERROR(SUM('Suspense_APR-2025'!E7:E1000)-SUM('Suspense_APR-2025'!F7:F1000),0) -> -54928.7 | F5: =IFERROR(SUM('Suspense_MAY-2025'!E7:E1000)-SUM('Suspense_MAY-2025'!F7:F1000),0) -> -78715.91 | G5: =IFERROR(SUM('Suspense_JUN-2025'!E7:E1000)-SUM('Suspense_JUN-2025'!F7:F1000),0) -> -32717.68 | H5: =IFERROR(SUM('Suspense_JUL-2025'!E7:E1000)-SUM('Suspense_JUL-2025'!F7:F1000),0) -> -329290.14 | I5: =IFERROR(SUM('Suspense_AUG-2025'!E7:E1000)-SUM('Suspense_AUG-2025'!F7:F1000),0) -> -44470.14 | J5: =IFERROR(SUM('Suspense_SEP-2025'!E7:E1000)-SUM('Suspense_SEP-2025'!F7:F1000),0) -> -42490.78 | K5: =IFERROR(SUM('Suspense_OCT-2025'!E7:E1000)-SUM('Suspense_OCT-2025'!F7:F1000),0) -> -169239.24 | L5: =IFERROR(SUM('Suspense_NOV-2025'!E7:E1000)-SUM('Suspense_NOV-2025'!F7:F1000),0) -> 0
A6: Total Credits | B6: 0 | C6: 0 | D6: 0 | E6: 0 | F6: 0 | G6: 0 | H6: 0 | I6: 0 | J6: 0 | K6: 0 | L6: 0
A7: Closing Balance | B7: =IFERROR('Suspense_JAN-2025'!E3,0) -> -62065.42 | C7: =IFERROR('Suspense_FEB-2025'!E3,0) -> -162101.8 | D7: =IFERROR('Suspense_MAR-2025'!E3,0) -> -113303.06 | E7: =IFERROR('Suspense_APR-2025'!E3,0) -> -72196.34 | F7: =IFERROR('Suspense_MAY-2025'!E3,0) -> -95983.55 | G7: =IFERROR('Suspense_JUN-2025'!E3,0) -> -49985.32 | H7: =IFERROR('Suspense_JUL-2025'!E3,0) -> -181912.71 | I7: =IFERROR('Suspense_AUG-2025'!E3,0) -> -61737.78 | J7: =IFERROR('Suspense_SEP-2025'!E3,0) -> -59758.42 | K7: =IFERROR('Suspense_OCT-2025'!E3,0) -> -186506.88 | L7: =IFERROR('Suspense_NOV-2025'!E3,0) -> 0
A8: Unidentified Items
A9: Resolution Rate %

Sheet Outstanding_Comparison
A1: CUSTOMER OUTSTANDING - MONTHLY COMPARISON
A3: Salesman | B3: Trend | C3: 45658 | D3: 45689 | E3: 45717 | F3: 45748 | G3: 45778 | H3: 45809 | I3: 45839 | J3: 45870 | K3: 45901 | L3: 45931 | M3: 45962
A4: nidheesh | B4: =IFERROR(__xludf.DUMMYFUNCTION("IF(COUNTA(C4:M4)=0,"""",SPARKLINE(C4:M4,{""charttype"",""line"";""linewidth"",2}))"),"") | C4: =IFERROR(SUMIF('Outstanding_JAN-2025'!$D$19:$D$502,$A4,'Outstanding_JAN-2025'!$G$19:$G$502),0) -> 42552.35 | D4: =IFERROR(SUMIF('Outstanding_FEB-2025'!$D$19:$D$502,$A4,'Outstanding_FEB-2025'!$G$19:$G$502),0) -> 45063.62 | E4: =IFERROR(SUMIF('Outstanding_MAR-2025'!$D$19:$D$502,$A4,'Outstanding_MAR-2025'!$G$19:$G$502),0) -> 57982.29 | F4: =IFERROR(SUMIF('Outstanding_APR-2025'!$D$19:$D$502,$A4,'Outstanding_APR-2025'!$G$19:$G$502),0) -> 55220.63 | G4: =IFERROR(SUMIF('Outstanding_MAY-2025'!$D$19:$D$502,$A4,'Outstanding_MAY-2025'!$G$19:$G$502),0) -> 86898.24 | H4: =IFERROR(SUMIF('Outstanding_JUN-2025'!$D$19:$D$502,$A4,'Outstanding_JUN-2025'!$G$19:$G$502),0) -> 74345.29 | I4: =IFERROR(SUMIF('Outstanding_JUL-2025'!$D$19:$D$502,$A4,'Outstanding_JUL-2025'!$G$19:$G$502),0) -> 71919.95 | J4: =IFERROR(SUMIF('Outstanding_AUG-2025'!$D$19:$D$502,$A4,'Outstanding_AUG-2025'!$G$19:$G$502),0) -> 69826.96 | K4: =IFERROR(SUMIF('Outstanding_SEP-2025'!$D$19:$D$502,$A4,'Outstanding_SEP-2025'!$G$19:$G$502),0) -> 72379.87 | L4: =IFERROR(SUMIF('Outstanding_OCT-2025'!$D$19:$D$502,$A4,'Outstanding_OCT-2025'!$G$19:$G$502),0) -> 76836.77 | M4: =IFERROR(SUMIF('Outstanding_NOV-2025'!$D$19:$D$502,$A4,'Outstanding_NOV-2025'!$G$19:$G$502),0) -> 79345.24
A5: jaseel | B5: =IFERROR(__xludf.DUMMYFUNCTION("IF(COUNTA(C5:M5)=0,"""",SPARKLINE(C5:M5,{""charttype"",""line"";""linewidth"",2}))"),"") | C5: =IFERROR(SUMIF('Outstanding_JAN-2025'!$D$19:$D$502,$A5,'Outstanding_JAN-2025'!$G$19:$G$502),0) -> 24265.64 | D5: =IFERROR(SUMIF('Outstanding_FEB-2025'!$D$19:$D$502,$A5,'Outstanding_FEB-2025'!$G$19:$G$502),0) -> 25395.4 | E5: =IFERROR(SUMIF('Outstanding_MAR-2025'!$D$19:$D$502,$A5,'Outstanding_MAR-2025'!$G$19:$G$502),0) -> 23396.73 | F5: =IFERROR(SUMIF('Outstanding_APR-2025'!$D$19:$D$502,$A5,'Outstanding_APR-2025'!$G$19:$G$502),0) -> 23222.49 | G5: =IFERROR(SUMIF('Outstanding_MAY-2025'!$D$19:$D$502,$A5,'Outstanding_MAY-2025'!$G$19:$G$502),0) -> 18197.45 | H5: =IFERROR(SUMIF('Outstanding_JUN-2025'!$D$19:$D$502,$A5,'Outstanding_JUN-2025'!$G$19:$G$502),0) -> 16255.67 | I5: =IFERROR(SUMIF('Outstanding_JUL-2025'!$D$19:$D$502,$A5,'Outstanding_JUL-2025'!$G$19:$G$502),0) -> 23149.21 | J5: =IFERROR(SUMIF('Outstanding_AUG-2025'!$D$19:$D$502,$A5,'Outstanding_AUG-2025'!$G$19:$G$502),0) -> 24260.07 | K5: =IFERROR(SUMIF('Outstanding_SEP-2025'!$D$19:$D$502,$A5,'Outstanding_SEP-2025'!$G$19:$G$502),0) -> 23755.49 | L5: =IFERROR(SUMIF('Outstanding_OCT-2025'!$D$19:$D$502,$A5,'Outstanding_OCT-2025'!$G$19:$G$502),0) -> 20506.08 | M5: =IFERROR(SUMIF('Outstanding_NOV-2025'!$D$19:$D$502,$A5,'Outstanding_NOV-2025'!$G$19:$G$502),0) -> 19951.36
A6: bassam | B6: =IFERROR(__xludf.DUMMYFUNCTION("IF(COUNTA(C6:M6)=0,"""",SPARKLINE(C6:M6,{""charttype"",""line"";""linewidth"",2}))"),"") | C6: =IFERROR(SUMIF('Outstanding_JAN-2025'!$D$19:$D$502,$A6,'Outstanding_JAN-2025'!$G$19:$G$502),0) -> 17887.52 | D6: =IFERROR(SUMIF('Outstanding_FEB-2025'!$D$19:$D$502,$A6,'Outstanding_FEB-2025'!$G$19:$G$502),0) -> 7652.1 | E6: =IFERROR(SUMIF('Outstanding_MAR-2025'!$D$19:$D$502,$A6,'Outstanding_MAR-2025'!$G$19:$G$502),0) -> 15534.5 | F6: =IFERROR(SUMIF('Outstanding_APR-2025'!$D$19:$D$502,$A6,'Outstanding_APR-2025'!$G$19:$G$502),0) -> 14069.24 | G6: =IFERROR(SUMIF('Outstanding_MAY-2025'!$D$19:$D$502,$A6,'Outstanding_MAY-2025'!$G$19:$G$502),0) -> 24512.04 | H6: =IFERROR(SUMIF('Outstanding_JUN-2025'!$D$19:$D$502,$A6,'Outstanding_JUN-2025'!$G$19:$G$502),0) -> 22573.22 | I6: =IFERROR(SUMIF('Outstanding_JUL-2025'!$D$19:$D$502,$A6,'Outstanding_JUL-2025'!$G$19:$G$502),0) -> 25052.83 | J6: =IFERROR(SUMIF('Outstanding_AUG-2025'!$D$19:$D$502,$A6,'Outstanding_AUG-2025'!$G$19:$G$502),0) -> 19724.86 | K6: =IFERROR(SUMIF('Outstanding_SEP-2025'!$D$19:$D$502,$A6,'Outstanding_SEP-2025'!$G$19:$G$502),0) -> 24945 | L6: =IFERROR(SUMIF('Outstanding_OCT-2025'!$D$19:$D$502,$A6,'Outstanding_OCT-2025'!$G$19:$G$502),0) -> 25219.28 | M6: =IFERROR(SUMIF('Outstanding_NOV-2025'!$D$19:$D$502,$A6,'Outstanding_NOV-2025'!$G$19:$G$502),0) -> 22733.87
A7: akmal | B7: =IFERROR(__xludf.DUMMYFUNCTION("IF(COUNTA(C7:M7)=0,"""",SPARKLINE(C7:M7,{""charttype"",""line"";""linewidth"",2}))"),"") | C7: =IFERROR(SUMIF('Outstanding_JAN-2025'!$D$19:$D$502,$A7,'Outstanding_JAN-2025'!$G$19:$G$502),0) -> 575.93 | D7: =IFERROR(SUMIF('Outstanding_FEB-2025'!$D$19:$D$502,$A7,'Outstanding_FEB-2025'!$G$19:$G$502),0) -> 837.92 | E7: =IFERROR(SUMIF('Outstanding_MAR-2025'!$D$19:$D$502,$A7,'Outstanding_MAR-2025'!$G$19:$G$502),0) -> 15595.44 | F7: =IFERROR(SUMIF('Outstanding_APR-2025'!$D$19:$D$502,$A7,'Outstanding_APR-2025'!$G$19:$G$502),0) -> 14302.95 | G7: =IFERROR(SUMIF('Outstanding_MAY-2025'!$D$19:$D$502,$A7,'Outstanding_MAY-2025'!$G$19:$G$502),0) -> 17759.41 | H7: =IFERROR(SUMIF('Outstanding_JUN-2025'!$D$19:$D$502,$A7,'Outstanding_JUN-2025'!$G$19:$G$502),0) -> 21216.07 | I7: =IFERROR(SUMIF('Outstanding_JUL-2025'!$D$19:$D$502,$A7,'Outstanding_JUL-2025'!$G$19:$G$502),0) -> 32516.24 | J7: =IFERROR(SUMIF('Outstanding_AUG-2025'!$D$19:$D$502,$A7,'Outstanding_AUG-2025'!$G$19:$G$502),0) -> 38060.96 | K7: =IFERROR(SUMIF('Outstanding_SEP-2025'!$D$19:$D$502,$A7,'Outstanding_SEP-2025'!$G$19:$G$502),0) -> 54291.15 | L7: =IFERROR(SUMIF('Outstanding_OCT-2025'!$D$19:$D$502,$A7,'Outstanding_OCT-2025'!$G$19:$G$502),0) -> 45795.01 | M7: =IFERROR(SUMIF('Outstanding_NOV-2025'!$D$19:$D$502,$A7,'Outstanding_NOV-2025'!$G$19:$G$502),0) -> 34121.05
A8: arshad | B8: =IFERROR(__xludf.DUMMYFUNCTION("IF(COUNTA(C8:M8)=0,"""",SPARKLINE(C8:M8,{""charttype"",""line"";""linewidth"",2}))"),"") | C8: =IFERROR(SUMIF('Outstanding_JAN-2025'!$D$19:$D$502,$A8,'Outstanding_JAN-2025'!$G$19:$G$502),0) -> 401746.31 | D8: =IFERROR(SUMIF('Outstanding_FEB-2025'!$D$19:$D$502,$A8,'Outstanding_FEB-2025'!$G$19:$G$502),0) -> 386314.4 | E8: =IFERROR(SUMIF('Outstanding_MAR-2025'!$D$19:$D$502,$A8,'Outstanding_MAR-2025'!$G$19:$G$502),0) -> 408441.36 | F8: =IFERROR(SUMIF('Outstanding_APR-2025'!$D$19:$D$502,$A8,'Outstanding_APR-2025'!$G$19:$G$502),0) -> 390433.84 | G8: =IFERROR(SUMIF('Outstanding_MAY-2025'!$D$19:$D$502,$A8,'Outstanding_MAY-2025'!$G$19:$G$502),0) -> 372922.38 | H8: =IFERROR(SUMIF('Outstanding_JUN-2025'!$D$19:$D$502,$A8,'Outstanding_JUN-2025'!$G$19:$G$502),0) -> 396181.7 | I8: =IFERROR(SUMIF('Outstanding_JUL-2025'!$D$19:$D$502,$A8,'Outstanding_JUL-2025'!$G$19:$G$502),0) -> 398562.17 | J8: =IFERROR(SUMIF('Outstanding_AUG-2025'!$D$19:$D$502,$A8,'Outstanding_AUG-2025'!$G$19:$G$502),0) -> 329881.32 | K8: =IFERROR(SUMIF('Outstanding_SEP-2025'!$D$19:$D$502,$A8,'Outstanding_SEP-2025'!$G$19:$G$502),0) -> 343351.34 | L8: =IFERROR(SUMIF('Outstanding_OCT-2025'!$D$19:$D$502,$A8,'Outstanding_OCT-2025'!$G$19:$G$502),0) -> 366543.83 | M8: =IFERROR(SUMIF('Outstanding_NOV-2025'!$D$19:$D$502,$A8,'Outstanding_NOV-2025'!$G$19:$G$502),0) -> 486637.4
A9: Shameer riyadh | B9: =IFERROR(__xludf.DUMMYFUNCTION("IF(COUNTA(C9:M9)=0,"""",SPARKLINE(C9:M9,{""charttype"",""line"";""linewidth"",2}))"),"") | C9: =IFERROR(SUMIF('Outstanding_JAN-2025'!$D$19:$D$502,$A9,'Outstanding_JAN-2025'!$G$19:$G$502),0) -> 22083.16 | D9: =IFERROR(SUMIF('Outstanding_FEB-2025'!$D$19:$D$502,$A9,'Outstanding_FEB-2025'!$G$19:$G$502),0) -> 45700.21 | E9: =IFERROR(SUMIF('Outstanding_MAR-2025'!$D$19:$D$502,$A9,'Outstanding_MAR-2025'!$G$19:$G$502),0) -> 45671.06 | F9: =IFERROR(SUMIF('Outstanding_APR-2025'!$D$19:$D$502,$A9,'Outstanding_APR-2025'!$G$19:$G$502),0) -> 59897.57 | G9: =IFERROR(SUMIF('Outstanding_MAY-2025'!$D$19:$D$502,$A9,'Outstanding_MAY-2025'!$G$19:$G$502),0) -> 65021.92 | H9: =IFERROR(SUMIF('Outstanding_JUN-2025'!$D$19:$D$502,$A9,'Outstanding_JUN-2025'!$G$19:$G$502),0) -> 69892.24 | I9: =IFERROR(SUMIF('Outstanding_JUL-2025'!$D$19:$D$502,$A9,'Outstanding_JUL-2025'!$G$19:$G$502),0) -> 66813.14 | J9: =IFERROR(SUMIF('Outstanding_AUG-2025'!$D$19:$D$502,$A9,'Outstanding_AUG-2025'!$G$19:$G$502),0) -> 71998.44 | K9: =IFERROR(SUMIF('Outstanding_SEP-2025'!$D$19:$D$502,$A9,'Outstanding_SEP-2025'!$G$19:$G$502),0) -> 77103.34 | L9: =IFERROR(SUMIF('Outstanding_OCT-2025'!$D$19:$D$502,$A9,'Outstanding_OCT-2025'!$G$19:$G$502),0) -> 72659.84 | M9: =IFERROR(SUMIF('Outstanding_NOV-2025'!$D$19:$D$502,$A9,'Outstanding_NOV-2025'!$G$19:$G$502),0) -> 92907.92
A10: company sales | B10: =IFERROR(__xludf.DUMMYFUNCTION("IF(COUNTA(C10:M10)=0,"""",SPARKLINE(C10:M10,{""charttype"",""line"";""linewidth"",2}))"),"") | C10: =IFERROR(SUMIF('Outstanding_JAN-2025'!$D$19:$D$502,$A10,'Outstanding_JAN-2025'!$G$19:$G$502),0) -> 985953.74 | D10: =IFERROR(SUMIF('Outstanding_FEB-2025'!$D$19:$D$502,$A10,'Outstanding_FEB-2025'!$G$19:$G$502),0) -> 778183.07 | E10: =IFERROR(SUMIF('Outstanding_MAR-2025'!$D$19:$D$502,$A10,'Outstanding_MAR-2025'!$G$19:$G$502),0) -> 650384.77 | F10: =IFERROR(SUMIF('Outstanding_APR-2025'!$D$19:$D$502,$A10,'Outstanding_APR-2025'!$G$19:$G$502),0) -> 809040.72 | G10: =IFERROR(SUMIF('Outstanding_MAY-2025'!$D$19:$D$502,$A10,'Outstanding_MAY-2025'!$G$19:$G$502),0) -> 1349535.5 | H10: =IFERROR(SUMIF('Outstanding_JUN-2025'!$D$19:$D$502,$A10,'Outstanding_JUN-2025'!$G$19:$G$502),0) -> 1250206 | I10: =IFERROR(SUMIF('Outstanding_JUL-2025'!$D$19:$D$502,$A10,'Outstanding_JUL-2025'!$G$19:$G$502),0) -> 1434277.6 | J10: =IFERROR(SUMIF('Outstanding_AUG-2025'!$D$19:$D$502,$A10,'Outstanding_AUG-2025'!$G$19:$G$502),0) -> 1087241.2 | K10: =IFERROR(SUMIF('Outstanding_SEP-2025'!$D$19:$D$502,$A10,'Outstanding_SEP-2025'!$G$19:$G$502),0) -> 1068473.3 | L10: =IFERROR(SUMIF('Outstanding_OCT-2025'!$D$19:$D$502,$A10,'Outstanding_OCT-2025'!$G$19:$G$502),0) -> 1056569.4 | M10: =IFERROR(SUMIF('Outstanding_NOV-2025'!$D$19:$D$502,$A10,'Outstanding_NOV-2025'!$G$19:$G$502),0) -> 976412.87
A11: shafi | B11: =IFERROR(__xludf.DUMMYFUNCTION("IF(COUNTA(C11:M11)=0,"""",SPARKLINE(C11:M11,{""charttype"",""line"";""linewidth"",2}))"),"") | C11: =IFERROR(SUMIF('Outstanding_JAN-2025'!$D$19:$D$502,$A11,'Outstanding_JAN-2025'!$G$19:$G$502),0) -> 0 | D11: =IFERROR(SUMIF('Outstanding_FEB-2025'!$D$19:$D$502,$A11,'Outstanding_FEB-2025'!$G$19:$G$502),0) -> 0 | E11: =IFERROR(SUMIF('Outstanding_MAR-2025'!$D$19:$D$502,$A11,'Outstanding_MAR-2025'!$G$19:$G$502),0) -> 779.99 | F11: =IFERROR(SUMIF('Outstanding_APR-2025'!$D$19:$D$502,$A11,'Outstanding_APR-2025'!$G$19:$G$502),0) -> 4846.35 | G11: =IFERROR(SUMIF('Outstanding_MAY-2025'!$D$19:$D$502,$A11,'Outstanding_MAY-2025'!$G$19:$G$502),0) -> 8545.51 | H11: =IFERROR(SUMIF('Outstanding_JUN-2025'!$D$19:$D$502,$A11,'Outstanding_JUN-2025'!$G$19:$G$502),0) -> 7230.55 | I11: =IFERROR(SUMIF('Outstanding_JUL-2025'!$D$19:$D$502,$A11,'Outstanding_JUL-2025'!$G$19:$G$502),0) -> 13792.6 | J11: =IFERROR(SUMIF('Outstanding_AUG-2025'!$D$19:$D$502,$A11,'Outstanding_AUG-2025'!$G$19:$G$502),0) -> 16057.58 | K11: =IFERROR(SUMIF('Outstanding_SEP-2025'!$D$19:$D$502,$A11,'Outstanding_SEP-2025'!$G$19:$G$502),0) -> 17862.18 | L11: =IFERROR(SUMIF('Outstanding_OCT-2025'!$D$19:$D$502,$A11,'Outstanding_OCT-2025'!$G$19:$G$502),0) -> 17259.59 | M11: =IFERROR(SUMIF('Outstanding_NOV-2025'!$D$19:$D$502,$A11,'Outstanding_NOV-2025'!$G$19:$G$502),0) -> 18398.82
A12: ashik | B12: =IFERROR(__xludf.DUMMYFUNCTION("IF(COUNTA(C12:M12)=0,"""",SPARKLINE(C12:M12,{""charttype"",""line"";""linewidth"",2}))"),"") | C12: =IFERROR(SUMIF('Outstanding_JAN-2025'!$D$19:$D$502,$A12,'Outstanding_JAN-2025'!$G$19:$G$502),0) -> 3674.58 | D12: =IFERROR(SUMIF('Outstanding_FEB-2025'!$D$19:$D$502,$A12,'Outstanding_FEB-2025'!$G$19:$G$502),0) -> 3500.62 | E12: =IFERROR(SUMIF('Outstanding_MAR-2025'!$D$19:$D$502,$A12,'Outstanding_MAR-2025'!$G$19:$G$502),0) -> 3408.64 | F12: =IFERROR(SUMIF('Outstanding_APR-2025'!$D$19:$D$502,$A12,'Outstanding_APR-2025'!$G$19:$G$502),0) -> 4062.21 | G12: =IFERROR(SUMIF('Outstanding_MAY-2025'!$D$19:$D$502,$A12,'Outstanding_MAY-2025'!$G$19:$G$502),0) -> 15556.35 | H12: =IFERROR(SUMIF('Outstanding_JUN-2025'!$D$19:$D$502,$A12,'Outstanding_JUN-2025'!$G$19:$G$502),0) -> 13950.79 | I12: =IFERROR(SUMIF('Outstanding_JUL-2025'!$D$19:$D$502,$A12,'Outstanding_JUL-2025'!$G$19:$G$502),0) -> 16876.6 | J12: =IFERROR(SUMIF('Outstanding_AUG-2025'!$D$19:$D$502,$A12,'Outstanding_AUG-2025'!$G$19:$G$502),0) -> 14387.17 | K12: =IFERROR(SUMIF('Outstanding_SEP-2025'!$D$19:$D$502,$A12,'Outstanding_SEP-2025'!$G$19:$G$502),0) -> 15423.13 | L12: =IFERROR(SUMIF('Outstanding_OCT-2025'!$D$19:$D$502,$A12,'Outstanding_OCT-2025'!$G$19:$G$502),0) -> 27926.05 | M12: =IFERROR(SUMIF('Outstanding_NOV-2025'!$D$19:$D$502,$A12,'Outstanding_NOV-2025'!$G$19:$G$502),0) -> 17807.28
A13: dhiya | B13: =IFERROR(__xludf.DUMMYFUNCTION("IF(COUNTA(C13:M13)=0,"""",SPARKLINE(C13:M13,{""charttype"",""line"";""linewidth"",2}))"),"") | C13: =IFERROR(SUMIF('Outstanding_JAN-2025'!$D$19:$D$502,$A13,'Outstanding_JAN-2025'!$G$19:$G$502),0) -> 237083.08 | D13: =IFERROR(SUMIF('Outstanding_FEB-2025'!$D$19:$D$502,$A13,'Outstanding_FEB-2025'!$G$19:$G$502),0) -> 228497.88 | E13: =IFERROR(SUMIF('Outstanding_MAR-2025'!$D$19:$D$502,$A13,'Outstanding_MAR-2025'!$G$19:$G$502),0) -> 231169.37 | F13: =IFERROR(SUMIF('Outstanding_APR-2025'!$D$19:$D$502,$A13,'Outstanding_APR-2025'!$G$19:$G$502),0) -> 264736.23 | G13: =IFERROR(SUMIF('Outstanding_MAY-2025'!$D$19:$D$502,$A13,'Outstanding_MAY-2025'!$G$19:$G$502),0) -> 248652.07 | H13: =IFERROR(SUMIF('Outstanding_JUN-2025'!$D$19:$D$502,$A13,'Outstanding_JUN-2025'!$G$19:$G$502),0) -> 229073.43 | I13: =IFERROR(SUMIF('Outstanding_JUL-2025'!$D$19:$D$502,$A13,'Outstanding_JUL-2025'!$G$19:$G$502),0) -> 214810.77 | J13: =IFERROR(SUMIF('Outstanding_AUG-2025'!$D$19:$D$502,$A13,'Outstanding_AUG-2025'!$G$19:$G$502),0) -> 250098.41 | K13: =IFERROR(SUMIF('Outstanding_SEP-2025'!$D$19:$D$502,$A13,'Outstanding_SEP-2025'!$G$19:$G$502),0) -> 235777.05 | L13: =IFERROR(SUMIF('Outstanding_OCT-2025'!$D$19:$D$502,$A13,'Outstanding_OCT-2025'!$G$19:$G$502),0) -> 245613.5 | M13: =IFERROR(SUMIF('Outstanding_NOV-2025'!$D$19:$D$502,$A13,'Outstanding_NOV-2025'!$G$19:$G$502),0) -> 270754.61
A14: khalid | B14: =IFERROR(__xludf.DUMMYFUNCTION("IF(COUNTA(C14:M14)=0,"""",SPARKLINE(C14:M14,{""charttype"",""line"";""linewidth"",2}))"),"") | C14: =IFERROR(SUMIF('Outstanding_JAN-2025'!$D$19:$D$502,$A14,'Outstanding_JAN-2025'!$G$19:$G$502),0) -> 55184.18 | D14: =IFERROR(SUMIF('Outstanding_FEB-2025'!$D$19:$D$502,$A14,'Outstanding_FEB-2025'!$G$19:$G$502),0) -> 57646.36 | E14: =IFERROR(SUMIF('Outstanding_MAR-2025'!$D$19:$D$502,$A14,'Outstanding_MAR-2025'!$G$19:$G$502),0) -> 49421.1 | F14: =IFERROR(SUMIF('Outstanding_APR-2025'!$D$19:$D$502,$A14,'Outstanding_APR-2025'!$G$19:$G$502),0) -> 65418.65 | G14: =IFERROR(SUMIF('Outstanding_MAY-2025'!$D$19:$D$502,$A14,'Outstanding_MAY-2025'!$G$19:$G$502),0) -> 72741.9 | H14: =IFERROR(SUMIF('Outstanding_JUN-2025'!$D$19:$D$502,$A14,'Outstanding_JUN-2025'!$G$19:$G$502),0) -> 81121.23 | I14: =IFERROR(SUMIF('Outstanding_JUL-2025'!$D$19:$D$502,$A14,'Outstanding_JUL-2025'!$G$19:$G$502),0) -> 88733.24 | J14: =IFERROR(SUMIF('Outstanding_AUG-2025'!$D$19:$D$502,$A14,'Outstanding_AUG-2025'!$G$19:$G$502),0) -> 88782.28 | K14: =IFERROR(SUMIF('Outstanding_SEP-2025'!$D$19:$D$502,$A14,'Outstanding_SEP-2025'!$G$19:$G$502),0) -> 85162.44 | L14: =IFERROR(SUMIF('Outstanding_OCT-2025'!$D$19:$D$502,$A14,'Outstanding_OCT-2025'!$G$19:$G$502),0) -> 99007.14 | M14: =IFERROR(SUMIF('Outstanding_NOV-2025'!$D$19:$D$502,$A14,'Outstanding_NOV-2025'!$G$19:$G$502),0) -> 89837.02
A15: shabeer | B15: =IFERROR(__xludf.DUMMYFUNCTION("IF(COUNTA(C15:M15)=0,"""",SPARKLINE(C15:M15,{""charttype"",""line"";""linewidth"",2}))"),"") | C15: =IFERROR(SUMIF('Outstanding_JAN-2025'!$D$19:$D$502,$A15,'Outstanding_JAN-2025'!$G$19:$G$502),0) -> 0 | D15: =IFERROR(SUMIF('Outstanding_FEB-2025'!$D$19:$D$502,$A15,'Outstanding_FEB-2025'!$G$19:$G$502),0) -> 0 | E15: =IFERROR(SUMIF('Outstanding_MAR-2025'!$D$19:$D$502,$A15,'Outstanding_MAR-2025'!$G$19:$G$502),0) -> 0 | F15: =IFERROR(SUMIF('Outstanding_APR-2025'!$D$19:$D$502,$A15,'Outstanding_APR-2025'!$G$19:$G$502),0) -> 0 | G15: =IFERROR(SUMIF('Outstanding_MAY-2025'!$D$19:$D$502,$A15,'Outstanding_MAY-2025'!$G$19:$G$502),0) -> 0 | H15: =IFERROR(SUMIF('Outstanding_JUN-2025'!$D$19:$D$502,$A15,'Outstanding_JUN-2025'!$G$19:$G$502),0) -> 0 | I15: =IFERROR(SUMIF('Outstanding_JUL-2025'!$D$19:$D$502,$A15,'Outstanding_JUL-2025'!$G$19:$G$502),0) -> 0 | J15: =IFERROR(SUMIF('Outstanding_AUG-2025'!$D$19:$D$502,$A15,'Outstanding_AUG-2025'!$G$19:$G$502),0) -> 0 | K15: =IFERROR(SUMIF('Outstanding_SEP-2025'!$D$19:$D$502,$A15,'Outstanding_SEP-2025'!$G$19:$G$502),0) -> 0 | L15: =IFERROR(SUMIF('Outstanding_OCT-2025'!$D$19:$D$502,$A15,'Outstanding_OCT-2025'!$G$19:$G$502),0) -> 0 | M15: =IFERROR(SUMIF('Outstanding_NOV-2025'!$D$19:$D$502,$A15,'Outstanding_NOV-2025'!$G$19:$G$502),0) -> 0
A16: al ahsa-4 | B16: =IFERROR(__xludf.DUMMYFUNCTION("IF(COUNTA(C16:M16)=0,"""",SPARKLINE(C16:M16,{""charttype"",""line"";""linewidth"",2}))"),"") | C16: =IFERROR(SUMIF('Outstanding_JAN-2025'!$D$19:$D$502,$A16,'Outstanding_JAN-2025'!$G$19:$G$502),0) -> 0 | D16: =IFERROR(SUMIF('Outstanding_FEB-2025'!$D$19:$D$502,$A16,'Outstanding_FEB-2025'!$G$19:$G$502),0) -> 0 | E16: =IFERROR(SUMIF('Outstanding_MAR-2025'!$D$19:$D$502,$A16,'Outstanding_MAR-2025'!$G$19:$G$502),0) -> 0 | F16: =IFERROR(SUMIF('Outstanding_APR-2025'!$D$19:$D$502,$A16,'Outstanding_APR-2025'!$G$19:$G$502),0) -> 0 | G16: =IFERROR(SUMIF('Outstanding_MAY-2025'!$D$19:$D$502,$A16,'Outstanding_MAY-2025'!$G$19:$G$502),0) -> 0 | H16: =IFERROR(SUMIF('Outstanding_JUN-2025'!$D$19:$D$502,$A16,'Outstanding_JUN-2025'!$G$19:$G$502),0) -> 0 | I16: =IFERROR(SUMIF('Outstanding_JUL-2025'!$D$19:$D$502,$A16,'Outstanding_JUL-2025'!$G$19:$G$502),0) -> 0 | J16: =IFERROR(SUMIF('Outstanding_AUG-2025'!$D$19:$D$502,$A16,'Outstanding_AUG-2025'!$G$19:$G$502),0) -> 0 | K16: =IFERROR(SUMIF('Outstanding_SEP-2025'!$D$19:$D$502,$A16,'Outstanding_SEP-2025'!$G$19:$G$502),0) -> 0 | L16: =IFERROR(SUMIF('Outstanding_OCT-2025'!$D$19:$D$502,$A16,'Outstanding_OCT-2025'!$G$19:$G$502),0) -> 0 | M16: =IFERROR(SUMIF('Outstanding_NOV-2025'!$D$19:$D$502,$A16,'Outstanding_NOV-2025'!$G$19:$G$502),0) -> 20589.67
A17: samir dmm | B17: =IFERROR(__xludf.DUMMYFUNCTION("IF(COUNTA(C17:M17)=0,"""",SPARKLINE(C17:M17,{""charttype"",""line"";""linewidth"",2}))"),"") | C17: =IFERROR(SUMIF('Outstanding_JAN-2025'!$D$19:$D$502,$A17,'Outstanding_JAN-2025'!$G$19:$G$502),0) -> 0 | D17: =IFERROR(SUMIF('Outstanding_FEB-2025'!$D$19:$D$502,$A17,'Outstanding_FEB-2025'!$G$19:$G$502),0) -> 0 | E17: =IFERROR(SUMIF('Outstanding_MAR-2025'!$D$19:$D$502,$A17,'Outstanding_MAR-2025'!$G$19:$G$502),0) -> 0 | F17: =IFERROR(SUMIF('Outstanding_APR-2025'!$D$19:$D$502,$A17,'Outstanding_APR-2025'!$G$19:$G$502),0) -> 0 | G17: =IFERROR(SUMIF('Outstanding_MAY-2025'!$D$19:$D$502,$A17,'Outstanding_MAY-2025'!$G$19:$G$502),0) -> 0 | H17: =IFERROR(SUMIF('Outstanding_JUN-2025'!$D$19:$D$502,$A17,'Outstanding_JUN-2025'!$G$19:$G$502),0) -> 0 | I17: =IFERROR(SUMIF('Outstanding_JUL-2025'!$D$19:$D$502,$A17,'Outstanding_JUL-2025'!$G$19:$G$502),0) -> 0 | J17: =IFERROR(SUMIF('Outstanding_AUG-2025'!$D$19:$D$502,$A17,'Outstanding_AUG-2025'!$G$19:$G$502),0) -> 0 | K17: =IFERROR(SUMIF('Outstanding_SEP-2025'!$D$19:$D$502,$A17,'Outstanding_SEP-2025'!$G$19:$G$502),0) -> 0 | L17: =IFERROR(SUMIF('Outstanding_OCT-2025'!$D$19:$D$502,$A17,'Outstanding_OCT-2025'!$G$19:$G$502),0) -> 0 | M17: =IFERROR(SUMIF('Outstanding_NOV-2025'!$D$19:$D$502,$A17,'Outstanding_NOV-2025'!$G$19:$G$502),0) -> 30912.4
A18: shareef | B18: =IFERROR(__xludf.DUMMYFUNCTION("IF(COUNTA(C18:M18)=0,"""",SPARKLINE(C18:M18,{""charttype"",""line"";""linewidth"",2}))"),"") | C18: =IFERROR(SUMIF('Outstanding_JAN-2025'!$D$19:$D$502,$A18,'Outstanding_JAN-2025'!$G$19:$G$502),0) -> 0 | D18: =IFERROR(SUMIF('Outstanding_FEB-2025'!$D$19:$D$502,$A18,'Outstanding_FEB-2025'!$G$19:$G$502),0) -> 0 | E18: =IFERROR(SUMIF('Outstanding_MAR-2025'!$D$19:$D$502,$A18,'Outstanding_MAR-2025'!$G$19:$G$502),0) -> 0 | F18: =IFERROR(SUMIF('Outstanding_APR-2025'!$D$19:$D$502,$A18,'Outstanding_APR-2025'!$G$19:$G$502),0) -> 4990.26 | G18: =IFERROR(SUMIF('Outstanding_MAY-2025'!$D$19:$D$502,$A18,'Outstanding_MAY-2025'!$G$19:$G$502),0) -> 4366.48 | H18: =IFERROR(SUMIF('Outstanding_JUN-2025'!$D$19:$D$502,$A18,'Outstanding_JUN-2025'!$G$19:$G$502),0) -> 4366.48 | I18: =IFERROR(SUMIF('Outstanding_JUL-2025'!$D$19:$D$502,$A18,'Outstanding_JUL-2025'!$G$19:$G$502),0) -> 4366.48 | J18: =IFERROR(SUMIF('Outstanding_AUG-2025'!$D$19:$D$502,$A18,'Outstanding_AUG-2025'!$G$19:$G$502),0) -> 4257.5 | K18: =IFERROR(SUMIF('Outstanding_SEP-2025'!$D$19:$D$502,$A18,'Outstanding_SEP-2025'!$G$19:$G$502),0) -> 0 | L18: =IFERROR(SUMIF('Outstanding_OCT-2025'!$D$19:$D$502,$A18,'Outstanding_OCT-2025'!$G$19:$G$502),0) -> 0 | M18: =IFERROR(SUMIF('Outstanding_NOV-2025'!$D$19:$D$502,$A18,'Outstanding_NOV-2025'!$G$19:$G$502),0) -> 4257.5
A19: samir | B19: =IFERROR(__xludf.DUMMYFUNCTION("IF(COUNTA(C19:M19)=0,"""",SPARKLINE(C19:M19,{""charttype"",""line"";""linewidth"",2}))"),"") | C19: =IFERROR(SUMIF('Outstanding_JAN-2025'!$D$19:$D$502,$A19,'Outstanding_JAN-2025'!$G$19:$G$502),0) -> 4863 | D19: =IFERROR(SUMIF('Outstanding_FEB-2025'!$D$19:$D$502,$A19,'Outstanding_FEB-2025'!$G$19:$G$502),0) -> 11134.02 | E19: =IFERROR(SUMIF('Outstanding_MAR-2025'!$D$19:$D$502,$A19,'Outstanding_MAR-2025'!$G$19:$G$502),0) -> 6051.96 | F19: =IFERROR(SUMIF('Outstanding_APR-2025'!$D$19:$D$502,$A19,'Outstanding_APR-2025'!$G$19:$G$502),0) -> 5859.02 | G19: =IFERROR(SUMIF('Outstanding_MAY-2025'!$D$19:$D$502,$A19,'Outstanding_MAY-2025'!$G$19:$G$502),0) -> 3245 | H19: =IFERROR(SUMIF('Outstanding_JUN-2025'!$D$19:$D$502,$A19,'Outstanding_JUN-2025'!$G$19:$G$502),0) -> 3046 | I19: =IFERROR(SUMIF('Outstanding_JUL-2025'!$D$19:$D$502,$A19,'Outstanding_JUL-2025'!$G$19:$G$502),0) -> 8916.95 | J19: =IFERROR(SUMIF('Outstanding_AUG-2025'!$D$19:$D$502,$A19,'Outstanding_AUG-2025'!$G$19:$G$502),0) -> 12195.64 | K19: =IFERROR(SUMIF('Outstanding_SEP-2025'!$D$19:$D$502,$A19,'Outstanding_SEP-2025'!$G$19:$G$502),0) -> 5260 | L19: =IFERROR(SUMIF('Outstanding_OCT-2025'!$D$19:$D$502,$A19,'Outstanding_OCT-2025'!$G$19:$G$502),0) -> 9086.56 | M19: =IFERROR(SUMIF('Outstanding_NOV-2025'!$D$19:$D$502,$A19,'Outstanding_NOV-2025'!$G$19:$G$502),0) -> 15016.49
A20: TOTAL | B20: =IFERROR(__xludf.DUMMYFUNCTION("IF(COUNTA(C20:M20)=0,"""",SPARKLINE(C20:M20,{""charttype"",""line"";""linewidth"",2}))"),"") | C20: =SUM(C4:C19) -> 1795869.5 | D20: =SUM(D4:D19) -> 1589925.6 | E20: =SUM(E4:E19) -> 1507837.2 | F20: =SUM(F4:F19) -> 1716100.2 | G20: =SUM(G4:G19) -> 2287954.2 | H20: =SUM(H4:H19) -> 2189458.7 | I20: =SUM(I4:I19) -> 2399787.8 | J20: =SUM(J4:J19) -> 2026772.4 | ... M20: =SUM(M4:M19) -> 2179683.5
A21: MoM Δ (TOTAL) | D21: =IF(C20="","",IFERROR(IF(D20=C20,"—",IF(D20>C20,"▲ +"&TEXT((D20-C20)/C20,"0.0%"),"▼ -"&TEXT(ABS((D20-C20)/C20),"0.0%"))),"")) -> ▼ -11.5% | E21: =IF(D20="","",IFERROR(IF(E20=D20,"—",IF(E20>D20,"▲ +"&TEXT((E20-D20)/D20,"0.0%"),"▼ -"&TEXT(ABS((E20-D20)/D20),"0.0%"))),"")) -> ▼ -5.2% | F21: =IF(E20="","",IFERROR(IF(F20=E20,"—",IF(F20>E20,"▲ +"&TEXT((F20-E20)/E20,"0.0%"),"▼ -"&TEXT(ABS((F20-E20)/E20),"0.0%"))),"")) -> ▲ +13.8% | G21: =IF(F20="","",IFERROR(IF(G20=F20,"—",IF(G20>F20,"▲ +"&TEXT((G20-F20)/F20,"0.0%"),"▼ -"&TEXT(ABS((G20-F20)/F20),"0.0%"))),"")) -> ▲ +33.3% | H21: =IF(G20="","",IFERROR(IF(H20=G20,"—",IF(H20>G20,"▲ +"&TEXT((H20-G20)/G20,"0.0%"),"▼ -"&TEXT(ABS((H20-G20)/G20),"0.0%"))),"")) -> ▼ -4.3% | I21: =IF(H20="","",IFERROR(IF(I20=H20,"—",IF(I20>H20,"▲ +"&TEXT((I20-H20)/H20,"0.0%"),"▼ -"&TEXT(ABS((I20-H20)/H20),"0.0%"))),"")) -> ▲ +9.6% | J21: =IF(I20="","",IFERROR(IF(J20=I20,"—",IF(J20>I20,"▲ +"&TEXT((J20-I20)/I20,"0.0%"),"▼ -"&TEXT(ABS((J20-I20)/I20),"0.0%"))),"")) -> ▼ -15.5% | K21: =IF(J20="","",IFERROR(IF(K20=J20,"—",IF(K20>J20,"▲ +"&TEXT((K20-J20)/J20,"0.0%"),"▼ -"&TEXT(ABS((K20-J20)/J20),"0.0%"))),"")) -> ▼ -0.1% | ... M21: =IF(L20="","",IFERROR(IF(M20=L20,"—",IF(M20>L20,"▲ +"&TEXT((M20-L20)/L20,"0.0%"),"▼ -"&TEXT(ABS((M20-L20)/L20),"0.0%"))),"")) -> ▲ +5.7%

Sheet Settings
A1: SYSTEM SETTINGS & CONFIGURATION
A3: INSTRUCTIONS FOR USE
A4: 1. Add new months using the menu: Monthly Reports > Add New Month
A5: 2. Update data in the current month sheets (Banks, Advances, Suspense, Outstanding)
A6: 3. View comparison reports and dashboard to track trends
A7: 4. Edit the master lists below to customize dropdowns in all sheets
A8: 5. Use "Fix Dropdowns" menu item after editing lists to update all sheets
A12: MASTER LISTS
A14: BANKS | C14: SALESMEN | E14: AREAS
A15: Alrajhi-1097 | C15: nidheesh | E15: Al Ahsa Wholesale
A16: Alrajhi-new | C16: jaseel | E16: Riyadh
A17: SNB Al Ahsa Branch | C17: bassam | E17: Dammam wholesale
A18: Albilad USD | C18: akmal | E18: Company Direct Sales
C19: arshad | E19: Dammam Retail
C20: Shameer riyadh | E20: Al Ahsa-2
C21: company sales | E21: Al Ahsa-3
C22: shafi | E22: Al Ahsa-1
C23: ashik | E23: Hafar Al Batin
C24: dhiya | E24: Qaseem
C25: khalid | E25: Dammam Retail-2
C26: shabeer
C27: al ahsa-4
C28: samir dmm
C29: shareef
C30: samir
A31: Version:
A32: SYSTEM INFORMATION
A33: SYSTEM INFORMATION
A34: Version:
A35: Last Updated: | B35: 45895.652 | D35: SUSPENSE Base (Jan) | E35: -17267.64
A36: Created By: | B36: 45896.128 | D36: SUSPENSE Base (Jan) | E36: -17267.64
A37: Created By: | B37: Account Department
D38: ADVANCES Base (Jan) | E38: 163800.84

Sheet Banks_NOV-2025
A1: BANK SUMMARY - NOV-2025
A3: Bank Name | B3: Opening Balance | C3: Total Received | D3: Bank Charges | E3: Total Payments | F3: Closing Balance | G3: Notes
A4: Alrajhi-1097 | B4: 210693.67 | F4: =B4+C4-D4-E4 -> 210693.67
A5: Alrajhi-new | B5: 564500.97 | F5: =B5+C5-D5-E5 -> 564500.97
A6: SNB Al Ahsa Branch | B6: 1562570.6 | F6: =B6+C6-D6-E6 -> 1562570.6
A7: Albilad | B7: 160054.48 | F7: =B7+C7-D7-E7 -> 160054.48
A9: SUB-TOTAL SAR | B9: =SUM(B4:B7) -> 2497819.7 | C9: =SUM(C4:C7) -> 0 | D9: =SUM(D4:D7) -> 0 | E9: =SUM(E4:E7) -> 0 | F9: =SUM(F4:F7) -> 2497819.7
A11: USD ACCOUNTS
A12: Bank Name | B12: Opening | C12: Amount Received | D12: Bank Charge | E12: Payment | F12: Balance | G12: Notes
A13: Albilad USD | B13: 133.57 | F13: =B13+C13-D13-E13 -> 133.57
A15: SUB-TOTAL USD | B15: =SUM(B13) -> 133.57 | C15: =SUM(C13) -> 0 | D15: =SUM(D13) -> 0 | E15: =SUM(E13) -> 0 | F15: =SUM(F13) -> 133.57
A17: GRAND TOTAL (SAR + USD Converted) | B17: =B9+B15*3.75 -> 2498320.6 | C17: =C9+C15*3.75 -> 0 | D17: =D9+D15*3.75 -> 0 | E17: =E9+E15*3.75 -> 0 | F17: =F9+F15*3.75 -> 2498320.6
A19: SUMMARY
A20: Total Bank Balance (SAR): | C20: =F17 -> 2498320.6

Sheet Advances_NOV-2025
A1: ADVANCE RECONCILIATION - NOV-2025
A3: OPENING BALANCE | B3: 540959.39 | D3: CLOSING BALANCE | E3: =0+SUM(E7:E1000) -> #REF!
A5: TRANSACTIONS
A6: Date | B6: Voucher No | C6: Description | D6: Person/Party | E6: Advance Given | F6: Amount Settled | G6: Running Balance
G7: =IF(E7="","",B3+E7-F7)
G8: =IF(E8="","",G7+E8-F8)
G9: =IF(E9="","",G8+E9-F9)
G10: =IF(E10="","",G9+E10-F10)
G11: =IF(E11="","",G10+E11-F11)
G12: =IF(E12="","",G11+E12-F12)
G13: =IF(E13="","",G12+E13-F13)
G14: =IF(E14="","",G13+E14-F14)
G15: =IF(E15="","",G14+E15-F15)
G16: =IF(E16="","",G15+E16-F16)
G17: =IF(E17="","",G16+E17-F17)
G18: =IF(E18="","",G17+E18-F18)
G19: =IF(E19="","",G18+E19-F19)
... G100: =IF(E100="","",G99+E100-F100)
A102: TOTAL | E102: =SUM(E7:E1000) -> #REF! | F102: =SUM(F7:F1000) -> #REF!

Sheet Suspense_NOV-2025
A1: SUSPENSE RECONCILIATION - NOV-2025
A3: OPENING BALANCE | B3: -186506.88 | D3: CLOSING BALANCE | E3: =0+SUM(E7:E1000)-SUM(F7:F1000) -> #REF!
A5: UNIDENTIFIED TRANSACTIONS
A6: Date | B6: Journal No | C6: Description | D6: Reference | E6: Debit | F6: Credit | G6: Running Balance
G7: =IF(AND(E7="",F7=""),"",B3+E7-F7)
G8: =IF(AND(E8="",F8=""),"",G7+E8-F8)
G9: =IF(AND(E9="",F9=""),"",G8+E9-F9)
G10: =IF(AND(E10="",F10=""),"",G9+E10-F10)
G11: =IF(AND(E11="",F11=""),"",G10+E11-F11)
G12: =IF(AND(E12="",F12=""),"",G11+E12-F12)
G13: =IF(AND(E13="",F13=""),"",G12+E13-F13)
G14: =IF(AND(E14="",F14=""),"",G13+E14-F14)
G15: =IF(AND(E15="",F15=""),"",G14+E15-F15)
G16: =IF(AND(E16="",F16=""),"",G15+E16-F16)
G17: =IF(AND(E17="",F17=""),"",G16+E17-F17)
G18: =IF(AND(E18="",F18=""),"",G17+E18-F18)
G19: =IF(AND(E19="",F19=""),"",G18+E19-F19)
... G100: =IF(AND(E100="",F100=""),"",G99+E100-F100)
A102: TOTAL | E102: =SUM(E7:E1000) -> #REF! | F102: =SUM(F7:F1000) -> #REF!

Sheet Outstanding_NOV-2025
A1: CUSTOMER OUTSTANDING - NOV-2025
A3: Salesman | B3: Total Outstanding | C3: No. of Customers | D3: Average
A4: nidheesh | B4: =SUMIF($D$23:$D$502,A4,$G$23:$G$502) -> 79345.24 | C4: =COUNTIF($D$23:$D$502,A4) -> 54 | D4: =IFERROR(B4/C4,0) -> 1469.3563
A5: jaseel | B5: =SUMIF($D$23:$D$502,A5,$G$23:$G$502) -> 19951.36 | C5: =COUNTIF($D$23:$D$502,A5) -> 17 | D5: =IFERROR(B5/C5,0) -> 1173.6094
A6: bassam | B6: =SUMIF($D$23:$D$502,A6,$G$23:$G$502) -> 22733.87 | C6: =COUNTIF($D$23:$D$502,A6) -> 15 | D6: =IFERROR(B6/C6,0) -> 1515.5913
A7: akmal | B7: =SUMIF($D$23:$D$502,A7,$G$23:$G$502) -> 34121.05 | C7: =COUNTIF($D$23:$D$502,A7) -> 14 | D7: =IFERROR(B7/C7,0) -> 2437.2179
A8: arshad | B8: =SUMIF($D$23:$D$502,A8,$G$23:$G$502) -> 486637.4 | C8: =COUNTIF($D$23:$D$502,A8) -> 26 | D8: =IFERROR(B8/C8,0) -> 18716.823
A9: Shameer riyadh | B9: =SUMIF($D$23:$D$502,A9,$G$23:$G$502) -> 92907.92 | C9: =COUNTIF($D$23:$D$502,A9) -> 61 | D9: =IFERROR(B9/C9,0) -> 1523.0807
A10: company sales | B10: =SUMIF($D$23:$D$502,A10,$G$23:$G$502) -> 976412.87 | C10: =COUNTIF($D$23:$D$502,A10) -> 15 | D10: =IFERROR(B10/C10,0) -> 65094.191
A11: shafi | B11: =SUMIF($D$23:$D$502,A11,$G$23:$G$502) -> 18398.82 | C11: =COUNTIF($D$23:$D$502,A11) -> 35 | D11: =IFERROR(B11/C11,0) -> 525.68057
A12: ashik | B12: =SUMIF($D$23:$D$502,A12,$G$23:$G$502) -> 17807.28 | C12: =COUNTIF($D$23:$D$502,A12) -> 26 | D12: =IFERROR(B12/C12,0) -> 684.89538
A13: dhiya | B13: =SUMIF($D$23:$D$502,A13,$G$23:$G$502) -> 270754.61 | C13: =COUNTIF($D$23:$D$502,A13) -> 21 | D13: =IFERROR(B13/C13,0) -> 12893.077
A14: khalid | B14: =SUMIF($D$23:$D$502,A14,$G$23:$G$502) -> 89837.02 | C14: =COUNTIF($D$23:$D$502,A14) -> 112 | D14: =IFERROR(B14/C14,0) -> 802.11625
A15: shabeer | B15: =SUMIF($D$23:$D$502,A15,$G$23:$G$502) -> 0 | C15: =COUNTIF($D$23:$D$502,A15) -> 0 | D15: =IFERROR(B15/C15,0) -> 0
... A18: shareef | B18: =SUMIF($D$23:$D$502,A18,$G$23:$G$502) -> 4257.5 | C18: =COUNTIF($D$23:$D$502,A18) -> 17 | D18: =IFERROR(B18/C18,0) -> 250.44118
A19: samir | B19: =SUMIF($D$23:$D$502,A19,$G$23:$G$502) -> 15016.49 | C19: =COUNTIF($D$23:$D$502,A19) -> 9 | D19: =IFERROR(B23/C19,0) -> 0
A20: TOTAL | B20: =SUM(B4:B19) -> 2179683.5 | C20: =SUM(C4:C19) -> 441 | D20: =IFERROR(B23/C20,0) -> 0
A22: Customer Code | B22: Customer Name | C22: Area | D22: Salesman | E22: Invoice Amount | F22: Paid Amount | G22: Balance | H22: Days
A23: CUST63 | B23: Saudi marketting | C23: Al Ahsa-1 | D23: jaseel | E23: 1019.82 | G23: =IF(E23="","",E23-F23) -> 1019.82
A24: CUST84 | B24: Najmath AL khayrath | C24: Al Ahsa-1 | D24: jaseel | E24: 1939.7 | G24: =IF(E24="","",E24-F24) -> 1939.7
A25: CUST163 | B25: Al sahla oasis groceri for foodstuff | C25: Al Ahsa-1 | D25: jaseel | E25: 192.96 | G25: =IF(E25="","",E25-F25) -> 192.96
A26: CUST204 | B26: Thamveenath Noorul usam | C26: Al Ahsa-1 | D26: jaseel | E26: 1460.78 | G26: =IF(E26="","",E26-F26) -> 1460.78
A27: CUST561 | B27: Grocery naster | C27: Al Ahsa-1 | D27: jaseel | E27: 284.96 | G27: =IF(E27="","",E27-F27) -> 284.96
A28: CUST1482 | B28: Wahab Al khaleej 2 | C28: Al Ahsa-1 | D28: jaseel | E28: 917.88 | G28: =IF(E28="","",E28-F28) -> 917.88
A29: CUST1999 | B29: Zone mart (j) | C29: Al Ahsa-1 | D29: jaseel | E29: 1201.86 | G29: =IF(E29="","",E29-F29) -> 1201.86
A30: CUST2141 | B30: Al Qafila al khalijiyyah supermarket | C30: Al Ahsa-1 | D30: jaseel | E30: 1257.81 | G30: =IF(E30="","",E30-F30) -> 1257.81
A31: CUST2237 | B31: Ghaith al safat food supplies | C31: Al Ahsa-1 | D31: jaseel | E31: 2567.63 | G31: =IF(E31="","",E31-F31) -> 2567.63
A32: CUST2326 | B32: Al Zahra (umm | C32: Al Ahsa-1 | D32: jaseel | E32: 1584.79 | G32: =IF(E32="","",E32-F32) -> 1584.79
A33: CUST2446 | B33: Durrat alshakhs foodstuff supplies | C33: Al Ahsa-1 | D33: jaseel | E33: 600 | G33: =IF(E33="","",E33-F33) -> 600
A34: CUST2493 | B34: Kayf al alha market | C34: Al Ahsa-1 | D34: jaseel | E34: 2569.55 | G34: =IF(E34="","",E34-F34) -> 2569.55
... A463: CUST6225 | B463: Amazon saudi Trading CO (al Azeeziya) | C463: Hafar Al Batin | D463: samir dmm | E463: 8503.9 | G463: =IF(E463="","",E463-F463) -> 8503.9
G464: =IF(E464="","",E464-F464)
G465: =IF(E465="","",E465-F465)
G466: =IF(E466="","",E466-F466)
G467: =IF(E467="","",E467-F467)
G468: =IF(E468="","",E468-F468)
G469: =IF(E469="","",E469-F469)
G470: =IF(E470="","",E470-F470)
G471: =IF(E471="","",E471-F471)
G472: =IF(E472="","",E472-F472)
G473: =IF(E473="","",E473-F473)
G474: =IF(E474="","",E474-F474)
G475: =IF(E475="","",E475-F475)
... G502: =IF(E502="","",E502-F502)
A503: GRAND TOTAL | E503: =SUM(E23:E502) -> 2179683.5 | F503: =SUM(F23:F502) -> 0 | G503: =SUM(G23:G502) -> 2179683.5

Sheet Banks_SEP-2025
A1: BANK SUMMARY - SEP-2025
A3: Bank Name | B3: Opening Balance | C3: Total Received | D3: Bank Charges | E3: Total Payments | F3: Closing Balance | G3: Notes
A4: Alrajhi-1097 | B4: 730511.72 | C4: 534244.8 | D4: 3574.6 | E4: 50288.93 | F4: =B4+C4-D4-E4 -> 1210893
A5: Alrajhi-new | B5: 613561.62 | C5: 415787.99 | D5: 0 | E5: 0 | F5: =B5+C5-D5-E5 -> 1029349.6
A6: SNB Al Ahsa Branch | B6: 770824.04 | C6: 474609.66 | D6: 345 | E6: 0 | F6: =B6+C6-D6-E6 -> 1245088.7
A7: Albilad | B7: 333879.5 | C7: 806860 | D7: 126.5 | E7: 787076.93 | F7: =B7+C7-D7-E7 -> 353536.07
A9: SUB-TOTAL SAR | B9: =SUM(B4:B7) -> 2448776.9 | C9: =SUM(C4:C7) -> 2231502.5 | D9: =SUM(D4:D7) -> 4046.1 | E9: =SUM(E4:E7) -> 837365.86 | F9: =SUM(F4:F7) -> 3838867.4
A11: USD ACCOUNTS
A12: Bank Name | B12: Opening | C12: Amount Received | D12: Bank Charge | E12: Payment | F12: Balance | G12: Notes
A13: Albilad USD | B13: 423.48 | C13: 13303.18 | E13: 10674.33 | F13: =B13+C13-D13-E13 -> 3052.33
A15: SUB-TOTAL USD | B15: =SUM(B13) -> 423.48 | C15: =SUM(C13) -> 13303.18 | D15: =SUM(D13) -> 0 | E15: =SUM(E13) -> 10674.33 | F15: =SUM(F13) -> 3052.33
A17: GRAND TOTAL (SAR + USD Converted) | B17: =B9+B15*3.75 -> 2450364.9 | C17: =C9+C15*3.75 -> 2281389.4 | D17: =D9+D15*3.75 -> 4046.1 | E17: =E9+E15*3.75 -> 877394.6 | F17: =F9+F15*3.75 -> 3850313.6
A19: SUMMARY
A20: Total Bank Balance (SAR): | C20: =F17 -> 3850313.6

Sheet Banks_OCT-2025
A1: BANK SUMMARY - OCT-2025
A3: Bank Name | B3: Opening Balance | C3: Total Received | D3: Bank Charges | E3: Total Payments | F3: Closing Balance | G3: Notes
A4: Alrajhi-1097 | B4: 1210893 | C4: 703586.3 | D4: 3838.82 | E4: 1699946.8 | F4: =B4+C4-D4-E4 -> 210693.67
A5: Alrajhi-new | B5: 1029349.6 | C5: 538084.41 | D5: 8.05 | E5: 1002925 | F5: =B5+C5-D5-E5 -> 564500.97
A6: SNB Al Ahsa Branch | B6: 1245088.7 | C6: 717855.66 | D6: 373.75 | E6: 400000 | F6: =B6+C6-D6-E6 -> 1562570.6
A7: Albilad | B7: 353536.07 | C7: 2429125 | D7: 109.25 | E7: 2622497.3 | F7: =B7+C7-D7-E7 -> 160054.48
A9: SUB-TOTAL SAR | B9: =SUM(B4:B7) -> 3838867.4 | C9: =SUM(C4:C7) -> 4388651.4 | D9: =SUM(D4:D7) -> 4329.87 | E9: =SUM(E4:E7) -> 5725369.1 | F9: =SUM(F4:F7) -> 2497819.7
A11: USD ACCOUNTS
A12: Bank Name | B12: Opening | C12: Amount Received | D12: Bank Charge | E12: Payment | F12: Balance | G12: Notes
A13: Albilad USD | B13: 3052.33 | C13: 530794.71 | D13: 107.31 | E13: 533606.16 | F13: =B13+C13-D13-E13 -> 133.57
A15: SUB-TOTAL USD | B15: =SUM(B13) -> 3052.33 | C15: =SUM(C13) -> 530794.71 | D15: =SUM(D13) -> 107.31 | E15: =SUM(E13) -> 533606.16 | F15: =SUM(F13) -> 133.57
A17: GRAND TOTAL (SAR + USD Converted) | B17: =B9+B15*3.75 -> 3850313.6 | C17: =C9+C15*3.75 -> 6379131.5 | D17: =D9+D15*3.75 -> 4732.2825 | E17: =E9+E15*3.75 -> 7726392.2 | F17: =F9+F15*3.75 -> 2498320.6
A19: SUMMARY
A20: Total Bank Balance (SAR): | C20: =F17 -> 2498320.6

Sheet Advances_OCT-2025
A1: ADVANCE RECONCILIATION - OCT-2025
A3: OPENING BALANCE | B3: 504511.39 | D3: CLOSING BALANCE | E3: =163800.84+SUM(E7:E101) -> 540959.39
A5: TRANSACTIONS
A6: Date | B6: Voucher No | C6: Description | D6: Person/Party | E6: Advance Given | F6: Amount Settled | G6: Running Balance
A7: 17/04/2024 | B7: EXP3391 | C7: Shirfan - Cash withdraw -- | E7: 1500 | G7: =IF(E7="","",B3+E7-F7) -> 506011.39
A8: 27/05/2024 | B8: EXP3462 | C8: THOYYIB VEHICLE WINGE EXP- | E8: 350 | G8: =IF(E8="","",G7+E8-F8) -> 506361.39
A9: 27/05/2024 | B9: EXP3462 | C9: ADVANCES -THOYYIBE VEHICLE COMPLAINT- | E9: 143.48 | G9: =IF(E9="","",G8+E9-F9) -> 506504.87
A10: 27/05/2024 | B10: EXP3462 | C10: ADVANCES -THOYYIBE VEHICLE COMPLAINT- | E10: 600 | G10: =IF(E10="","",G9+E10-F10) -> 507104.87
A11: 16/06/2024 | B11: JN5365 | C11: COLLECTION CASH TAKEN BY HANI | E11: 34000 | G11: =IF(E11="","",G10+E11-F11) -> 541104.87
A12: 24/06/2024 | B12: EXP3614 | C12: ADVANCE-SALMANUL FARIZ-RIYADH- | E12: 500 | G12: =IF(E12="","",G11+E12-F12) -> 541604.87
A13: 45298 | B13: EXP3645 | C13: ASHIK-ADVANCE- | E13: 4000 | G13: =IF(E13="","",G12+E13-F13) -> 545604.87
A14: 45450 | B14: EXP3699 | C14: FT24188664289852 Ben WHITE GRAPHICS-ADVANCE FOR RECEPTION WORK- | E14: 2790 | G14: =IF(E14="","",G13+E14-F14) -> 548394.87
A15: 13/08/2024 | B15: EXP4197 | C15: AL JARAHA ADVANCE PAYMENT-METAL DETECTOR AND HIGHSPEED PACKING MACHINE-FT24226303374754- | E15: 74656.7 | G15: =IF(E15="","",G14+E15-F15) -> 623051.57
A16: 13/08/2024 | B16: EXP4198 | C16: AL JARAHA ADVANCE PAYMENT-METAL DETECTOR AND HIGHSPEED PACKING MACHINE-FT24226094147820- | E16: 25655.23 | G16: =IF(E16="","",G15+E16-F16) -> 648706.8
A17: 27/08/2024 | B17: EXP4327 | C17: FT24240219059921 Ben EGYPTIAN SAUDI IMPORT EXPORT PAPER-DOUBLE TRANSFER-AMOUNT- | E17: 5000 | G17: =IF(E17="","",G16+E17-F17) -> 653706.8
A18: 13/10/2024 | B18: EXP4386 | C18: SHIRFAN ADVANCE FROM NIDHEESH COLLECTION- | E18: 4650 | G18: =IF(E18="","",G17+E18-F18) -> 658356.8
A19: 20/10/2024 | B19: EXP4423 | C19: THOYYIB ADVANCE QASEEM NEW ROUTE- | E19: 500 | G19: =IF(E19="","",G18+E19-F19) -> 658856.8
A20: 31/10/2024 | C20: MANAFIZ RENT DMM ROUTE | E20: 16857.45 | G20: =IF(E20="","",G19+E20-F20) -> 675714.25
A21: 45546 | B21: EXP4569 | C21: SALMAN FARIZ ADVANCE FROM NIDHEESH COLLECTION- | E21: 4450 | G21: =IF(E21="","",G20+E21-F21) -> 680164.25
A22: 45637 | B22: EXP4573 | C22: ASLAM ADVANCE TO SALMAN FARIZ- | E22: 80 | G22: =IF(E22="","",G21+E22-F22) -> 680244.25
A23: 45577 | B23: EXP4697 | C23: AL JARAHA ADVANCE PAYMENT-METAL DETECTOR AND HIGHSPEED PACKING MACHINE-FT24226094147820- | E23: 49001.48 | G23: =IF(E23="","",G22+E23-F23) -> 729245.73
A24: 25/12/2024 | B24: EXP4747 | C24: SHIRFAN ADVANCE NIDHEESH COLLECTION- | E24: 300 | G24: =IF(E24="","",G23+E24-F24) -> 729545.73
A25: 30/12/2024 | B25: EXP4756 | C25: FUEL-ADVANCE-FAWAS- | E25: 150 | G25: =IF(E25="","",G24+E25-F25) -> 729695.73
A26: 14/01/2025 | B26: EXP4790 | C26: Al jara machinary payment- | E26: 51310.45 | G26: =IF(E26="","",G25+E26-F26) -> 781006.18
A27: 45749 | B27: EXP4884 | C27: PURCHASE ADVANCE-ASHOK- | E27: 200 | G27: =IF(E27="","",G26+E27-F27) -> 781206.18
A28: 16/02/2025 | B28: EXP4912 | C28: NNA REPAIR EXP-ASLAM- | E28: 334.8 | G28: =IF(E28="","",G27+E28-F28) -> 781540.98
A29: 16/02/2025 | B29: EXP4912 | C29: NNA REPAIR EXP-AKMAL- | E29: 300 | G29: =IF(E29="","",G28+E29-F29) -> 781840.98
A30: 16/02/2025 | B30: EXP4912 | C30: NNA REPAIR EXP-ASLAM- | E30: 350 | G30: =IF(E30="","",G29+E30-F30) -> 782190.98
A31: 45752 | B31: EXP5155 | C31: PURCHASE ADVANCE-ASLAM- | E31: 200 | G31: =IF(E31="","",G30+E31-F31) -> 782390.98
A32: 24/05/2025 | B32: EXP5247 | C32: SHIRFAN ADVANCES- | E32: 170 | G32: =IF(E32="","",G31+E32-F32) -> 782560.98
A33: 31/05/2025 | C33: VEHICLE SERVICE BALANCE-SHIRFAN SIR | E33: 219 | G33: =IF(E33="","",G32+E33-F33) -> 782779.98
A34: 45997 | B34: EXP5275 | C34: ADVANCE-SALMAN SIR- | E34: 260.96 | G34: =IF(E34="","",G33+E34-F34) -> 783040.94
A35: 26/06/2025 | B35: EXP5389 | C35: BAYCITY BALANCE-AMOUNT PAID-20000 SETTLED-11000 - | E35: 9000 | G35: =IF(E35="","",G34+E35-F35) -> 792040.94
A36: 29/06/2025 | B36: EXP5402 | C36: SALARY ADVANCE-ASLAM- | E36: 100 | G36: =IF(E36="","",G35+E36-F36) -> 792140.94
A37: 21/07/2025 | B37: EXP5475 | C37: SHIRFAN SIR ADVANCE- | E37: 200 | G37: =IF(E37="","",G36+E37-F37) -> 792340.94
A38: 19/08/2025 | B38: EXP5590 | C38: SUSHI ADVANCE -LABOUR CHARGE-09-08-2025 TO 14-08-2025-TOTAL AMOUNT-7500/-- | E38: 1500 | G38: =IF(E38="","",G37+E38-F38) -> 793840.94
A39: 19/08/2025 | B39: EXP5590 | C39: SALMAN SIR ADVANCE FOR TRAFFIC VIOLATION- | E39: 450 | G39: =IF(E39="","",G38+E39-F39) -> 794290.94
A40: 21/08/2025 | B40: EXP5603 | C40: SALMAN SIR ADVANCE-NIDHEESH- | E40: 100 | G40: =IF(E40="","",G39+E40-F40) -> 794390.94
A41: 45939 | B41: EXP5681 | C41: VEHICLE KEY DUPLICATE- | E41: 15 | G41: =IF(E41="","",G40+E41-F41) -> 794405.94
A42: 13/09/2025 | B42: EXP5683 | C42: KOYA ADVANCE FROM DHIYA CLLECTION NNA FUEL- | E42: 100 | G42: =IF(E42="","",G41+E42-F42) -> 794505.94
A43: 14/09/2025 | B43: EXP5684 | C43: ADVANCE SHIRFAN SIR- | E43: 700 | G43: =IF(E43="","",G42+E43-F43) -> 795205.94
A44: 21/09/2025 | B44: EXP5690 | C44: SHIRFAN SIR ADVANCE- | E44: 1000 | G44: =IF(E44="","",G43+E44-F44) -> 796205.94
A45: 22/09/2025 | B45: EXP5691 | C45: AL HASA PLASTIC OUTSTANDING PAYMENT- | E45: 16000 | G45: =IF(E45="","",G44+E45-F45) -> 812205.94
A46: 27/09/2025 | B46: EXP5718 | C46: ADVANCE MEDICAL EXP-MUNEESH- | E46: 2000 | G46: =IF(E46="","",G45+E46-F46) -> 814205.94
A47: 27/09/2025 | B47: EXP5718 | C47: SHIRFAN SIR ADVANCE- | E47: 4210 | G47: =IF(E47="","",G46+E47-F47) -> 818415.94
A48: 28/09/2025 | B48: EXP5719 | C48: AL AHSA PLASTIC BALANCE PAYMENT- | E48: 16470 | G48: =IF(E48="","",G47+E48-F48) -> 834885.94
A49: 28/09/2025 | B49: EXP5719 | C49: ADVANCE BALANCE-SABARI- | E49: 64 | G49: =IF(E49="","",G48+E49-F49) -> 834949.94
A50: 30/09/2025 | B50: EXP5721 | C50: DRILL FOR OFFICE RENOVATION- | E50: 140 | G50: =IF(E50="","",G49+E50-F50) -> 835089.94
C51: ADVANCE CLOSING BALANCE CHANGE | E51: 35 | G51: =IF(E51="","",G50+E51-F51) -> 835124.94
A52: 45910 | B52: EXP5764 | C52: ADVANCE-NIDHEESH- | E52: 2000 | G52: =IF(E52="","",G51+E52-F52) -> 837124.94
A53: 45971 | B53: EXP5765 | C53: ADVANCE- | E53: 4000 | G53: =IF(E53="","",G52+E53-F53) -> 841124.94
A54: 46001 | B54: EXP5766 | C54: ADVANCE- | E54: 6100 | G54: =IF(E54="","",G53+E54-F54) -> 847224.94
A55: 13/10/2025 | B55: EXP5787 | C55: ADVANCE- | E55: 545 | G55: =IF(E55="","",G54+E55-F55) -> 847769.94
A56: 16/10/2025 | B56: JN11526 | C56: AL AHSA PLASTIC ADVANCE PAYMENT-INV-2025-PPC-3255 | E56: 10000 | G56: =IF(E56="","",G55+E56-F56) -> 857769.94
A57: 30/10/2025 | B57: EXP5806 | C57: Advance-Sabari- | E57: 2000 | G57: =IF(E57="","",G56+E57-F57) -> 859769.94
A58: 30/10/2025 | B58: EXP5806 | C58: Advance-Sabari- | E58: 1500 | G58: =IF(E58="","",G57+E58-F58) -> 861269.94
A59: 30/10/2025 | B59: EXP5806 | C59: Advance-Khudair note change- | E59: 20400 | G59: =IF(E59="","",G58+E59-F59) -> 881669.94
G60: =IF(E60="","",G59+E60-F60)
G61: =IF(E61="","",G60+E61-F61)
G62: =IF(E62="","",G61+E62-F62)
G63: =IF(E63="","",G62+E63-F63)
G64: =IF(E64="","",G63+E64-F64)
G65: =IF(E65="","",G64+E65-F65)
G66: =IF(E66="","",G65+E66-F66)
G67: =IF(E67="","",G66+E67-F67)
G68: =IF(E68="","",G67+E68-F68)
G69: =IF(E69="","",G68+E69-F69)
G70: =IF(E70="","",G69+E70-F70)
G71: =IF(E71="","",G70+E71-F71)
... G100: =IF(E100="","",G99+E100-F100)
A102: TOTAL | E102: =SUM(E7:E1000) -> #REF! | F102: =SUM(F7:F1000) -> #REF!

Sheet Suspense_OCT-2025
A1: SUSPENSE RECONCILIATION - OCT-2025
A3: OPENING BALANCE | B3: -59758.42 | D3: CLOSING BALANCE | E3: =-17267.64+SUM(E7:E1000)-SUM(F7:F1000) -> -186506.88
A5: UNIDENTIFIED TRANSACTIONS
A6: Date | B6: Journal No | C6: Description | D6: Reference | E6: Debit | F6: Credit | G6: Running Balance
A7: 45295 | B7: JN4377 | C7: Bank sale - Thoyyib - DMM | E7: 24078
A8: 45295 | B8: JN4381 | C8: BANK SALES ON POS -NIDHEESH | E8: 142.97
A9: 45326 | B9: JN4384 | C9: BANK SALE POS FASIL | E9: 159.97
A10: 45326 | B10: JN4384 | C10: BANK SALE POS FASIL | E10: 503.93
A11: 45326 | B11: JN4384 | C11: BANK SALE POS FASIL | E11: 476.93
A12: 14/04/2024 | B12: JN4467 | C12: Bank sale - POS - Jaseel | E12: 564.94
A13: 45355 | B13: JN4425 | C13: CHEQUE DEPOSIT -SAMIR | E13: 0 | F13: 4450.57
A14: 22/04/2024 | B14: EXP4515 | C14: for bank reconciliation-FT24113842248106 Ben Saalim Alhamid -NOT RECIEVED IN BILL- | E14: 4348.76 | F14: 0
A15: 26/06/2024 | B15: JN7242 | C15: BAB#38825126#2792024062411513800001211042 -SADAD REFUND | E15: 0 | F15: 100
A16: 13/08/2024 | B16: JN6115 | C16: MISTAKE ENTRY BALANCE AMOUNT NOT IDENTIFIED BILL-SHABEER CASH BOOK | E16: 365.68
A17: 23/11/2024 | B17: JN7638 | C17: BANK TRANSFER-NOT IDENTIFIED | E17: 0 | F17: 2175.71
A18: 14/12/2024 | B18: JN7950 | C18: BANK POSNO-8117929503058544 | E18: 0 | F18: 1.94
A19: 14/01/2025 | B19: JN8176 | C19: BANK TRANSFER-NIDHEEESH | E19: 0 | F19: 1
A20: 19/01/2025 | B20: JN8400 | C20: BANK TRANSFER- | E20: 0 | F20: 2550
A21: 45690 | B21: JN8696 | C21: BANK TRANSFER-NOT IDENTIFIED | E21: 0 | F21: 2500
A22: 45750 | B22: JN9046 | C22: BANK TRANSFER-NOT IDENTIFIED | E22: 0 | F22: 2000
A23: 13/03/2025 | C23: BANK TRANSFER-SHAREEF | E23: 201 | F23: 0
A24: 45873 | B24: JN9444 | C24: BANK TRANSFER-NOT IDENTIFIED | E24: 0 | F24: 1500
A25: 45965 | B25: JN9447 | C25: BANK-POS | E25: 0 | F25: 0.02
A26: 20/04/2025 | B26: JN9451 | C26: BANK TRANSFER-NOT IDENTIFIED | E26: 0 | F26: 285.96
A27: 20/04/2025 | B27: JN9452 | C27: BANK TRANSFER-NOT IDENTIFIED | E27: 0 | F27: 1380
A28: 29/04/2025 | B28: JN9455 | C28: BANK TRANSFER-NOT IDENTIFIED | E28: 0 | F28: 1000
A29: 45301 | B29: JN9330 | C29: UNKNOWN CREDIT-BILAD -OCTOBER | F29: 4000
A30: 45721 | B30: JN9446 | C30: BANK POS | E30: 0 | F30: 0.01
A31: 45782 | B31: JN9739 | C31: BANK TRANSFER- | E31: 0 | F31: 1600
A32: 45996 | B32: JN9748 | C32: BANK TRANSFER- | E32: 0 | F32: 1000
A33: 17/05/2025 | B33: JN9793 | C33: BANK TRANSFER- | E33: 0 | F33: 1389
A34: 18/05/2025 | B34: JN9787 | C34: BANK POS-SHAREEF | E34: 0 | F34: 523.92
A35: 23/05/2025 | B35: JN9795 | C35: BANK TRANSFER- | E35: 0 | F35: 1000
A36: 27/05/2025 | B36: JN9831 | C36: BANK TRANSFER- | E36: 0 | F36: 1488
A37: 45783 | B37: JN10142 | C37: BANK TRANSFER-NOT IDENTIFIED | E37: 0 | F37: 1005.88
A38: 45906 | B38: JN10143 | C38: BANK POS-SHAREEF | E38: 0 | F38: 108.98
A39: 19/06/2025 | B39: JN10145 | C39: BANK TRANSFER-NOT IDENTIFIED | E39: 0 | F39: 1020.84
A40: 21/06/2025 | B40: JN10146 | C40: BANK | E40: 0 | F40: 0.01
A41: 26/06/2025 | B41: JN10147 | C41: BANK TRANSFER-NOT IDENTIFIED | E41: 0 | F41: 290
A42: 30/06/2025 | C42: BANK CHARGES | E42: 0 | F42: 29
A43: 29/07/2025 | B43: JN10472 | C43: T24 INST. 1 LOANFLEET00001041 T24Batch-NEW DYNA- | E43: 3938.28 | F43: 0
A44: 29/07/2025 | B44: JN10472 | C44: T24 INST. 1 LOANFLEET00001041 T24Batch-NEW DYNA- | E44: 3938.28 | F44: 0
A45: 25/08/2025 | B45: JN10873 | C45: BANK TRANSFER-NOT IDENTIFIED | E45: 0 | F45: 607.92
A46: 29/08/2025 | B46: EXP5667 | C46: for bank reconciliation-T24 INST. 2 LOANFLEET00001041 T24Batch-new dyna -- | E46: 3938.28 | F46: 0
A47: 29/08/2025 | B47: EXP5667 | C47: for bank reconciliation-T24 INST. 2 LOANFLEET00001041 T24Batch-new dyna- | E47: 3938.28 | F47: 0
A48: 31/08/2025 | B48: EXP5670 | C48: 9131082500538722/HANI AHMED ALSHUWKAIKHAT/l- | E48: 5000 | F48: 0
A49: 31/08/2025 | C49: BANK TRANSFER-SHAMEER RIYADH -RECIEPT NOT RECEIVED | E49: 345
A50: 45666 | B50: JN11306 | C50: BANK POS SHAMEER-RIYADH | E50: 0 | F50: 75
A51: 45666 | B51: JN11307 | C51: BANK POS SHAMEER-RIYADH | E51: 0 | F51: 195.22
A52: 13/09/2025 | B52: JN11248 | C52: BANK POS-KHALID | E52: 0 | F52: 108.98
A53: 26/09/2025 | B53: JN11365 | C53: BANK TRANSFER-NOT IDENTIFIFED | E53: 0 | F53: 630
A54: 29/09/2025 | B54: EXP5754 | C54: for bank reconciliation-T24 INST. 3 LOANFLEET00001041 T24Batch-NEW DYNA INSTALMENT- | E54: 3938.28 | F54: 0
A55: 29/09/2025 | B55: EXP5754 | C55: for bank reconciliation-for bank reconciliation-T24 INST. 3 LOANFLEET00001041 T24Batch-NEW DYNA INSTALMENT- | E55: 3938.28 | F55: 0
C56: BANK TRANSFER-SHAMEER RIYADH RECIEPT NOT RECEIVED | E56: 109
C57: BANK CHARGES | E57: 98
A58: 45667 | B58: JN12018 | C58: BANK TRANSFER-SHAMEER RIYADH-8408.69 | E58: 0 | F58: 518
A59: 45667 | B59: JN12083 | C59: BANK POS-SHAMEER RIYADH-19948.69 | E59: 0 | F59: 259
A60: 45698 | B60: JN12103 | C60: BANK TRANSFER-NOT IDENTIFIED | E60: 0 | F60: 562.03
A61: 45698 | B61: JN12084 | C61: BANK POS-SHAMEER RIYADH-19948.69 | E61: 0 | F61: 2897.67
A62: 45726 | B62: JN11986 | C62: BANK POS-KHALID-9296.16 | E62: 0 | F62: 201
A63: 45757 | B63: JN12000 | C63: BANK TRANSFER-KHALLID- 19,402.92 | E63: 0 | F63: 4495
A64: 45787 | B64: JN12001 | C64: BANK TRANSFER-KHALLID- 19,402.92 | E64: 0 | F64: 196
A65: 45787 | B65: JN12065 | C65: BANK POS-SHAMEER RIYADH | E65: 0 | F65: 20
A66: 45787 | B66: JN12085 | C66: BANK POS MACHINE TEST | E66: 0 | F66: 0.01
A67: 45787 | B67: JN12044 | C67: BANK TRANSFER-SHAMEER HAFAR- 5,302 | E67: 0 | F67: 3035
A68: 45818 | B68: JN12066 | C68: BANK POS-SHAMEER RIYADH-19948.49 | E68: 0 | F68: 620
A69: 45818 | B69: JN12030 | C69: BANK POS-SHAMEER HAFAR-7264 | E69: 0 | F69: 927
... A87: 46001 | B87: JN12070 | C87: BANK POS-SHAMEER RIYADH-19948.49 | E87: 0 | F87: 368
A88: 13/10/2025 | B88: JN12071 | C88: BANK POS-SHAMEER RIYADH-19948.49 | E88: 0 | F88: 100
A89: 15/10/2025 | B89: JN11990 | C89: BANK POS-KHALID-9296.16 | E89: 0 | F89: 217.97
A90: 15/10/2025 | B90: JN12003 | C90: BANK TRANSFER-KHALLID- 19,402.92 | E90: 0 | F90: 357.98
A91: 15/10/2025 | B91: JN12072 | C91: BANK POS-SHAMEER RIYADH-19948.49 | E91: 0 | F91: 1541.76
A92: 15/10/2025 | B92: JN12033 | C92: BANK POS-SHAMEER HAFAR-7264 | E92: 0 | F92: 1631
A93: 16/10/2025 | B93: JN12073 | C93: BANK POS-SHAMEER RIYADH-19948.49 | E93: 0 | F93: 368
A94: 16/10/2025 | B94: JN12074 | C94: BANK POS-SHAMEER RIYADH-19948.69 | E94: 0 | F94: 4607.21
A95: 16/10/2025 | B95: JN12004 | C95: BANK TRANSFER-KHALLID- 19,402.92 | E95: 0 | F95: 91.98
A96: 16/10/2025 | B96: JN12020 | C96: BANK TRANSFER-SHAMEER RIYADH-8408.69 | E96: 0 | F96: 494
A97: 16/10/2025 | B97: JN12021 | C97: BANK TRANSFER-SHAMEER RIYADH-8408.69 | E97: 0 | F97: 827
A98: 16/10/2025 | B98: JN11997 | C98: BANK TRANSFER-KHALLID- 19,402.92 | E98: 0 | F98: 918
A99: 16/10/2025 | B99: JN11998 | C99: BANK TRANSFER-KHALLID- 19,402.92 | E99: 0 | F99: 1917
... A175: 31/10/2025 | B175: JN12101 | C175: BANK TRANSFER-NOT IDENTIFIED | E175: 0 | F175: 577.92

Sheet Outstanding_OCT-2025
A1: CUSTOMER OUTSTANDING - OCT-2025
A3: Salesman | B3: Total Outstanding | C3: No. of Customers | D3: Average
A4: Nidheesh | B4: =SUMIF($D$19:$D$502,A4,$G$19:$G$502) -> 76836.77 | C4: =COUNTIF($D$19:$D$502,A4) -> 47 | D4: =IFERROR(B4/C4,0) -> 1634.8249
A5: Jaseel | B5: =SUMIF($D$19:$D$502,A5,$G$19:$G$502) -> 20506.08 | C5: =COUNTIF($D$19:$D$502,A5) -> 18 | D5: =IFERROR(B5/C5,0) -> 1139.2267
A6: Bassam | B6: =SUMIF($D$19:$D$502,A6,$G$19:$G$502) -> 25219.28 | C6: =COUNTIF($D$19:$D$502,A6) -> 33 | D6: =IFERROR(B6/C6,0) -> 764.22061
A7: akmal | B7: =SUMIF($D$19:$D$502,A7,$G$19:$G$502) -> 45795.01 | C7: =COUNTIF($D$19:$D$502,A7) -> 19 | D7: =IFERROR(B7/C7,0) -> 2410.2637
A8: arshad | B8: =SUMIF($D$19:$D$502,A8,$G$19:$G$502) -> 366543.83 | C8: =COUNTIF($D$19:$D$502,A8) -> 26 | D8: =IFERROR(B8/C8,0) -> 14097.84
A9: Shameer riyadh | B9: =SUMIF($D$19:$D$502,A9,$G$19:$G$502) -> 72659.84 | C9: =COUNTIF($D$19:$D$502,A9) -> 55 | D9: =IFERROR(B9/C9,0) -> 1321.088
A10: company sales | B10: =SUMIF($D$19:$D$502,A10,$G$19:$G$502) -> 1056569.4 | C10: =COUNTIF($D$19:$D$502,A10) -> 15 | D10: =IFERROR(B10/C10,0) -> 70437.962
A11: shafi | B11: =SUMIF($D$19:$D$502,A11,$G$19:$G$502) -> 17259.59 | C11: =COUNTIF($D$19:$D$502,A11) -> 35 | D11: =IFERROR(B11/C11,0) -> 493.13114
A12: ashik | B12: =SUMIF($D$19:$D$502,A12,$G$19:$G$502) -> 27926.05 | C12: =COUNTIF($D$19:$D$502,A12) -> 28 | D12: =IFERROR(B12/C12,0) -> 997.35893
A13: dhiya | B13: =SUMIF($D$19:$D$502,A13,$G$19:$G$502) -> 245613.5 | C13: =COUNTIF($D$19:$D$502,A13) -> 19 | D13: =IFERROR(B13/C13,0) -> 12927.026
A14: salman | B14: =SUMIF($D$19:$D$502,A14,$G$19:$G$502) -> 0 | C14: =COUNTIF($D$19:$D$502,A14) -> 0 | D14: =IFERROR(B14/C14,0) -> 0
A15: samir | B15: =SUMIF($D$19:$D$502,A15,$G$19:$G$502) -> 9086.56 | C15: =COUNTIF($D$19:$D$502,A15) -> 10 | D15: =IFERROR(B15/C15,0) -> 908.656
A16: TOTAL | B16: =SUM(B4:B15) -> 1964015.9 | C16: =SUM(C4:C15) -> 305 | D16: =IFERROR(B16/C16,0) -> 6439.3965
A18: Customer Code | B18: Customer Name | C18: Area | D18: Salesman | E18: Invoice Amount | F18: Paid Amount | G18: Balance | H18: Days
A19: CUST63 | B19: Saudi marketting | C19: Al Ahsa-1 | D19: Jaseel | E19: 1019.82 | G19: =IF(E19="","",E19-F19) -> 1019.82
A20: CUST84 | B20: Najmath AL khayrath | C20: Al Ahsa-1 | D20: Jaseel | E20: 1939.7 | G20: =IF(E20="","",E20-F20) -> 1939.7
A21: CUST204 | B21: Thamveenath Noorul usam | C21: Al Ahsa-1 | D21: Jaseel | E21: 1460.78 | G21: =IF(E21="","",E21-F21) -> 1460.78
A22: CUST437 | B22: Aswaq sahab alhadid | C22: Al Ahsa-1 | D22: Jaseel | E22: 1049.85 | G22: =IF(E22="","",E22-F22) -> 1049.85
A23: CUST561 | B23: Grocery naster | C23: Al Ahsa-1 | D23: Jaseel | E23: 284.96 | G23: =IF(E23="","",E23-F23) -> 284.96
A24: CUST565 | B24: Sahab mart | C24: Al Ahsa-1 | D24: Jaseel | E24: 1087.86 | G24: =IF(E24="","",E24-F24) -> 1087.86
A25: CUST1967 | B25: Thanveenath hoor sahadath | C25: Al Ahsa-1 | D25: Jaseel | E25: 158.97 | G25: =IF(E25="","",E25-F25) -> 158.97
A26: CUST1999 | B26: Zone mart (j) | C26: Al Ahsa-1 | D26: Jaseel | E26: 1507.81 | G26: =IF(E26="","",E26-F26) -> 1507.81
A27: CUST2139 | B27: Sama alsaada foodstuff markets | C27: Al Ahsa-1 | D27: Jaseel | E27: 600 | G27: =IF(E27="","",E27-F27) -> 600
A28: CUST2141 | B28: Al Qafila al khalijiyyah supermarket | C28: Al Ahsa-1 | D28: Jaseel | E28: 1257.81 | G28: =IF(E28="","",E28-F28) -> 1257.81
A29: CUST2237 | B29: Ghaith al safat food supplies | C29: Al Ahsa-1 | D29: Jaseel | E29: 2567.63 | G29: =IF(E29="","",E29-F29) -> 2567.63
A30: CUST2326 | B30: Al Zahra (umm | C30: Al Ahsa-1 | D30: Jaseel | E30: 1415.82 | G30: =IF(E30="","",E30-F30) -> 1415.82
... A437: CUST6152 | B437: Shareekth kamal al thawfeer al thijariyath dl dammam | C437: Dammam Retail | D437: akmal | E437: 4284.11 | G437: =IF(E437="","",E437-F437) -> 4284.11
G438: =IF(E438="","",E438-F438)
G439: =IF(E439="","",E439-F439)
G440: =IF(E440="","",E440-F440)
G441: =IF(E441="","",E441-F441)
G442: =IF(E442="","",E442-F442)
G443: =IF(E443="","",E443-F443)
G444: =IF(E444="","",E444-F444)
G445: =IF(E445="","",E445-F445)
G446: =IF(E446="","",E446-F446)
G447: =IF(E447="","",E447-F447)
G448: =IF(E448="","",E448-F448)
G449: =IF(E449="","",E449-F449)
... G502: =IF(E502="","",E502-F502)
A503: GRAND TOTAL | E503: =SUM(E19:E502) -> 2063023.1 | F503: =SUM(F19:F502) -> 0 | G503: =SUM(G19:G502) -> 2063023.1

Sheet Advances_SEP-2025
A1: ADVANCE RECONCILIATION - SEP-2025
A3: OPENING BALANCE | B3: 473840.39 | D3: CLOSING BALANCE | E3: =163800.84+SUM(E7:E101) -> 504511.39
A5: TRANSACTIONS
A6: Date | B6: Voucher No | C6: Description | D6: Person/Party | E6: Advance Given | F6: Amount Settled | G6: Running Balance
A7: 17/04/2024 | B7: EXP3391 | C7: Shirfan - Cash withdraw -- | E7: 1500 | G7: =IF(E7="","",B3+E7-F7) -> 475340.39
A8: 27/05/2024 | B8: EXP3462 | C8: THOYYIB VEHICLE WINGE EXP- | E8: 350 | G8: =IF(E8="","",G7+E8-F8) -> 475690.39
A9: 27/05/2024 | B9: EXP3462 | C9: ADVANCES -THOYYIBE VEHICLE COMPLAINT- | E9: 143.48 | G9: =IF(E9="","",G8+E9-F9) -> 475833.87
A10: 27/05/2024 | B10: EXP3462 | C10: ADVANCES -THOYYIBE VEHICLE COMPLAINT- | E10: 600 | G10: =IF(E10="","",G9+E10-F10) -> 476433.87
A11: 16/06/2024 | B11: JN5365 | C11: COLLECTION CASH TAKEN BY HANI | E11: 34000 | G11: =IF(E11="","",G10+E11-F11) -> 510433.87
A12: 24/06/2024 | B12: EXP3614 | C12: ADVANCE-SALMANUL FARIZ-RIYADH- | E12: 500 | G12: =IF(E12="","",G11+E12-F12) -> 510933.87
A13: 45298 | B13: EXP3645 | C13: ASHIK-ADVANCE- | E13: 4000 | G13: =IF(E13="","",G12+E13-F13) -> 514933.87
A14: 45450 | B14: EXP3699 | C14: FT24188664289852 Ben WHITE GRAPHICS-ADVANCE FOR RECEPTION WORK- | E14: 2790 | G14: =IF(E14="","",G13+E14-F14) -> 517723.87
A15: 13/08/2024 | B15: EXP4197 | C15: AL JARAHA ADVANCE PAYMENT-METAL DETECTOR AND HIGHSPEED PACKING MACHINE-FT24226303374754- | E15: 74656.7 | G15: =IF(E15="","",G14+E15-F15) -> 592380.57
A16: 13/08/2024 | B16: EXP4198 | C16: AL JARAHA ADVANCE PAYMENT-METAL DETECTOR AND HIGHSPEED PACKING MACHINE-FT24226094147820- | E16: 25655.23 | G16: =IF(E16="","",G15+E16-F16) -> 618035.8
A17: 27/08/2024 | B17: EXP4327 | C17: FT24240219059921 Ben EGYPTIAN SAUDI IMPORT EXPORT PAPER-DOUBLE TRANSFER-AMOUNT- | E17: 5000 | G17: =IF(E17="","",G16+E17-F17) -> 623035.8
A18: 13/10/2024 | B18: EXP4386 | C18: SHIRFAN ADVANCE FROM NIDHEESH COLLECTION- | E18: 4650 | G18: =IF(E18="","",G17+E18-F18) -> 627685.8
A19: 20/10/2024 | B19: EXP4423 | C19: THOYYIB ADVANCE QASEEM NEW ROUTE- | E19: 500 | G19: =IF(E19="","",G18+E19-F19) -> 628185.8
A20: 31/10/2024 | C20: MANAFIZ RENT DMM ROUTE | E20: 16857.45 | G20: =IF(E20="","",G19+E20-F20) -> 645043.25
A21: 45546 | B21: EXP4569 | C21: SALMAN FARIZ ADVANCE FROM NIDHEESH COLLECTION- | E21: 4450 | G21: =IF(E21="","",G20+E21-F21) -> 649493.25
A22: 45637 | B22: EXP4573 | C22: ASLAM ADVANCE TO SALMAN FARIZ- | E22: 80 | G22: =IF(E22="","",G21+E22-F22) -> 649573.25
A23: 45577 | B23: EXP4697 | C23: AL JARAHA ADVANCE PAYMENT-METAL DETECTOR AND HIGHSPEED PACKING MACHINE-FT24226094147820- | E23: 49001.48 | G23: =IF(E23="","",G22+E23-F23) -> 698574.73
A24: 25/12/2024 | B24: EXP4747 | C24: SHIRFAN ADVANCE NIDHEESH COLLECTION- | E24: 300 | G24: =IF(E24="","",G23+E24-F24) -> 698874.73
A25: 30/12/2024 | B25: EXP4756 | C25: FUEL-ADVANCE-FAWAS- | E25: 150 | G25: =IF(E25="","",G24+E25-F25) -> 699024.73
A26: 14/01/2025 | B26: EXP4790 | C26: Al jara machinary payment- | E26: 51310.45 | G26: =IF(E26="","",G25+E26-F26) -> 750335.18
A27: 45749 | B27: EXP4884 | C27: PURCHASE ADVANCE-ASHOK- | E27: 200 | G27: =IF(E27="","",G26+E27-F27) -> 750535.18
A28: 16/02/2025 | B28: EXP4912 | C28: NNA REPAIR EXP-ASLAM- | E28: 334.8 | G28: =IF(E28="","",G27+E28-F28) -> 750869.98
A29: 16/02/2025 | B29: EXP4912 | C29: NNA REPAIR EXP-AKMAL- | E29: 300 | G29: =IF(E29="","",G28+E29-F29) -> 751169.98
A30: 16/02/2025 | B30: EXP4912 | C30: NNA REPAIR EXP-ASLAM- | E30: 350 | G30: =IF(E30="","",G29+E30-F30) -> 751519.98
A31: 45752 | B31: EXP5155 | C31: PURCHASE ADVANCE-ASLAM- | E31: 200 | G31: =IF(E31="","",G30+E31-F31) -> 751719.98
A32: 24/05/2025 | B32: EXP5247 | C32: SHIRFAN ADVANCES- | E32: 170 | G32: =IF(E32="","",G31+E32-F32) -> 751889.98
A33: 31/05/2025 | C33: VEHICLE SERVICE BALANCE-SHIRFAN SIR | E33: 219 | G33: =IF(E33="","",G32+E33-F33) -> 752108.98
A34: 45997 | B34: EXP5275 | C34: ADVANCE-SALMAN SIR- | E34: 260.96 | G34: =IF(E34="","",G33+E34-F34) -> 752369.94
A35: 26/06/2025 | B35: EXP5389 | C35: BAYCITY BALANCE-AMOUNT PAID-20000 SETTLED-11000 - | E35: 9000 | G35: =IF(E35="","",G34+E35-F35) -> 761369.94
A36: 29/06/2025 | B36: EXP5402 | C36: SALARY ADVANCE-ASLAM- | E36: 100 | G36: =IF(E36="","",G35+E36-F36) -> 761469.94
A37: 21/07/2025 | B37: EXP5475 | C37: SHIRFAN SIR ADVANCE- | E37: 200 | G37: =IF(E37="","",G36+E37-F37) -> 761669.94
A38: 17/08/2025 | B38: EXP5588 | C38: SHAFI VEHICLE REPAIR ADVANCE- | E38: 5000 | G38: =IF(E38="","",G37+E38-F38) -> 766669.94
A39: 19/08/2025 | B39: EXP5590 | C39: SUSHI ADVANCE -LABOUR CHARGE-09-08-2025 TO 14-08-2025-TOTAL AMOUNT-7500/-- | E39: 1500 | G39: =IF(E39="","",G38+E39-F39) -> 768169.94
A40: 19/08/2025 | B40: EXP5590 | C40: SALMAN SIR ADVANCE FOR TRAFFIC VIOLATION- | E40: 450 | G40: =IF(E40="","",G39+E40-F40) -> 768619.94
A41: 21/08/2025 | B41: EXP5603 | C41: SALMAN SIR ADVANCE-NIDHEESH- | E41: 100 | G41: =IF(E41="","",G40+E41-F41) -> 768719.94
A42: 45939 | B42: EXP5681 | C42: VEHICLE KEY DUPLICATE- | E42: 15 | G42: =IF(E42="","",G41+E42-F42) -> 768734.94
A43: 13/09/2025 | B43: EXP5683 | C43: KOYA ADVANCE FROM DHIYA CLLECTION NNA FUEL- | E43: 100 | G43: =IF(E43="","",G42+E43-F43) -> 768834.94
A44: 14/09/2025 | B44: EXP5684 | C44: ADVANCE SHIRFAN SIR- | E44: 700 | G44: =IF(E44="","",G43+E44-F44) -> 769534.94
A45: 21/09/2025 | B45: EXP5690 | C45: SHIRFAN SIR ADVANCE- | E45: 1000 | G45: =IF(E45="","",G44+E45-F45) -> 770534.94
A46: 22/09/2025 | B46: EXP5691 | C46: AL HASA PLASTIC OUTSTANDING PAYMENT- | E46: 16000 | G46: =IF(E46="","",G45+E46-F46) -> 786534.94
A47: 25/09/2025 | B47: JN11292 | C47: KHALID VEHICLE REPAIR ADVANCE | E47: 4297 | G47: =IF(E47="","",G46+E47-F47) -> 790831.94
A48: 27/09/2025 | B48: EXP5718 | C48: ADVANCE MEDICAL EXP-MUNEESH- | E48: 2000 | G48: =IF(E48="","",G47+E48-F48) -> 792831.94
A49: 27/09/2025 | B49: EXP5718 | C49: MEDICAL EXP-ADVANCE-MUNEESH- | E49: 300 | G49: =IF(E49="","",G48+E49-F49) -> 793131.94
A50: 27/09/2025 | B50: EXP5718 | C50: SHIRFAN SIR ADVANCE- | E50: 4210 | G50: =IF(E50="","",G49+E50-F50) -> 797341.94
A51: 28/09/2025 | B51: EXP5719 | C51: AL AHSA PLASTIC BALANCE PAYMENT- | E51: 16470 | G51: =IF(E51="","",G50+E51-F51) -> 813811.94
A52: 28/09/2025 | B52: EXP5719 | C52: ADVANCE BALANCE-SABARI- | E52: 64 | G52: =IF(E52="","",G51+E52-F52) -> 813875.94
A53: 30/09/2025 | B53: EXP5721 | C53: PURCHASE ADVANCE SABARI- | E53: 500 | G53: =IF(E53="","",G52+E53-F53) -> 814375.94
A54: 30/09/2025 | B54: EXP5721 | C54: DRILL FOR OFFICE RENOVATION- | E54: 140 | G54: =IF(E54="","",G53+E54-F54) -> 814515.94
C55: ADVANCE CLOSING BALANCE CHANGE | E55: 35 | G55: =IF(E55="","",G54+E55-F55) -> 814550.94
G56: =IF(E56="","",G55+E56-F56)
G57: =IF(E57="","",G56+E57-F57)
G58: =IF(E58="","",G57+E58-F58)
G59: =IF(E59="","",G58+E59-F59)
G60: =IF(E60="","",G59+E60-F60)
G61: =IF(E61="","",G60+E61-F61)
G62: =IF(E62="","",G61+E62-F62)
G63: =IF(E63="","",G62+E63-F63)
G64: =IF(E64="","",G63+E64-F64)
G65: =IF(E65="","",G64+E65-F65)
G66: =IF(E66="","",G65+E66-F66)
G67: =IF(E67="","",G66+E67-F67)
... G100: =IF(E100="","",G99+E100-F100)
A102: TOTAL | E102: =SUM(E7:E101) -> 340710.55 | F102: =SUM(F7:F101) -> 0

Sheet Suspense_SEP-2025
A1: SUSPENSE RECONCILIATION - SEP-2025
A3: OPENING BALANCE | B3: -22235.07 | D3: CLOSING BALANCE | E3: =-17267.64+SUM(E7:E1000)-SUM(F7:F1000) -> -59758.42
A5: UNIDENTIFIED TRANSACTIONS
A6: Date | B6: Journal No | C6: Description | D6: Reference | E6: Debit | F6: Credit | G6: Running Balance
A7: 45295 | B7: JN4377 | C7: Bank sale - Thoyyib - DMM | E7: 24078 | G7: =IF(AND(E7="",F7=""),"",B3+E7-F7) -> 1842.93
A8: 45295 | B8: JN4381 | C8: BANK SALES ON POS -NIDHEESH | E8: 142.97 | G8: =IF(AND(E8="",F8=""),"",G7+E8-F8) -> 1985.9
A9: 45326 | B9: JN4384 | C9: BANK SALE POS FASIL | E9: 159.97 | G9: =IF(AND(E9="",F9=""),"",G8+E9-F9) -> 2145.87
A10: 45326 | B10: JN4384 | C10: BANK SALE POS FASIL | E10: 503.93 | G10: =IF(AND(E10="",F10=""),"",G9+E10-F10) -> 2649.8
A11: 45326 | B11: JN4384 | C11: BANK SALE POS FASIL | E11: 476.93 | G11: =IF(AND(E11="",F11=""),"",G10+E11-F11) -> 3126.73
A12: 14/04/2024 | B12: JN4467 | C12: Bank sale - POS - Jaseel | E12: 564.94 | G12: =IF(AND(E12="",F12=""),"",G11+E12-F12) -> 3691.67
A13: 45355 | B13: JN4425 | C13: CHEQUE DEPOSIT -SAMIR | E13: 0 | F13: 4450.57 | G13: =IF(AND(E13="",F13=""),"",G12+E13-F13) -> -758.9
A14: 22/04/2024 | B14: EXP4515 | C14: for bank reconciliation-FT24113842248106 Ben Saalim Alhamid -NOT RECIEVED IN BILL- | E14: 4348.76 | F14: 0 | G14: =IF(AND(E14="",F14=""),"",G13+E14-F14) -> 3589.86
A15: 26/06/2024 | B15: JN7242 | C15: BAB#38825126#2792024062411513800001211042 -SADAD REFUND | E15: 0 | F15: 100 | G15: =IF(AND(E15="",F15=""),"",G14+E15-F15) -> 3489.86
A16: 13/08/2024 | B16: JN6115 | C16: MISTAKE ENTRY BALANCE AMOUNT NOT IDENTIFIED BILL-SHABEER CASH BOOK | E16: 365.68 | G16: =IF(AND(E16="",F16=""),"",G15+E16-F16) -> 3855.54
A17: 23/11/2024 | B17: JN7638 | C17: BANK TRANSFER-NOT IDENTIFIED | E17: 0 | F17: 2175.71 | G17: =IF(AND(E17="",F17=""),"",G16+E17-F17) -> 1679.83
A18: 14/12/2024 | B18: JN7950 | C18: BANK POSNO-8117929503058544 | E18: 0 | F18: 1.94 | G18: =IF(AND(E18="",F18=""),"",G17+E18-F18) -> 1677.89
A19: 14/01/2025 | B19: JN8176 | C19: BANK TRANSFER-NIDHEEESH | E19: 0 | F19: 1 | G19: =IF(AND(E19="",F19=""),"",G18+E19-F19) -> 1676.89
A20: 19/01/2025 | B20: JN8400 | C20: BANK TRANSFER- | E20: 0 | F20: 2550 | G20: =IF(AND(E20="",F20=""),"",G19+E20-F20) -> -873.11
A21: 45690 | B21: JN8696 | C21: BANK TRANSFER-NOT IDENTIFIED | E21: 0 | F21: 2500 | G21: =IF(AND(E21="",F21=""),"",G20+E21-F21) -> -3373.11
A22: 45750 | B22: JN9046 | C22: BANK TRANSFER-NOT IDENTIFIED | E22: 0 | F22: 2000 | G22: =IF(AND(E22="",F22=""),"",G21+E22-F22) -> -5373.11
A23: 13/03/2025 | C23: BANK TRANSFER-SHAREEF | E23: 201 | F23: 0 | G23: =IF(AND(E23="",F23=""),"",G22+E23-F23) -> -5172.11
A24: 45873 | B24: JN9444 | C24: BANK TRANSFER-NOT IDENTIFIED | E24: 0 | F24: 1500 | G24: =IF(AND(E24="",F24=""),"",G23+E24-F24) -> -6672.11
A25: 45965 | B25: JN9447 | C25: BANK-POS | E25: 0 | F25: 0.02 | G25: =IF(AND(E25="",F25=""),"",G24+E25-F25) -> -6672.13
A26: 20/04/2025 | B26: JN9451 | C26: BANK TRANSFER-NOT IDENTIFIED | E26: 0 | F26: 285.96 | G26: =IF(AND(E26="",F26=""),"",G25+E26-F26) -> -6958.09
A27: 20/04/2025 | B27: JN9452 | C27: BANK TRANSFER-NOT IDENTIFIED | E27: 0 | F27: 1380 | G27: =IF(AND(E27="",F27=""),"",G26+E27-F27) -> -8338.09
A28: 29/04/2025 | B28: JN9455 | C28: BANK TRANSFER-NOT IDENTIFIED | E28: 0 | F28: 1000 | G28: =IF(AND(E28="",F28=""),"",G27+E28-F28) -> -9338.09
A29: 45301 | B29: JN9330 | C29: UNKNOWN CREDIT-BILAD -OCTOBER | F29: 4000 | G29: =IF(AND(E29="",F29=""),"",G28+E29-F29) -> -13338.09
A30: 45721 | B30: JN9446 | C30: BANK POS | E30: 0 | F30: 0.01 | G30: =IF(AND(E30="",F30=""),"",G29+E30-F30) -> -13338.1
A31: 45782 | B31: JN9739 | C31: BANK TRANSFER- | E31: 0 | F31: 1600 | G31: =IF(AND(E31="",F31=""),"",G30+E31-F31) -> -14938.1
A32: 45996 | B32: JN9748 | C32: BANK TRANSFER- | E32: 0 | F32: 1000 | G32: =IF(AND(E32="",F32=""),"",G31+E32-F32) -> -15938.1
A33: 17/05/2025 | B33: JN9793 | C33: BANK TRANSFER- | E33: 0 | F33: 1389 | G33: =IF(AND(E33="",F33=""),"",G32+E33-F33) -> -17327.1
A34: 18/05/2025 | B34: JN9787 | C34: BANK POS-SHAREEF | E34: 0 | F34: 523.92 | G34: =IF(AND(E34="",F34=""),"",G33+E34-F34) -> -17851.02
A35: 23/05/2025 | B35: JN9795 | C35: BANK TRANSFER- | E35: 0 | F35: 1000 | G35: =IF(AND(E35="",F35=""),"",G34+E35-F35) -> -18851.02
A36: 27/05/2025 | B36: JN9831 | C36: BANK TRANSFER- | E36: 0 | F36: 1488 | G36: =IF(AND(E36="",F36=""),"",G35+E36-F36) -> -20339.02
A37: 45783 | B37: JN10142 | C37: BANK TRANSFER-NOT IDENTIFIED | E37: 0 | F37: 1005.88 | G37: =IF(AND(E37="",F37=""),"",G36+E37-F37) -> -21344.9
A38: 45906 | B38: JN10143 | C38: BANK POS-SHAREEF | E38: 0 | F38: 108.98 | G38: =IF(AND(E38="",F38=""),"",G37+E38-F38) -> -21453.88
A39: 19/06/2025 | B39: JN10145 | C39: BANK TRANSFER-NOT IDENTIFIED | E39: 0 | F39: 1020.84 | G39: =IF(AND(E39="",F39=""),"",G38+E39-F39) -> -22474.72
A40: 21/06/2025 | B40: JN10146 | C40: BANK | E40: 0 | F40: 0.01 | G40: =IF(AND(E40="",F40=""),"",G39+E40-F40) -> -22474.73
A41: 26/06/2025 | B41: JN10147 | C41: BANK TRANSFER-NOT IDENTIFIED | E41: 0 | F41: 290 | G41: =IF(AND(E41="",F41=""),"",G40+E41-F41) -> -22764.73
A42: 30/06/2025 | C42: BANK CHARGES | E42: 0 | F42: 29 | G42: =IF(AND(E42="",F42=""),"",G41+E42-F42) -> -22793.73
A43: 27/07/2025 | B43: JN10469 | C43: BANK TRANSFER NOT IDENTIFIED | E43: 0 | F43: 613 | G43: =IF(AND(E43="",F43=""),"",G42+E43-F43) -> -23406.73
A44: 28/07/2025 | B44: JN10466 | C44: BANK POS-SHAFI | E44: 0 | F44: 3111 | G44: =IF(AND(E44="",F44=""),"",G43+E44-F44) -> -26517.73
A45: 29/07/2025 | B45: JN10472 | C45: T24 INST. 1 LOANFLEET00001041 T24Batch-NEW DYNA- | E45: 3938.28 | F45: 0 | G45: =IF(AND(E45="",F45=""),"",G44+E45-F45) -> -22579.45
A46: 29/07/2025 | B46: JN10472 | C46: T24 INST. 1 LOANFLEET00001041 T24Batch-NEW DYNA- | E46: 3938.28 | F46: 0 | G46: =IF(AND(E46="",F46=""),"",G45+E46-F46) -> -18641.17
A47: 31/07/2025 | B47: JN10467 | C47: BANK POS-SHAFI | E47: 0 | F47: 579 | G47: =IF(AND(E47="",F47=""),"",G46+E47-F47) -> -19220.17
A48: 45999 | B48: JN10871 | C48: BANK TRANSFER-NOT IDENTIFIED | E48: 0 | F48: 681.03 | G48: =IF(AND(E48="",F48=""),"",G47+E48-F48) -> -19901.2
A49: 45999 | B49: JN10878 | C49: BANK TRANSFER-NOT IDENTIFIED | E49: 0 | F49: 804.26 | G49: =IF(AND(E49="",F49=""),"",G48+E49-F49) -> -20705.46
A50: 19/08/2025 | B50: JN10872 | C50: BANK TRANSFER-SHAFI | E50: 0 | F50: 460 | G50: =IF(AND(E50="",F50=""),"",G49+E50-F50) -> -21165.46
A51: 20/08/2025 | B51: JN10844 | C51: BANK POS-SHAFI | E51: 0 | F51: 511 | G51: =IF(AND(E51="",F51=""),"",G50+E51-F51) -> -21676.46
A52: 23/08/2025 | B52: JN10845 | C52: BANK POS-SHAFI | E52: 0 | F52: 300 | G52: =IF(AND(E52="",F52=""),"",G51+E52-F52) -> -21976.46
A53: 24/08/2025 | B53: JN10879 | C53: BANK TRANSFER-NOT IDENTIFIED | E53: 0 | F53: 2237.16 | G53: =IF(AND(E53="",F53=""),"",G52+E53-F53) -> -24213.62
A54: 25/08/2025 | B54: JN10873 | C54: BANK TRANSFER-NOT IDENTIFIED | E54: 0 | F54: 607.92 | G54: =IF(AND(E54="",F54=""),"",G53+E54-F54) -> -24821.54
A55: 25/08/2025 | B55: JN10874 | C55: BANK TRANSFER-NOT IDENTIFIED | E55: 0 | F55: 494.02 | G55: =IF(AND(E55="",F55=""),"",G54+E55-F55) -> -25315.56
A56: 29/08/2025 | B56: EXP5667 | C56: for bank reconciliation-T24 INST. 2 LOANFLEET00001041 T24Batch-new dyna -- | E56: 3938.28 | F56: 0 | G56: =IF(AND(E56="",F56=""),"",G55+E56-F56) -> -21377.28
A57: 29/08/2025 | B57: EXP5667 | C57: for bank reconciliation-T24 INST. 2 LOANFLEET00001041 T24Batch-new dyna- | E57: 3938.28 | F57: 0 | G57: =IF(AND(E57="",F57=""),"",G56+E57-F57) -> -17439
A58: 31/08/2025 | B58: EXP5670 | C58: 9131082500538722/HANI AHMED ALSHUWKAIKHAT/l- | E58: 5000 | F58: 0 | G58: =IF(AND(E58="",F58=""),"",G57+E58-F58) -> -12439
A59: 31/08/2025 | B59: JN10840 | C59: BANK POS-AKMAL | E59: 0 | F59: 141 | G59: =IF(AND(E59="",F59=""),"",G58+E59-F59) -> -12580
A60: 31/08/2025 | C60: BANK TRANSFER-SHAMEER RIYADH -RECIEPT NOT RECEIVED | E60: 345 | G60: =IF(AND(E60="",F60=""),"",G59+E60-F60) -> -12235
A61: 45666 | B61: JN11253 | C61: BANK TRANSFER-KHALID | E61: 0 | F61: 242 | G61: =IF(AND(E61="",F61=""),"",G60+E61-F61) -> -12477
A62: 45666 | B62: JN11306 | C62: BANK POS SHAMEER-RIYADH | E62: 0 | F62: 351 | G62: =IF(AND(E62="",F62=""),"",G61+E62-F62) -> -12828
A63: 45666 | B63: JN11306 | C63: BANK POS SHAMEER-RIYADH | E63: 0 | F63: 75 | G63: =IF(AND(E63="",F63=""),"",G62+E63-F63) -> -12903
A64: 45666 | B64: JN11307 | C64: BANK POS SHAMEER-RIYADH | E64: 0 | F64: 195.22 | G64: =IF(AND(E64="",F64=""),"",G63+E64-F64) -> -13098.22
A65: 45697 | B65: JN11245 | C65: BANK POS-KHALID | E65: 0 | F65: 232.53 | G65: =IF(AND(E65="",F65=""),"",G64+E65-F65) -> -13330.75
A66: 45756 | B66: JN11254 | C66: BANK TRANSFER-KHALID | E66: 0 | F66: 289.97 | G66: =IF(AND(E66="",F66=""),"",G65+E66-F66) -> -13620.72
A67: 45756 | B67: JN11297 | C67: BANK POS-SHAMEER-RIYADH | E67: 0 | F67: 3488.68 | G67: =IF(AND(E67="",F67=""),"",G66+E67-F67) -> -17109.4
A68: 45786 | B68: JN11246 | C68: BANK POS-KHALID | E68: 0 | F68: 401.98 | G68: =IF(AND(E68="",F68=""),"",G67+E68-F68) -> -17511.38
A69: 45817 | B69: JN11298 | C69: BANK POS-SHAMEER-RIYADH | E69: 0 | F69: 1192 | G69: =IF(AND(E69="",F69=""),"",G68+E69-F69) -> -18703.38
A70: 45817 | B70: JN11291 | C70: BANK TRANSFER-SHAMEER RIYADH | E70: 0 | F70: 1991.84 | G70: =IF(AND(E70="",F70=""),"",G69+E70-F70) -> -20695.22
A71: 45847 | B71: JN11299 | C71: BANK POS-SHAMEER-RIYADH | E71: 0 | F71: 476 | G71: =IF(AND(E71="",F71=""),"",G70+E71-F71) -> -21171.22
A72: 45847 | B72: JN11361 | C72: BANK TRANSFER-ARSHADH | E72: 0 | F72: 3794 | G72: =IF(AND(E72="",F72=""),"",G71+E72-F72) -> -24965.22
... A79: 45970 | B79: JN11300 | C79: BANK POS-SHAMEER-RIYADH | E79: 0 | F79: 1175 | G79: =IF(AND(E79="",F79=""),"",G78+E79-F79) -> -31688.9
A80: 13/09/2025 | B80: JN11248 | C80: BANK POS-KHALID | E80: 0 | F80: 293 | G80: =IF(AND(E80="",F80=""),"",G79+E80-F80) -> -31981.9
A81: 13/09/2025 | B81: JN11248 | C81: BANK POS-KHALID | E81: 0 | F81: 108.98 | G81: =IF(AND(E81="",F81=""),"",G80+E81-F81) -> -32090.88
A82: 14/09/2025 | B82: JN11256 | C82: BANK TRANSFER-KHALID | E82: 0 | F82: 4128 | G82: =IF(AND(E82="",F82=""),"",G81+E82-F82) -> -36218.88
A83: 14/09/2025 | B83: JN11311 | C83: BANK POS-SHAMEER HAFAR | E83: 0 | F83: 1145 | G83: =IF(AND(E83="",F83=""),"",G82+E83-F83) -> -37363.88
A84: 15/09/2025 | B84: JN11301 | C84: BANK POS-SHAMEER-RIYADH | E84: 0 | F84: 223.73 | G84: =IF(AND(E84="",F84=""),"",G83+E84-F84) -> -37587.61
A85: 15/09/2025 | B85: JN11284 | C85: BANK TRANSFER-SHAMEER RIYADH | E85: 0 | F85: 2449.9 | G85: =IF(AND(E85="",F85=""),"",G84+E85-F85) -> -40037.51
A86: 15/09/2025 | B86: JN11257 | C86: BANK TRANSFER-KHALID | E86: 0 | F86: 460 | G86: =IF(AND(E86="",F86=""),"",G85+E86-F86) -> -40497.51
A87: 16/09/2025 | B87: JN11249 | C87: BANK POS-KHALID | E87: 0 | F87: 126 | G87: =IF(AND(E87="",F87=""),"",G86+E87-F87) -> -40623.51
A88: 16/09/2025 | B88: JN11258 | C88: BANK TRANSFER-KHALID | E88: 0 | F88: 2762 | G88: =IF(AND(E88="",F88=""),"",G87+E88-F88) -> -43385.51
A89: 16/09/2025 | B89: JN11259 | C89: BANK TRANSFER-KHALID | E89: 0 | F89: 263 | G89: =IF(AND(E89="",F89=""),"",G88+E89-F89) -> -43648.51
A90: 16/09/2025 | B90: JN11231 | C90: BANK POS-SHAFI | E90: 0 | F90: 1067 | G90: =IF(AND(E90="",F90=""),"",G89+E90-F90) -> -44715.51
A91: 17/09/2025 | B91: JN11285 | C91: BANK TRANSFER-SHAMEER RIYADH | E91: 0 | F91: 385 | G91: =IF(AND(E91="",F91=""),"",G90+E91-F91) -> -45100.51
... A100: 20/09/2025 | B100: JN11326 | C100: BANK POS-AKMAL | E100: 0 | F100: 874.88 | G100: =IF(AND(E100="",F100=""),"",G99+E100-F100) -> -53952.42
A101: 21/09/2025 | B101: JN11261 | C101: BANK TRANSFER-KHALID | E101: 0 | F101: 327
A102: 21/09/2025 | B102: JN11262 | C102: BANK TRANSFER-KHALID | E102: 0 | F102: 562
A103: 21/09/2025 | B103: JN11322 | C103: BANK TRANSFER-SHAMEER HAFAR | E103: 0 | F103: 913
A104: 22/09/2025 | B104: JN11232 | C104: BANK POS-SHAFI | E104: 0 | F104: 300
A105: 22/09/2025 | B105: JN11266 | C105: BANK TRANSFER-KHALID | E105: 0 | F105: 2112
A106: 22/09/2025 | B106: JN11333 | C106: BANK TRANSFER-AKMAL | E106: 0 | F106: 225
A107: 22/09/2025 | B107: JN11339 | C107: BANK TRANSFER-AKMAL | E107: 0 | F107: 2190.15
A108: 23/09/2025 | B108: JN11321 | C108: BANK TRANSFER-SHAMEER HAFAR | E108: 0 | F108: 128
A109: 23/09/2025 | B109: JN11241 | C109: BANK TRANSFER -SHAFI | E109: 0 | F109: 953.06
A110: 23/09/2025 | B110: JN11264 | C110: BANK TRANSFER-KHALID | E110: 0 | F110: 459.94
A111: 24/09/2025 | B111: JN11242 | C111: BANK TRANSFER -SHAFI | E111: 0 | F111: 320
A112: 25/09/2025 | B112: JN11042 | C112: BANK CHEQUE-DHIYA | E112: 1939.88 | F112: 0
... A145: 30/09/2025 | B145: JN11305 | C145: BANK POS-SHAMEER-RIYADH | E145: 0 | F145: 900
C146: BANK TRANSFER-SHAMEER RIYADH RECIEPT NOT RECEIVED | E146: 109
C147: BANK CHARGES | E147: 48

Sheet Outstanding_SEP-2025
A1: CUSTOMER OUTSTANDING - SEP-2025
A3: Salesman | B3: Total Outstanding | C3: No. of Customers | D3: Average
A4: Nidheesh | B4: =SUMIF($D$19:$D$502,A4,$G$19:$G$502) -> 72379.87 | C4: =COUNTIF($D$19:$D$502,A4) -> 47 | D4: =IFERROR(B4/C4,0) -> 1539.9972
A5: Jaseel | B5: =SUMIF($D$19:$D$502,A5,$G$19:$G$502) -> 23755.49 | C5: =COUNTIF($D$19:$D$502,A5) -> 21 | D5: =IFERROR(B5/C5,0) -> 1131.2138
A6: Bassam | B6: =SUMIF($D$19:$D$502,A6,$G$19:$G$502) -> 24945 | C6: =COUNTIF($D$19:$D$502,A6) -> 17 | D6: =IFERROR(B6/C6,0) -> 1467.3529
A7: akmal | B7: =SUMIF($D$19:$D$502,A7,$G$19:$G$502) -> 54291.15 | C7: =COUNTIF($D$19:$D$502,A7) -> 23 | D7: =IFERROR(B7/C7,0) -> 2360.4848
A8: arshad | B8: =SUMIF($D$19:$D$502,A8,$G$19:$G$502) -> 343351.34 | C8: =COUNTIF($D$19:$D$502,A8) -> 29 | D8: =IFERROR(B8/C8,0) -> 11839.701
A9: Shameer riyadh | B9: =SUMIF($D$19:$D$502,A9,$G$19:$G$502) -> 77103.34 | C9: =COUNTIF($D$19:$D$502,A9) -> 61 | D9: =IFERROR(B9/C9,0) -> 1263.9892
A10: company sales | B10: =SUMIF($D$19:$D$502,A10,$G$19:$G$502) -> 1068473.3 | C10: =COUNTIF($D$19:$D$502,A10) -> 15 | D10: =IFERROR(B10/C10,0) -> 71231.553
A11: shafi | B11: =SUMIF($D$19:$D$502,A11,$G$19:$G$502) -> 17862.18 | C11: =COUNTIF($D$19:$D$502,A11) -> 35 | D11: =IFERROR(B11/C11,0) -> 510.348
A12: ashik | B12: =SUMIF($D$19:$D$502,A12,$G$19:$G$502) -> 15423.13 | C12: =COUNTIF($D$19:$D$502,A12) -> 21 | D12: =IFERROR(B12/C12,0) -> 734.43476
A13: dhiya | B13: =SUMIF($D$19:$D$502,A13,$G$19:$G$502) -> 235777.05 | C13: =COUNTIF($D$19:$D$502,A13) -> 21 | D13: =IFERROR(B13/C13,0) -> 11227.479
A14: SALMAN | B14: =SUMIF($D$19:$D$502,A14,$G$19:$G$502) -> 0 | C14: =COUNTIF($D$19:$D$502,A14) -> 0 | D14: =IFERROR(B14/C14,0) -> 0
A15: samir | B15: =SUMIF($D$19:$D$502,A15,$G$19:$G$502) -> 5260 | C15: =COUNTIF($D$19:$D$502,A15) -> 7 | D15: =IFERROR(B15/C15,0) -> 751.42857
A16: TOTAL | B16: =SUM(B4:B15) -> 1938621.8 | C16: =SUM(C4:C15) -> 297 | D16: =IFERROR(B16/C16,0) -> 6527.3463
A18: Customer Code | B18: Customer Name | C18: Area | D18: Salesman | E18: Invoice Amount | F18: Paid Amount | G18: Balance | H18: Days
A19: CUST63 | B19: Saudi marketting | C19: Al Ahsa-1 | D19: Jaseel | E19: 2241.7 | G19: =IF(E19="","",E19-F19) -> 2241.7
A20: CUST80 | B20: Jassim Ali AL rasheed central markets | C20: Al Ahsa-1 | D20: Jaseel | E20: 1003.85 | G20: =IF(E20="","",E20-F20) -> 1003.85
A21: CUST84 | B21: Najmath AL khayrath | C21: Al Ahsa-1 | D21: Jaseel | E21: 1939.7 | G21: =IF(E21="","",E21-F21) -> 1939.7
A22: CUST201 | B22: Rainbow for food minimarket | C22: Al Ahsa-1 | D22: Jaseel | E22: 91.98 | G22: =IF(E22="","",E22-F22) -> 91.98
A23: CUST204 | B23: Thamveenath Noorul usam | C23: Al Ahsa-1 | D23: Jaseel | E23: 1460.78 | G23: =IF(E23="","",E23-F23) -> 1460.78
A24: CUST437 | B24: Aswaq sahab alhadid | C24: Al Ahsa-1 | D24: Jaseel | E24: 953.87 | G24: =IF(E24="","",E24-F24) -> 953.87
A25: CUST515 | B25: Hoor altamayuz grocery | C25: Al Ahsa-1 | D25: Jaseel | E25: 123.97 | G25: =IF(E25="","",E25-F25) -> 123.97
A26: CUST520 | B26: Ahdaf al asima tradinng Co. | C26: Al Ahsa-1 | D26: Jaseel | E26: 1225.82 | G26: =IF(E26="","",E26-F26) -> 1225.82
A27: CUST561 | B27: Grocery naster | C27: Al Ahsa-1 | D27: Jaseel | E27: 284.96 | G27: =IF(E27="","",E27-F27) -> 284.96
A28: CUST565 | B28: Sahab mart | C28: Al Ahsa-1 | D28: Jaseel | E28: 609.91 | G28: =IF(E28="","",E28-F28) -> 609.91
A29: CUST583 | B29: Road mart | C29: Al Ahsa-1 | D29: Jaseel | E29: 1001.86 | G29: =IF(E29="","",E29-F29) -> 1001.86
A30: CUST643 | B30: Ahdaf al asima trading co. | C30: Al Ahsa-1 | D30: Jaseel | E30: 324.94 | G30: =IF(E30="","",E30-F30) -> 324.94
... A428: CUST6009 | B428: WARATHATH AL MUSTLAK YANBU STREET LABAN | C428: Riyadh | D428: khalid | E428: 91.98 | G428: =IF(E428="","",E428-F428) -> 91.98
G429: =IF(E429="","",E429-F429)
G430: =IF(E430="","",E430-F430)
G431: =IF(E431="","",E431-F431)
G432: =IF(E432="","",E432-F432)
G433: =IF(E433="","",E433-F433)
G434: =IF(E434="","",E434-F434)
G435: =IF(E435="","",E435-F435)
G436: =IF(E436="","",E436-F436)
G437: =IF(E437="","",E437-F437)
G438: =IF(E438="","",E438-F438)
G439: =IF(E439="","",E439-F439)
G440: =IF(E440="","",E440-F440)
... G502: =IF(E502="","",E502-F502)
A503: GRAND TOTAL | E503: =SUM(E19:E502) -> 2023784.3 | F503: =SUM(F19:F502) -> 0 | G503: =SUM(G19:G502) -> 2023784.3

Sheet Banks_AUG-2025
A1: BANK SUMMARY - AUG-2025
A3: Bank Name | B3: Opening Balance | C3: Total Received | D3: Bank Charges | E3: Total Payments | F3: Closing Balance | G3: Notes
A4: Alrajhi-1097 | B4: 200148.5 | C4: 761851.08 | D4: 3163.93 | E4: 228323.93 | F4: =B4+C4-D4-E4 -> 730511.72
A5: Alrajhi-new | B5: 439596.55 | C5: 173964.23 | F5: =B5+C5-D5-E5 -> 613560.78
A6: SNB Al Ahsa Branch | B6: 1314787.1 | C6: 456399.24 | D6: 362.25 | E6: 1000000 | F6: =B6+C6-D6-E6 -> 770824.04
A7: Albilad | B7: 675194.19 | C7: 1745450 | D7: 120.75 | E7: 2086644.4 | F7: =B7+C7-D7-E7 -> 333879.01
A9: SUB-TOTAL SAR | B9: =SUM(B4:B7) -> 2629726.3 | C9: =SUM(C4:C7) -> 3137664.5 | D9: =SUM(D4:D7) -> 3646.93 | E9: =SUM(E4:E7) -> 3314968.4 | F9: =SUM(F4:F7) -> 2448775.5
A11: USD ACCOUNTS
A12: Bank Name | B12: Opening | C12: Amount Received | D12: Bank Charge | E12: Payment | F12: Balance | G12: Notes
A13: Albilad USD | B13: 371.25 | C13: 434700 | D13: 61.32 | E13: 434586.45 | F13: =B13+C13-D13-E13 -> 423.48
A15: SUB-TOTAL USD | B15: =SUM(B13) -> 371.25 | C15: =SUM(C13) -> 434700 | D15: =SUM(D13) -> 61.32 | E15: =SUM(E13) -> 434586.45 | F15: =SUM(F13) -> 423.48
A17: GRAND TOTAL (SAR + USD Converted) | B17: =B9+B15*3.75 -> 2631118.5 | C17: =C9+C15*3.75 -> 4767789.5 | D17: =D9+D15*3.75 -> 3876.88 | E17: =E9+E15*3.75 -> 4944667.5 | F17: =F9+F15*3.75 -> 2450363.6
A19: SUMMARY
A20: Total Bank Balance (SAR): | C20: =F17 -> 2450363.6

Sheet Advances_AUG-2025
A1: ADVANCE RECONCILIATION - AUG-2025
A3: OPENING BALANCE | B3: 452575.39 | D3: CLOSING BALANCE | E3: =164800.84+SUM(E7:E101) -> 473840.39
A5: TRANSACTIONS
A6: Date | B6: Voucher No | C6: Description | D6: Person/Party | E6: Advance Given | F6: Amount Settled | G6: Running Balance
A7: 17/04/2024 | B7: EXP3391 | C7: Shirfan - Cash withdraw -- | E7: 1500 | G7: =IF(E7="","",B3+E7-F7) -> 454075.39 | H7: =IF(B7="","",IF(IFERROR(MATCH(B7,'Advances_JULY-2025'!B:B,0),0)>0,"C/F","NEW")) -> NEW
A8: 27/05/2024 | B8: EXP3462 | C8: THOYYIB VEHICLE WINGE EXP- | E8: 350 | G8: =IF(E8="","",G7+E8-F8) -> 454425.39 | H8: =IF(B8="","",IF(IFERROR(MATCH(B8,'Advances_JULY-2025'!B:B,0),0)>0,"C/F","NEW")) -> NEW
A9: 27/05/2024 | B9: EXP3462 | C9: ADVANCES -THOYYIBE VEHICLE COMPLAINT- | E9: 143.48 | G9: =IF(E9="","",G8+E9-F9) -> 454568.87 | H9: =IF(B9="","",IF(IFERROR(MATCH(B9,'Advances_JULY-2025'!B:B,0),0)>0,"C/F","NEW")) -> NEW
A10: 27/05/2024 | B10: EXP3462 | C10: ADVANCES -THOYYIBE VEHICLE COMPLAINT- | E10: 600 | G10: =IF(E10="","",G9+E10-F10) -> 455168.87 | H10: =IF(B10="","",IF(IFERROR(MATCH(B10,'Advances_JULY-2025'!B:B,0),0)>0,"C/F","NEW")) -> NEW
A11: 16/06/2024 | B11: JN5365 | C11: COLLECTION CASH TAKEN BY HANI | E11: 34000 | G11: =IF(E11="","",G10+E11-F11) -> 489168.87 | H11: =IF(B11="","",IF(IFERROR(MATCH(B11,'Advances_JULY-2025'!B:B,0),0)>0,"C/F","NEW")) -> NEW
A12: 24/06/2024 | B12: EXP3614 | C12: ADVANCE-SALMANUL FARIZ-RIYADH- | E12: 500 | G12: =IF(E12="","",G11+E12-F12) -> 489668.87 | H12: =IF(B12="","",IF(IFERROR(MATCH(B12,'Advances_JULY-2025'!B:B,0),0)>0,"C/F","NEW")) -> NEW
A13: 45298 | B13: EXP3645 | C13: ASHIK-ADVANCE- | E13: 4000 | G13: =IF(E13="","",G12+E13-F13) -> 493668.87 | H13: =IF(B13="","",IF(IFERROR(MATCH(B13,'Advances_JULY-2025'!B:B,0),0)>0,"C/F","NEW")) -> NEW
A14: 45450 | B14: EXP3699 | C14: FT24188664289852 Ben WHITE GRAPHICS-ADVANCE FOR RECEPTION WORK- | E14: 2790 | G14: =IF(E14="","",G13+E14-F14) -> 496458.87 | H14: =IF(B14="","",IF(IFERROR(MATCH(B14,'Advances_JULY-2025'!B:B,0),0)>0,"C/F","NEW")) -> NEW
A15: 13/08/2024 | B15: EXP4197 | C15: AL JARAHA ADVANCE PAYMENT-METAL DETECTOR AND HIGHSPEED PACKING MACHINE-FT24226303374754- | E15: 74656.7 | G15: =IF(E15="","",G14+E15-F15) -> 571115.57 | H15: =IF(B15="","",IF(IFERROR(MATCH(B15,'Advances_JULY-2025'!B:B,0),0)>0,"C/F","NEW")) -> NEW
A16: 13/08/2024 | B16: EXP4198 | C16: AL JARAHA ADVANCE PAYMENT-METAL DETECTOR AND HIGHSPEED PACKING MACHINE-FT24226094147820- | E16: 25655.23 | G16: =IF(E16="","",G15+E16-F16) -> 596770.8 | H16: =IF(B16="","",IF(IFERROR(MATCH(B16,'Advances_JULY-2025'!B:B,0),0)>0,"C/F","NEW")) -> NEW
A17: 27/08/2024 | B17: EXP4327 | C17: FT24240219059921 Ben EGYPTIAN SAUDI IMPORT EXPORT PAPER-DOUBLE TRANSFER-AMOUNT- | E17: 5000 | G17: =IF(E17="","",G16+E17-F17) -> 601770.8 | H17: =IF(B17="","",IF(IFERROR(MATCH(B17,'Advances_JULY-2025'!B:B,0),0)>0,"C/F","NEW")) -> NEW
A18: 13/10/2024 | B18: EXP4386 | C18: SHIRFAN ADVANCE FROM NIDHEESH COLLECTION- | E18: 4650 | G18: =IF(E18="","",G17+E18-F18) -> 606420.8 | H18: =IF(B18="","",IF(IFERROR(MATCH(B18,'Advances_JULY-2025'!B:B,0),0)>0,"C/F","NEW")) -> NEW
A19: 20/10/2024 | B19: EXP4423 | C19: THOYYIB ADVANCE QASEEM NEW ROUTE- | E19: 500 | G19: =IF(E19="","",G18+E19-F19) -> 606920.8 | H19: =IF(B19="","",IF(IFERROR(MATCH(B19,'Advances_JULY-2025'!B:B,0),0)>0,"C/F","NEW")) -> NEW
A20: 31/10/2024 | C20: MANAFIZ RENT DMM ROUTE | E20: 16857.45 | G20: =IF(E20="","",G19+E20-F20) -> 623778.25 | H20: =IF(B20="","",IF(IFERROR(MATCH(B20,'Advances_JULY-2025'!B:B,0),0)>0,"C/F","NEW"))
A21: 45546 | B21: EXP4569 | C21: SALMAN FARIZ ADVANCE FROM NIDHEESH COLLECTION- | E21: 4450 | G21: =IF(E21="","",G20+E21-F21) -> 628228.25 | H21: =IF(B21="","",IF(IFERROR(MATCH(B21,'Advances_JULY-2025'!B:B,0),0)>0,"C/F","NEW")) -> NEW
A22: 45637 | B22: EXP4573 | C22: ASLAM ADVANCE TO SALMAN FARIZ- | E22: 80 | G22: =IF(E22="","",G21+E22-F22) -> 628308.25 | H22: =IF(B22="","",IF(IFERROR(MATCH(B22,'Advances_JULY-2025'!B:B,0),0)>0,"C/F","NEW")) -> NEW
A23: 45577 | B23: EXP4697 | C23: AL JARAHA ADVANCE PAYMENT-METAL DETECTOR AND HIGHSPEED PACKING MACHINE-FT24226094147820- | E23: 49001.48 | G23: =IF(E23="","",G22+E23-F23) -> 677309.73 | H23: =IF(B23="","",IF(IFERROR(MATCH(B23,'Advances_JULY-2025'!B:B,0),0)>0,"C/F","NEW")) -> NEW
A24: 25/12/2024 | B24: EXP4747 | C24: SHIRFAN ADVANCE NIDHEESH COLLECTION- | E24: 300 | G24: =IF(E24="","",G23+E24-F24) -> 677609.73 | H24: =IF(B24="","",IF(IFERROR(MATCH(B24,'Advances_JULY-2025'!B:B,0),0)>0,"C/F","NEW")) -> NEW
A25: 30/12/2024 | B25: EXP4756 | C25: FUEL-ADVANCE-FAWAS- | E25: 150 | G25: =IF(E25="","",G24+E25-F25) -> 677759.73 | H25: =IF(B25="","",IF(IFERROR(MATCH(B25,'Advances_JULY-2025'!B:B,0),0)>0,"C/F","NEW")) -> NEW
A26: 14/01/2025 | B26: EXP4790 | C26: Al jara machinary payment- | E26: 51310.45 | G26: =IF(E26="","",G25+E26-F26) -> 729070.18 | H26: =IF(B26="","",IF(IFERROR(MATCH(B26,'Advances_JULY-2025'!B:B,0),0)>0,"C/F","NEW")) -> NEW
A27: 45749 | B27: EXP4884 | C27: PURCHASE ADVANCE-ASHOK- | E27: 200 | G27: =IF(E27="","",G26+E27-F27) -> 729270.18 | H27: =IF(B27="","",IF(IFERROR(MATCH(B27,'Advances_JULY-2025'!B:B,0),0)>0,"C/F","NEW")) -> NEW
A28: 16/02/2025 | B28: EXP4912 | C28: NNA REPAIR EXP-ASLAM- | E28: 334.8 | G28: =IF(E28="","",G27+E28-F28) -> 729604.98 | H28: =IF(B28="","",IF(IFERROR(MATCH(B28,'Advances_JULY-2025'!B:B,0),0)>0,"C/F","NEW")) -> NEW
A29: 16/02/2025 | B29: EXP4912 | C29: NNA REPAIR EXP-AKMAL- | E29: 300 | G29: =IF(E29="","",G28+E29-F29) -> 729904.98 | H29: =IF(B29="","",IF(IFERROR(MATCH(B29,'Advances_JULY-2025'!B:B,0),0)>0,"C/F","NEW")) -> NEW
A30: 16/02/2025 | B30: EXP4912 | C30: NNA REPAIR EXP-ASLAM- | E30: 350 | G30: =IF(E30="","",G29+E30-F30) -> 730254.98 | H30: =IF(B30="","",IF(IFERROR(MATCH(B30,'Advances_JULY-2025'!B:B,0),0)>0,"C/F","NEW")) -> NEW
A31: 45752 | B31: EXP5155 | C31: PURCHASE ADVANCE-ASLAM- | E31: 200 | G31: =IF(E31="","",G30+E31-F31) -> 730454.98 | H31: =IF(B31="","",IF(IFERROR(MATCH(B31,'Advances_JULY-2025'!B:B,0),0)>0,"C/F","NEW")) -> NEW
A32: 24/05/2025 | B32: EXP5247 | C32: SHIRFAN ADVANCES- | E32: 170 | G32: =IF(E32="","",G31+E32-F32) -> 730624.98 | H32: =IF(B32="","",IF(IFERROR(MATCH(B32,'Advances_JULY-2025'!B:B,0),0)>0,"C/F","NEW")) -> NEW
A33: 31/05/2025 | C33: VEHICLE SERVICE BALANCE-SHIRFAN SIR | E33: 219 | G33: =IF(E33="","",G32+E33-F33) -> 730843.98 | H33: =IF(B33="","",IF(IFERROR(MATCH(B33,'Advances_JULY-2025'!B:B,0),0)>0,"C/F","NEW"))
A34: 45997 | B34: EXP5275 | C34: ADVANCE-SALMAN SIR- | E34: 260.96 | G34: =IF(E34="","",G33+E34-F34) -> 731104.94 | H34: =IF(B34="","",IF(IFERROR(MATCH(B34,'Advances_JULY-2025'!B:B,0),0)>0,"C/F","NEW")) -> NEW
A35: 26/06/2025 | B35: EXP5389 | C35: BAYCITY BALANCE-AMOUNT PAID-20000 SETTLED-11000 - | E35: 9000 | G35: =IF(E35="","",G34+E35-F35) -> 740104.94 | H35: =IF(B35="","",IF(IFERROR(MATCH(B35,'Advances_JULY-2025'!B:B,0),0)>0,"C/F","NEW")) -> NEW
A36: 29/06/2025 | B36: EXP5402 | C36: SALARY ADVANCE-ASLAM- | E36: 100 | G36: =IF(E36="","",G35+E36-F36) -> 740204.94 | H36: =IF(B36="","",IF(IFERROR(MATCH(B36,'Advances_JULY-2025'!B:B,0),0)>0,"C/F","NEW")) -> NEW
A37: 21/07/2025 | B37: EXP5475 | C37: SHIRFAN SIR ADVANCE- | E37: 200 | G37: =IF(E37="","",G36+E37-F37) -> 740404.94 | H37: =IF(B37="","",IF(IFERROR(MATCH(B37,'Advances_JULY-2025'!B:B,0),0)>0,"C/F","NEW")) -> NEW
A38: 45816 | B38: EXP5575 | C38: ADVANCES- | E38: 8660 | G38: =IF(E38="","",G37+E38-F38) -> 749064.94 | H38: =IF(B38="","",IF(IFERROR(MATCH(B38,'Advances_JULY-2025'!B:B,0),0)>0,"C/F","NEW")) -> NEW
A39: 17/08/2025 | B39: EXP5588 | C39: SHAFI VEHICLE REPAIR ADVANCE- | E39: 5000 | G39: =IF(E39="","",G38+E39-F39) -> 754064.94 | H39: =IF(B39="","",IF(IFERROR(MATCH(B39,'Advances_JULY-2025'!B:B,0),0)>0,"C/F","NEW")) -> NEW
A40: 19/08/2025 | B40: EXP5590 | C40: SUSHI ADVANCE -LABOUR CHARGE-09-08-2025 TO 14-08-2025-TOTAL AMOUNT-7500/-- | E40: 1500 | G40: =IF(E40="","",G39+E40-F40) -> 755564.94 | H40: =IF(B40="","",IF(IFERROR(MATCH(B40,'Advances_JULY-2025'!B:B,0),0)>0,"C/F","NEW")) -> NEW
A41: 19/08/2025 | B41: EXP5590 | C41: SALMAN SIR ADVANCE FOR TRAFFIC VIOLATION- | E41: 450 | G41: =IF(E41="","",G40+E41-F41) -> 756014.94 | H41: =IF(B41="","",IF(IFERROR(MATCH(B41,'Advances_JULY-2025'!B:B,0),0)>0,"C/F","NEW")) -> NEW
A42: 21/08/2025 | B42: EXP5603 | C42: SALMAN SIR ADVANCE-NIDHEESH- | E42: 100 | G42: =IF(E42="","",G41+E42-F42) -> 756114.94 | H42: =IF(B42="","",IF(IFERROR(MATCH(B42,'Advances_JULY-2025'!B:B,0),0)>0,"C/F","NEW")) -> NEW
A43: 30/08/2025 | B43: EXP5630 | C43: PURCHASE ADVANCE-SADATH- | E43: 2000 | G43: =IF(E43="","",G42+E43-F43) -> 758114.94 | H43: =IF(B43="","",IF(IFERROR(MATCH(B43,'Advances_JULY-2025'!B:B,0),0)>0,"C/F","NEW")) -> NEW
A44: 31/08/2025 | B44: EXP5631 | C44: PURCHASE ADVANCE-SABARI- | E44: 1000 | G44: =IF(E44="","",G43+E44-F44) -> 759114.94 | H44: =IF(B44="","",IF(IFERROR(MATCH(B44,'Advances_JULY-2025'!B:B,0),0)>0,"C/F","NEW")) -> NEW
A45: 31/08/2025 | B45: EXP5631 | C45: PURCHASE ADVANCE-SABARI- | E45: 500 | G45: =IF(E45="","",G44+E45-F45) -> 759614.94 | H45: =IF(B45="","",IF(IFERROR(MATCH(B45,'Advances_JULY-2025'!B:B,0),0)>0,"C/F","NEW")) -> NEW
A46: 31/08/2025 | B46: EXP5631 | C46: PURCHASE ADVANCE-SABARI- | E46: 2000 | G46: =IF(E46="","",G45+E46-F46) -> 761614.94 | H46: =IF(B46="","",IF(IFERROR(MATCH(B46,'Advances_JULY-2025'!B:B,0),0)>0,"C/F","NEW")) -> NEW
G47: =IF(E47="","",G46+E47-F47)
G48: =IF(E48="","",G47+E48-F48)
G49: =IF(E49="","",G48+E49-F49)
G50: =IF(E50="","",G49+E50-F50)
G51: =IF(E51="","",G50+E51-F51)
G52: =IF(E52="","",G51+E52-F52)
G53: =IF(E53="","",G52+E53-F53)
G54: =IF(E54="","",G53+E54-F54)
G55: =IF(E55="","",G54+E55-F55)
G56: =IF(E56="","",G55+E56-F56)
G57: =IF(E57="","",G56+E57-F57)
G58: =IF(E58="","",G57+E58-F58)
... G100: =IF(E100="","",G99+E100-F100)
A102: TOTAL | E102: =SUM(E7:E101) -> 309039.55 | F102: =SUM(F7:F101) -> 0

Sheet Suspense_AUG-2025
A1: SUSPENSE RECONCILIATION - AUG-2025
A3: OPENING BALANCE | B3: -289792.79 | D3: CLOSING BALANCE | E3: =-17267.64+SUM(E7:E1000)-SUM(F7:F1000) -> -61737.78
A5: UNIDENTIFIED TRANSACTIONS
A6: Date | B6: Journal No | C6: Description | D6: Reference | E6: Debit | F6: Credit | G6: Running Balance
A7: 14/01/2025 | B7: JN8176 | C7: BANK TRANSFER-NIDHEEESH | E7: 0 | F7: 1 | G7: =IF(AND(E7="",F7=""),"",B3+E7-F7) -> -289793.79
A8: 19/01/2025 | B8: JN8400 | C8: BANK TRANSFER- | E8: 0 | F8: 2550 | G8: =IF(AND(E8="",F8=""),"",G7+E8-F8) -> -292343.79
A9: 45690 | B9: JN8696 | C9: BANK TRANSFER-NOT IDENTIFIED | E9: 0 | F9: 2500 | G9: =IF(AND(E9="",F9=""),"",G8+E9-F9) -> -294843.79
A10: 45750 | B10: JN9046 | C10: BANK TRANSFER-NOT IDENTIFIED | E10: 0 | F10: 2000 | G10: =IF(AND(E10="",F10=""),"",G9+E10-F10) -> -296843.79
A11: 13/03/2025 | C11: BANK TRANSFER-SHAREEF | E11: 201 | F11: 0 | G11: =IF(AND(E11="",F11=""),"",G10+E11-F11) -> -296642.79
A12: 45873 | B12: JN9444 | C12: BANK TRANSFER-NOT IDENTIFIED | E12: 0 | F12: 1500 | G12: =IF(AND(E12="",F12=""),"",G11+E12-F12) -> -298142.79
A13: 45965 | B13: JN9447 | C13: BANK-POS | E13: 0 | F13: 0.02 | G13: =IF(AND(E13="",F13=""),"",G12+E13-F13) -> -298142.81
A14: 20/04/2025 | B14: JN9451 | C14: BANK TRANSFER-NOT IDENTIFIED | E14: 0 | F14: 285.96 | G14: =IF(AND(E14="",F14=""),"",G13+E14-F14) -> -298428.77
A15: 20/04/2025 | B15: JN9452 | C15: BANK TRANSFER-NOT IDENTIFIED | E15: 0 | F15: 1380 | G15: =IF(AND(E15="",F15=""),"",G14+E15-F15) -> -299808.77
A16: 29/04/2025 | B16: JN9455 | C16: BANK TRANSFER-NOT IDENTIFIED | E16: 0 | F16: 1000 | G16: =IF(AND(E16="",F16=""),"",G15+E16-F16) -> -300808.77
A17: 45301 | B17: JN9330 | C17: UNKNOWN CREDIT-BILAD -OCTOBER | F17: 4000 | G17: =IF(AND(E17="",F17=""),"",G16+E17-F17) -> -304808.77
A18: 45721 | B18: JN9446 | C18: BANK POS | E18: 0 | F18: 0.01 | G18: =IF(AND(E18="",F18=""),"",G17+E18-F18) -> -304808.78
A19: 45782 | B19: JN9739 | C19: BANK TRANSFER- | E19: 0 | F19: 1600 | G19: =IF(AND(E19="",F19=""),"",G18+E19-F19) -> -306408.78
A20: 45996 | B20: JN9748 | C20: BANK TRANSFER- | E20: 0 | F20: 1000 | G20: =IF(AND(E20="",F20=""),"",G19+E20-F20) -> -307408.78
A21: 17/05/2025 | B21: JN9793 | C21: BANK TRANSFER- | E21: 0 | F21: 1389 | G21: =IF(AND(E21="",F21=""),"",G20+E21-F21) -> -308797.78
A22: 18/05/2025 | B22: JN9787 | C22: BANK POS-SHAREEF | E22: 0 | F22: 523.92 | G22: =IF(AND(E22="",F22=""),"",G21+E22-F22) -> -309321.7
A23: 23/05/2025 | B23: JN9795 | C23: BANK TRANSFER- | E23: 0 | F23: 1000 | G23: =IF(AND(E23="",F23=""),"",G22+E23-F23) -> -310321.7
A24: 27/05/2025 | B24: JN9831 | C24: BANK TRANSFER- | E24: 0 | F24: 1488 | G24: =IF(AND(E24="",F24=""),"",G23+E24-F24) -> -311809.7
A25: 45783 | B25: JN10142 | C25: BANK TRANSFER-NOT IDENTIFIED | E25: 0 | F25: 1005.88 | G25: =IF(AND(E25="",F25=""),"",G24+E25-F25) -> -312815.58
A26: 45906 | B26: JN10143 | C26: BANK POS-SHAREEF | E26: 0 | F26: 108.98 | G26: =IF(AND(E26="",F26=""),"",G25+E26-F26) -> -312924.56
A27: 19/06/2025 | B27: JN10145 | C27: BANK TRANSFER-NOT IDENTIFIED | E27: 0 | F27: 1020.84 | G27: =IF(AND(E27="",F27=""),"",G26+E27-F27) -> -313945.4
A28: 21/06/2025 | B28: JN10146 | C28: BANK | E28: 0 | F28: 0.01 | G28: =IF(AND(E28="",F28=""),"",G27+E28-F28) -> -313945.41
A29: 26/06/2025 | B29: JN10147 | C29: BANK TRANSFER-NOT IDENTIFIED | E29: 0 | F29: 290 | G29: =IF(AND(E29="",F29=""),"",G28+E29-F29) -> -314235.41
A30: 30/06/2025 | C30: BANK CHARGES | E30: 0 | F30: 29 | G30: =IF(AND(E30="",F30=""),"",G29+E30-F30) -> -314264.41
A31: 27/07/2025 | B31: JN10469 | C31: BANK TRANSFER NOT IDENTIFIED | E31: 0 | F31: 613 | G31: =IF(AND(E31="",F31=""),"",G30+E31-F31) -> -314877.41
A32: 28/07/2025 | B32: JN10466 | C32: BANK POS-SHAFI | E32: 0 | F32: 3111 | G32: =IF(AND(E32="",F32=""),"",G31+E32-F32) -> -317988.41
A33: 29/07/2025 | B33: JN10472 | C33: T24 INST. 1 LOANFLEET00001041 T24Batch-NEW DYNA- | E33: 3938.28 | F33: 0 | G33: =IF(AND(E33="",F33=""),"",G32+E33-F33) -> -314050.13
A34: 29/07/2025 | B34: JN10472 | C34: T24 INST. 1 LOANFLEET00001041 T24Batch-NEW DYNA- | E34: 3938.28 | F34: 0 | G34: =IF(AND(E34="",F34=""),"",G33+E34-F34) -> -310111.85
A35: 31/07/2025 | B35: JN10467 | C35: BANK POS-SHAFI | E35: 0 | F35: 579 | G35: =IF(AND(E35="",F35=""),"",G34+E35-F35) -> -310690.85
A36: 45755 | B36: JN10870 | C36: BANK TRANSFER-NOT IDENTIFIED | E36: 0 | F36: 789.88 | G36: =IF(AND(E36="",F36=""),"",G35+E36-F36) -> -311480.73
A37: 45785 | B37: JN10833 | C37: BANK POS-SMAEER HAFAR-2831 | E37: 0 | F37: 107 | G37: =IF(AND(E37="",F37=""),"",G36+E37-F37) -> -311587.73
A38: 45816 | B38: JN10850 | C38: BANK TRANSFER-SHAMEER HAFAR | E38: 0 | F38: 3200 | G38: =IF(AND(E38="",F38=""),"",G37+E38-F38) -> -314787.73
A39: 45816 | B39: JN10876 | C39: BANK TRANSFER-SAMEER HAFAR | E39: 0 | F39: 2754 | G39: =IF(AND(E39="",F39=""),"",G38+E39-F39) -> -317541.73
A40: 45877 | B40: JN10834 | C40: BANK POS-SMAEER HAFAR-2831 | E40: 0 | F40: 462 | G40: =IF(AND(E40="",F40=""),"",G39+E40-F40) -> -318003.73
A41: 45938 | B41: JN10835 | C41: BANK POS-SMAEER HAFAR-2831 | E41: 0 | F41: 799 | G41: =IF(AND(E41="",F41=""),"",G40+E41-F41) -> -318802.73
A42: 45999 | B42: JN10847 | C42: BANK TRANSFER-SAMEER HAFAR | E42: 0 | F42: 607 | G42: =IF(AND(E42="",F42=""),"",G41+E42-F42) -> -319409.73
A43: 45999 | B43: JN10871 | C43: BANK TRANSFER-NOT IDENTIFIED | E43: 0 | F43: 681.03 | G43: =IF(AND(E43="",F43=""),"",G42+E43-F43) -> -320090.76
A44: 45999 | B44: JN10878 | C44: BANK TRANSFER-NOT IDENTIFIED | E44: 0 | F44: 804.26 | G44: =IF(AND(E44="",F44=""),"",G43+E44-F44) -> -320895.02
A45: 18/08/2025 | B45: JN10836 | C45: BANK POS-SMAEER HAFAR-2831 | E45: 0 | F45: 935 | G45: =IF(AND(E45="",F45=""),"",G44+E45-F45) -> -321830.02
A46: 18/08/2025 | B46: JN10846 | C46: BANK TRANSFER-SAMEER HAFAR | E46: 0 | F46: 124 | G46: =IF(AND(E46="",F46=""),"",G45+E46-F46) -> -321954.02
A47: 19/08/2025 | B47: JN10872 | C47: BANK TRANSFER-SHAFI | E47: 0 | F47: 460 | G47: =IF(AND(E47="",F47=""),"",G46+E47-F47) -> -322414.02
A48: 20/08/2025 | B48: JN10844 | C48: BANK POS-SHAFI | E48: 0 | F48: 511 | G48: =IF(AND(E48="",F48=""),"",G47+E48-F48) -> -322925.02
A49: 20/08/2025 | B49: JN10848 | C49: BANK TRANSFER-SAMEER HAFAR | E49: 0 | F49: 2270 | G49: =IF(AND(E49="",F49=""),"",G48+E49-F49) -> -325195.02
A50: 23/08/2025 | B50: JN10660 | C50: BANK CHEQUE-DHIYA | E50: 6687.5 | F50: 0 | G50: =IF(AND(E50="",F50=""),"",G49+E50-F50) -> -318507.52
A51: 23/08/2025 | B51: JN10845 | C51: BANK POS-SHAFI | E51: 0 | F51: 300 | G51: =IF(AND(E51="",F51=""),"",G50+E51-F51) -> -318807.52
A52: 24/08/2025 | B52: JN10849 | C52: BANK TRANSFER-SHAMEER HAFAR | E52: 0 | F52: 2604 | G52: =IF(AND(E52="",F52=""),"",G51+E52-F52) -> -321411.52
A53: 24/08/2025 | B53: JN10879 | C53: BANK TRANSFER-NOT IDENTIFIED | E53: 0 | F53: 2237.16 | G53: =IF(AND(E53="",F53=""),"",G52+E53-F53) -> -323648.68
A54: 25/08/2025 | B54: JN10837 | C54: BANK POS-SMAEER HAFAR-2831 | E54: 0 | F54: 58 | G54: =IF(AND(E54="",F54=""),"",G53+E54-F54) -> -323706.68
A55: 25/08/2025 | B55: JN10873 | C55: BANK TRANSFER-NOT IDENTIFIED | E55: 0 | F55: 607.92 | G55: =IF(AND(E55="",F55=""),"",G54+E55-F55) -> -324314.6
A56: 25/08/2025 | B56: JN10874 | C56: BANK TRANSFER-NOT IDENTIFIED | E56: 0 | F56: 494.02 | G56: =IF(AND(E56="",F56=""),"",G55+E56-F56) -> -324808.62
... A68: 31/08/2025 | B68: JN10877 | C68: BANK TRANSFER-THOYYIB | E68: 0 | F68: 2213.7 | G68: =IF(AND(E68="",F68=""),"",G67+E68-F68) -> -314040.86
A69: 31/08/2025 | C69: BANK TRANSFER-SHAMEER RIYADH -RECIEPT NOT RECEIVED | E69: 1344 | G69: =IF(AND(E69="",F69=""),"",G68+E69-F69) -> -312696.86
A70: 31/08/2025 | C70: BANK TRANSFER-SHAMEER RIYADH -RECIEPT NOT RECEIVED | E70: 276 | G70: =IF(AND(E70="",F70=""),"",G69+E70-F70) -> -312420.86
A71: 31/08/2025 | C71: BANK TRANSFER-SHAMEER RIYADH -RECIEPT NOT RECEIVED | E71: 345 | G71: =IF(AND(E71="",F71=""),"",G70+E71-F71) -> -312075.86
C72: BANK CHARGES | E72: 48 | G72: =IF(AND(E72="",F72=""),"",G71+E72-F72) -> -312027.86
G73: =IF(AND(E73="",F73=""),"",G72+E73-F73)
G74: =IF(AND(E74="",F74=""),"",G73+E74-F74)
G75: =IF(AND(E75="",F75=""),"",G74+E75-F75)
G76: =IF(AND(E76="",F76=""),"",G75+E76-F76)
G77: =IF(AND(E77="",F77=""),"",G76+E77-F77)
G78: =IF(AND(E78="",F78=""),"",G77+E78-F78)
G79: =IF(AND(E79="",F79=""),"",G78+E79-F79)
G80: =IF(AND(E80="",F80=""),"",G79+E80-F80)
G81: =IF(AND(E81="",F81=""),"",G80+E81-F81)
G82: =IF(AND(E82="",F82=""),"",G81+E82-F82)
G83: =IF(AND(E83="",F83=""),"",G82+E83-F83)
G84: =IF(AND(E84="",F84=""),"",G83+E84-F84)
... G100: =IF(AND(E100="",F100=""),"",G99+E100-F100)
A102: TOTAL | E102: =SUM(E7:E101) -> 35254.31 | F102: =SUM(F7:F101) -> 57489.38

Sheet Advances_JAN-2025
A1: ADVANCE RECONCILIATION - JAN-2025
A3: OPENING BALANCE | B3: 163800.84 | D3: CLOSING BALANCE | E3: =164800.84+SUM(E7:E101) -> 479608.52
A5: TRANSACTIONS
A6: Date | B6: Voucher No | C6: Description | D6: Person/Party | E6: Advance Given | F6: Amount Settled | G6: Running Balance | H6: status
A7: 45447 | B7: EXP3275 | C7: CONSTRUCTION WORK ADVANCE RAJENDHRAN- | E7: 3000 | G7: =IF(E7="","",B$3+IF(H7="C/F",0,E7)-F7) -> 166800.84 | H7: =IF(B7="","","NEW") -> NEW
A8: 17/04/2024 | B8: EXP3295 | C8: TANJI BAO PAYMENT TO BE CHARGED TO BOILING POT- | E8: 8625 | G8: =IF(E8="","",G7+IF(H8="C/F",0,E8)-F8) -> 175425.84 | H8: =IF(B8="","","NEW") -> NEW
A9: 17/04/2024 | B9: EXP3391 | C9: Shirfan - Cash withdraw -- | E9: 1500 | G9: =IF(E9="","",G8+IF(H9="C/F",0,E9)-F9) -> 176925.84 | H9: =IF(B9="","","NEW") -> NEW
A10: 16/05/2024 | B10: EXP3422 | C10: sabari-seeds unloading staff refreshment drink- | E10: 20 | G10: =IF(E10="","",G9+IF(H10="C/F",0,E10)-F10) -> 176945.84 | H10: =IF(B10="","","NEW") -> NEW
A11: 27/05/2024 | B11: EXP3462 | C11: THOYYIB VEHICLE WINGE EXP- | E11: 350 | G11: =IF(E11="","",G10+IF(H11="C/F",0,E11)-F11) -> 177295.84 | H11: =IF(B11="","","NEW") -> NEW
A12: 27/05/2024 | B12: EXP3462 | C12: ADVANCES -THOYYIBE VEHICLE COMPLAINT- | E12: 143.48 | G12: =IF(E12="","",G11+IF(H12="C/F",0,E12)-F12) -> 177439.32 | H12: =IF(B12="","","NEW") -> NEW
A13: 27/05/2024 | B13: EXP3462 | C13: ADVANCES -THOYYIBE VEHICLE COMPLAINT- | E13: 600 | G13: =IF(E13="","",G12+IF(H13="C/F",0,E13)-F13) -> 178039.32 | H13: =IF(B13="","","NEW") -> NEW
A14: 45602 | B14: EXP3508 | C14: AMITHFOOD ADVANCE-SABARI- | E14: 15 | G14: =IF(E14="","",G13+IF(H14="C/F",0,E14)-F14) -> 178054.32 | H14: =IF(B14="","","NEW") -> NEW
A15: 16/06/2024 | B15: EXP3683 | C15: AIR TRANSPORTAION AIR LANKA- | E15: 2730 | G15: =IF(E15="","",G14+IF(H15="C/F",0,E15)-F15) -> 180784.32 | H15: =IF(B15="","","NEW") -> NEW
A16: 16/06/2024 | B16: JN5365 | C16: COLLECTION CASH TAKEN BY HANI | E16: 34000 | G16: =IF(E16="","",G15+IF(H16="C/F",0,E16)-F16) -> 214784.32 | H16: =IF(B16="","","NEW") -> NEW
A17: 24/06/2024 | B17: EXP3614 | C17: ADVANCE-SALMANUL FARIZ-RIYADH- | E17: 500 | G17: =IF(E17="","",G16+IF(H17="C/F",0,E17)-F17) -> 215284.32 | H17: =IF(B17="","","NEW") -> NEW
A18: 45298 | B18: EXP3645 | C18: ASHIK-ADVANCE- | E18: 4000 | G18: =IF(E18="","",G17+IF(H18="C/F",0,E18)-F18) -> 219284.32 | H18: =IF(B18="","","NEW") -> NEW
A19: 45358 | B19: EXP3654 | C19: SIVA RIYADH TRAVELING EXP ADVANCE-- | E19: 2000 | G19: =IF(E19="","",G18+IF(H19="C/F",0,E19)-F19) -> 221284.32 | H19: =IF(B19="","","NEW") -> NEW
A20: 45450 | B20: EXP3699 | C20: FT24188664289852 Ben WHITE GRAPHICS-ADVANCE FOR RECEPTION WORK- | E20: 2790 | G20: =IF(E20="","",G19+IF(H20="C/F",0,E20)-F20) -> 224074.32 | H20: =IF(B20="","","NEW") -> NEW
A21: 45603 | B21: EXP3749 | C21: FUEL ADVANCE-MUNEESH- | E21: 50 | G21: =IF(E21="","",G20+IF(H21="C/F",0,E21)-F21) -> 224124.32 | H21: =IF(B21="","","NEW") -> NEW
A22: 17/07/2024 | B22: EXP4088 | C22: Traffic Violati REF 5366217470-7023706836-TRAFFIC -NIDHEESH- | E22: 113 | G22: =IF(E22="","",G21+IF(H22="C/F",0,E22)-F22) -> 224237.32 | H22: =IF(B22="","","NEW") -> NEW
A23: 31/07/2024 | B23: EXP4021 | C23: FUEL-ADVANCE-NASAR- | E23: 100 | G23: =IF(E23="","",G22+IF(H23="C/F",0,E23)-F23) -> 224337.32 | H23: =IF(B23="","","NEW") -> NEW
A24: 45573 | B24: EXP4074 | C24: SARIKA TAXI EXP -- | E24: 60 | G24: =IF(E24="","",G23+IF(H24="C/F",0,E24)-F24) -> 224397.32 | H24: =IF(B24="","","NEW") -> NEW
A25: 13/08/2024 | B25: EXP4197 | C25: AL JARAHA ADVANCE PAYMENT-METAL DETECTOR AND HIGHSPEED PACKING MACHINE-FT24226303374754- | E25: 74656.7 | G25: =IF(E25="","",G24+IF(H25="C/F",0,E25)-F25) -> 299054.02 | H25: =IF(B25="","","NEW") -> NEW
A26: 13/08/2024 | B26: EXP4198 | C26: AL JARAHA ADVANCE PAYMENT-METAL DETECTOR AND HIGHSPEED PACKING MACHINE-FT24226094147820- | E26: 25655.23 | G26: =IF(E26="","",G25+IF(H26="C/F",0,E26)-F26) -> 324709.25 | H26: =IF(B26="","","NEW") -> NEW
A27: 27/08/2024 | B27: EXP4327 | C27: FT24240219059921 Ben EGYPTIAN SAUDI IMPORT EXPORT PAPER-DOUBLE TRANSFER-AMOUNT- | E27: 5000 | G27: =IF(E27="","",G26+IF(H27="C/F",0,E27)-F27) -> 329709.25 | H27: =IF(B27="","","NEW") -> NEW
A28: 29/08/2024 | B28: EXP4267 | C28: PURCHASE ADVANCE-FAWAS- | E28: 45 | G28: =IF(E28="","",G27+IF(H28="C/F",0,E28)-F28) -> 329754.25 | H28: =IF(B28="","","NEW") -> NEW
A29: 45326 | B29: EXP3255 | C29: FUEL EXP MUNEESH- | E29: 30 | G29: =IF(E29="","",G28+IF(H29="C/F",0,E29)-F29) -> 329784.25 | H29: =IF(B29="","","NEW") -> NEW
A30: 45605 | B30: EXP4358 | C30: Advances-Muneesh- | E30: 613.5 | G30: =IF(E30="","",G29+IF(H30="C/F",0,E30)-F30) -> 330397.75 | H30: =IF(B30="","","NEW") -> NEW
A31: 25/09/2024 | B31: EXP4401 | C31: TRAFFIC-VIOLATIONS- | E31: 113 | G31: =IF(E31="","",G30+IF(H31="C/F",0,E31)-F31) -> 330510.75 | H31: =IF(B31="","","NEW") -> NEW
A32: 25/09/2024 | B32: EXP4401 | C32: TRAFFIC-VIOLATIONS- | E32: 75 | G32: =IF(E32="","",G31+IF(H32="C/F",0,E32)-F32) -> 330585.75 | H32: =IF(B32="","","NEW") -> NEW
A33: 13/10/2024 | B33: EXP4386 | C33: SHIRFAN ADVANCE FROM NIDHEESH COLLECTION- | E33: 4650 | G33: =IF(E33="","",G32+IF(H33="C/F",0,E33)-F33) -> 335235.75 | H33: =IF(B33="","","NEW") -> NEW
A34: 20/10/2024 | B34: EXP4423 | C34: THOYYIB ADVANCE QASEEM NEW ROUTE- | E34: 500 | G34: =IF(E34="","",G33+IF(H34="C/F",0,E34)-F34) -> 335735.75 | H34: =IF(B34="","","NEW") -> NEW
A35: 27/10/2024 | B35: EXP4488 | C35: SHIRFAN FROM ARSHADH COLLECTION- | E35: 2000 | G35: =IF(E35="","",G34+IF(H35="C/F",0,E35)-F35) -> 337735.75 | H35: =IF(B35="","","NEW") -> NEW
A36: 31/10/2024 | C36: MANAFIZ RENT DMM ROUTE | E36: 16857.45 | G36: =IF(E36="","",G35+IF(H36="C/F",0,E36)-F36) -> 354593.2 | H36: =IF(B36="","","NEW")
A37: 31/10/2024 | B37: EXP4499 | C37: SHIRFAN ADVANCE- | E37: 2000 | G37: =IF(E37="","",G36+IF(H37="C/F",0,E37)-F37) -> 356593.2 | H37: =IF(B37="","","NEW") -> NEW
A38: 45546 | B38: EXP4569 | C38: SALMAN FARIZ ADVANCE FROM NIDHEESH COLLECTION- | E38: 4450 | G38: =IF(E38="","",G37+IF(H38="C/F",0,E38)-F38) -> 361043.2 | H38: =IF(B38="","","NEW") -> NEW
A39: 45637 | B39: EXP4573 | C39: ASLAM ADVANCE TO SALMAN FARIZ- | E39: 80 | G39: =IF(E39="","",G38+IF(H39="C/F",0,E39)-F39) -> 361123.2 | H39: =IF(B39="","","NEW") -> NEW
A40: 18/11/2024 | B40: EXP4597 | C40: PURCHASE ADVANCE-FAWAS- | E40: 20 | G40: =IF(E40="","",G39+IF(H40="C/F",0,E40)-F40) -> 361143.2 | H40: =IF(B40="","","NEW") -> NEW
A41: 45303 | B41: EXP4637 | C41: SALMAN FARIZ ADVANCE-GAS PURCHASE- | E41: 20.87 | G41: =IF(E41="","",G40+IF(H41="C/F",0,E41)-F41) -> 361164.07 | H41: =IF(B41="","","NEW") -> NEW
A42: 45303 | B42: EXP4637 | C42: SHIRFAN ADVANCES-SINGLE SOCKET- | E42: 34.78 | G42: =IF(E42="","",G41+IF(H42="C/F",0,E42)-F42) -> 361198.85 | H42: =IF(B42="","","NEW") -> NEW
A43: 45303 | B43: EXP4637 | C43: LED-HALOGEN LAMB- | E43: 60.87 | G43: =IF(E43="","",G42+IF(H43="C/F",0,E43)-F43) -> 361259.72 | H43: =IF(B43="","","NEW") -> NEW
A44: 45394 | B44: EXP4685 | C44: NEW STAFF SAFEER BED- | E44: 80.5 | G44: =IF(E44="","",G43+IF(H44="C/F",0,E44)-F44) -> 361340.22 | H44: =IF(B44="","","NEW") -> NEW
A45: 45394 | B45: EXP4685 | C45: NEW STAFF SAFEER PILLOW- | E45: 11.5 | G45: =IF(E45="","",G44+IF(H45="C/F",0,E45)-F45) -> 361351.72 | H45: =IF(B45="","","NEW") -> NEW
A46: 45577 | B46: EXP4697 | C46: AL JARAHA ADVANCE PAYMENT-METAL DETECTOR AND HIGHSPEED PACKING MACHINE-FT24226094147820- | E46: 49001.48 | G46: =IF(E46="","",G45+IF(H46="C/F",0,E46)-F46) -> 410353.2 | H46: =IF(B46="","","NEW") -> NEW
A47: 15/12/2024 | B47: EXP4705 | C47: FOOD EXPENSE ADANCE-shirfan- Nepali man power supply food- | E47: 180 | G47: =IF(E47="","",G46+IF(H47="C/F",0,E47)-F47) -> 410533.2 | H47: =IF(B47="","","NEW") -> NEW
A48: 16/12/2024 | B48: JN7768 | C48: CASH COLLCETION SHORT -KHALID | E48: 1337.87 | G48: =IF(E48="","",G47+IF(H48="C/F",0,E48)-F48) -> 411871.07 | H48: =IF(B48="","","NEW") -> NEW
A49: 16/12/2024 | B49: EXP4707 | C49: KHALID COLLECTION AMOUNT GIVEN TO AYOOB- | E49: 7500 | G49: =IF(E49="","",G48+IF(H49="C/F",0,E49)-F49) -> 419371.07 | H49: =IF(B49="","","NEW") -> NEW
A50: 24/12/2024 | B50: EXP4745 | C50: COINS SHORT-ADVANCE- | E50: 85 | G50: =IF(E50="","",G49+IF(H50="C/F",0,E50)-F50) -> 419456.07 | H50: =IF(B50="","","NEW") -> NEW
A51: 25/12/2024 | B51: EXP4747 | C51: SHIRFAN ADVANCE NIDHEESH COLLECTION- | E51: 300 | G51: =IF(E51="","",G50+IF(H51="C/F",0,E51)-F51) -> 419756.07 | H51: =IF(B51="","","NEW") -> NEW
A52: 30/12/2024 | B52: EXP4756 | C52: FUEL-ADVANCE-FAWAS- | E52: 150 | G52: =IF(E52="","",G51+IF(H52="C/F",0,E52)-F52) -> 419906.07 | H52: =IF(B52="","","NEW") -> NEW
A53: 45748 | B53: EXP4780 | C53: PURCHASE ADVANCE-NASAR- | E53: 100 | G53: =IF(E53="","",G52+IF(H53="C/F",0,E53)-F53) -> 420006.07 | H53: =IF(B53="","","NEW") -> NEW
A54: 45901 | B54: EXP4786 | C54: BAB REPAIR DAMAGE CHANGE-DHIYA ADVANCE- | E54: 450 | G54: =IF(E54="","",G53+IF(H54="C/F",0,E54)-F54) -> 420456.07 | H54: =IF(B54="","","NEW") -> NEW
A55: 14/01/2025 | B55: EXP4790 | C55: Al jara machinary payment- | E55: 51310.45 | G55: =IF(E55="","",G54+IF(H55="C/F",0,E55)-F55) -> 471766.52 | H55: =IF(B55="","","NEW") -> NEW
A56: 16/01/2025 | B56: EXP4794 | C56: PURCHASE ADVANCE SABARI- | E56: 400 | G56: =IF(E56="","",G55+IF(H56="C/F",0,E56)-F56) -> 472166.52 | H56: =IF(B56="","","NEW") -> NEW
A57: 19/01/2025 | B57: EXP4796 | C57: JHOON PAYMENT-ANSARI-8 HALF HOUR- | E57: 170 | G57: =IF(E57="","",G56+IF(H57="C/F",0,E57)-F57) -> 472336.52 | H57: =IF(B57="","","NEW") -> NEW
A58: 20/01/2025 | B58: EXP4797 | C58: PURCHASE ADVANCE-MUNEESH- | E58: 2000 | G58: =IF(E58="","",G57+IF(H58="C/F",0,E58)-F58) -> 474336.52 | H58: =IF(B58="","","NEW") -> NEW
A59: 21/01/2025 | B59: EXP4798 | C59: PURCHASE ADVANCE-MUNEESH- | E59: 1500 | G59: =IF(E59="","",G58+IF(H59="C/F",0,E59)-F59) -> 475836.52 | H59: =IF(B59="","","NEW") -> NEW
A60: 22/01/2025 | B60: EXP4799 | C60: PURCHASE ADVANCE-KHUDAIR- | E60: 200 | G60: =IF(E60="","",G59+IF(H60="C/F",0,E60)-F60) -> 476036.52 | H60: =IF(B60="","","NEW") -> NEW
A61: 25/01/2025 | B61: EXP4839 | C61: PURCHASE -ADVANCE-GAS ACCOMODATION- | E61: 100 | G61: =IF(E61="","",G60+IF(H61="C/F",0,E61)-F61) -> 476136.52 | H61: =IF(B61="","","NEW") -> NEW
A62: 25/01/2025 | B62: EXP4839 | C62: PURCHASE ADVANCE-ASLAM- | E62: 215 | G62: =IF(E62="","",G61+IF(H62="C/F",0,E62)-F62) -> 476351.52 | H62: =IF(B62="","","NEW") -> NEW
A63: 25/01/2025 | B63: EXP4839 | C63: PURCHASE ADVANCE-ASLAM- | E63: 1100 | G63: =IF(E63="","",G62+IF(H63="C/F",0,E63)-F63) -> 477451.52 | H63: =IF(B63="","","NEW") -> NEW
A64: 30/01/2025 | B64: EXP4876 | C64: ASHOK BAHRAIN ADVANCE- | E64: 1000 | G64: =IF(E64="","",G63+IF(H64="C/F",0,E64)-F64) -> 478451.52 | H64: =IF(B64="","","NEW") -> NEW
A65: 30/01/2025 | B65: EXP4876 | C65: KHUDAIR COINS CHANGE MARKET- | E65: 157 | G65: =IF(E65="","",G64+IF(H65="C/F",0,E65)-F65) -> 478608.52 | H65: =IF(B65="","","NEW") -> NEW
G66: =IF(E66="","",G65+IF(H66="C/F",0,E66)-F66) | H66: =IF(B66="","","NEW")
G67: =IF(E67="","",G66+IF(H67="C/F",0,E67)-F67) | H67: =IF(B67="","","NEW")
G68: =IF(E68="","",G67+IF(H68="C/F",0,E68)-F68) | H68: =IF(B68="","","NEW")
G69: =IF(E69="","",G68+IF(H69="C/F",0,E69)-F69) | H69: =IF(B69="","","NEW")
G70: =IF(E70="","",G69+IF(H70="C/F",0,E70)-F70) | H70: =IF(B70="","","NEW")
G71: =IF(E71="","",G70+IF(H71="C/F",0,E71)-F71) | H71: =IF(B71="","","NEW")
G72: =IF(E72="","",G71+IF(H72="C/F",0,E72)-F72) | H72: =IF(B72="","","NEW")
G73: =IF(E73="","",G72+IF(H73="C/F",0,E73)-F73) | H73: =IF(B73="","","NEW")
G74: =IF(E74="","",G73+IF(H74="C/F",0,E74)-F74) | H74: =IF(B74="","","NEW")
G75: =IF(E75="","",G74+IF(H75="C/F",0,E75)-F75) | H75: =IF(B75="","","NEW")
G76: =IF(E76="","",G75+IF(H76="C/F",0,E76)-F76) | H76: =IF(B76="","","NEW")
G77: =IF(E77="","",G76+IF(H77="C/F",0,E77)-F77) | H77: =IF(B77="","","NEW")
... G100: =IF(E100="","",G99+IF(H100="C/F",0,E100)-F100) | H100: =IF(B100="","","NEW")
A102: TOTAL | E102: =SUM(E7:E101) -> 314807.68 | F102: =SUM(F7:F101) -> 0

Sheet Outstanding_AUG-2025
A1: CUSTOMER OUTSTANDING - AUG-2025
A3: Salesman | B3: Total Outstanding | C3: No. of Customers | D3: Average
A4: Nidheesh | B4: =SUMIF($D$19:$D$502,A4,$G$19:$G$502) -> 69826.96 | C4: =COUNTIF($D$19:$D$502,A4) -> 43 | D4: =IFERROR(B4/C4,0) -> 1623.8828
A5: Jaseel | B5: =SUMIF($D$19:$D$502,A5,$G$19:$G$502) -> 24260.07 | C5: =COUNTIF($D$19:$D$502,A5) -> 20 | D5: =IFERROR(B5/C5,0) -> 1213.0035
A6: Bassam | B6: =SUMIF($D$19:$D$502,A6,$G$19:$G$502) -> 19724.86 | C6: =COUNTIF($D$19:$D$502,A6) -> 17 | D6: =IFERROR(B6/C6,0) -> 1160.2859
A7: akmal | B7: =SUMIF($D$19:$D$502,A7,$G$19:$G$502) -> 38060.96 | C7: =COUNTIF($D$19:$D$502,A7) -> 19 | D7: =IFERROR(B7/C7,0) -> 2003.2084
A8: arshad | B8: =SUMIF($D$19:$D$502,A8,$G$19:$G$502) -> 329881.32 | C8: =COUNTIF($D$19:$D$502,A8) -> 26 | D8: =IFERROR(B8/C8,0) -> 12687.743
A9: Shameer riyadh | B9: =SUMIF($D$19:$D$502,A9,$G$19:$G$502) -> 71998.44 | C9: =COUNTIF($D$19:$D$502,A9) -> 50 | D9: =IFERROR(B9/C9,0) -> 1439.9688
A10: company sales | B10: =SUMIF($D$19:$D$502,A10,$G$19:$G$502) -> 1087241.2 | C10: =COUNTIF($D$19:$D$502,A10) -> 16 | D10: =IFERROR(B10/C10,0) -> 67952.576
A11: shafi | B11: =SUMIF($D$19:$D$502,A11,$G$19:$G$502) -> 16057.58 | C11: =COUNTIF($D$19:$D$502,A11) -> 34 | D11: =IFERROR(B11/C11,0) -> 472.28176
A12: ashik | B12: =SUMIF($D$19:$D$502,A12,$G$19:$G$502) -> 14387.17 | C12: =COUNTIF($D$19:$D$502,A12) -> 18 | D12: =IFERROR(B12/C12,0) -> 799.28722
A13: dhiya | B13: =SUMIF($D$19:$D$502,A13,$G$19:$G$502) -> 250098.41 | C13: =COUNTIF($D$19:$D$502,A13) -> 20 | D13: =IFERROR(B13/C13,0) -> 12504.921
A14: SALMAN | B14: =SUMIF($D$19:$D$502,A14,$G$19:$G$502) -> 0 | C14: =COUNTIF($D$19:$D$502,A14) -> 0 | D14: =IFERROR(B14/C14,0) -> 0
A15: samir | B15: =SUMIF($D$19:$D$502,A15,$G$19:$G$502) -> 12195.64 | C15: =COUNTIF($D$19:$D$502,A15) -> 11 | D15: =IFERROR(B15/C15,0) -> 1108.6945
... A17: shareef | B17: =SUMIF($D$19:$D$502,A17,$G$19:$G$502) -> 4257.5 | C17: =COUNTIF($D$19:$D$502,A17) -> 17 | D17: =IFERROR(B17/C17,0) -> 250.44118
A18: TOTAL | B18: =SUM(B4:B17) -> 2026772.4 | C18: =SUM(C4:C17) -> 403 | D18: =IFERROR(B18/C18,0) -> 5029.2119
A20: Customer Code | B20: Customer Name | C20: Area | D20: Salesman | E20: Invoice Amount | F20: Paid Amount | G20: Balance | H20: Days
A21: CUST57 | B21: Essa Muhammad al Abbadi | C21: Al Ahsa-2 | D21: Nidheesh | E21: 135.97 | G21: =IF(E21="","",E21-F21) -> 135.97
A22: CUST154 | B22: Moona al aila family | C22: Al Ahsa-2 | D22: Nidheesh | E22: 1200.81 | G22: =IF(E22="","",E22-F22) -> 1200.81
A23: CUST156 | B23: Al nouri grocery to sell food | C23: Al Ahsa-2 | D23: Nidheesh | E23: 997.93 | G23: =IF(E23="","",E23-F23) -> 997.93
A24: CUST175 | B24: Red apple supermarket | C24: Al Ahsa-2 | D24: Nidheesh | E24: 1611.75 | G24: =IF(E24="","",E24-F24) -> 1611.75
A25: CUST199 | B25: Thamuniyath wajihath al busthan | C25: Al Ahsa-2 | D25: Nidheesh | E25: 746.89 | G25: =IF(E25="","",E25-F25) -> 746.89
A26: CUST202 | B26: Athareek al mothi | C26: Al Ahsa-2 | D26: Nidheesh | E26: 1416.81 | G26: =IF(E26="","",E26-F26) -> 1416.81
A27: CUST285 | B27: Mosasath likuli almujtamae altijaria | C27: Al Ahsa-2 | D27: Nidheesh | E27: 1860.81 | G27: =IF(E27="","",E27-F27) -> 1860.81
A28: CUST347 | B28: Markaz Darth al shahsi | C28: Al Ahsa-2 | D28: Nidheesh | E28: 1629.71 | G28: =IF(E28="","",E28-F28) -> 1629.71
A29: CUST421 | B29: Nasaem al nada.. | C29: Al Ahsa-2 | D29: Nidheesh | E29: 1123.68 | G29: =IF(E29="","",E29-F29) -> 1123.68
A30: CUST478 | B30: Sharikath toufirul al Ghada lithijara | C30: Al Ahsa-2 | D30: Nidheesh | E30: 480 | G30: =IF(E30="","",E30-F30) -> 480
A31: CUST487 | B31: Althuraya mood limwad alghdhayyt | C31: Al Ahsa-2 | D31: Nidheesh | E31: 1263.56 | G31: =IF(E31="","",E31-F31) -> 1263.56
A32: CUST584 | B32: Wajihathul andaleeb foodstuff | C32: Al Ahsa-2 | D32: Nidheesh | E32: 1021.87 | G32: =IF(E32="","",E32-F32) -> 1021.87
... A423: CUST5840 | B423: Day N Day | C423: Dammam Retail | D423: akmal | E423: 2190.15 | G423: =IF(E423="","",E423-F423) -> 2190.15
G424: =IF(E424="","",E424-F424)
G425: =IF(E425="","",E425-F425)
G426: =IF(E426="","",E426-F426)
G427: =IF(E427="","",E427-F427)
G428: =IF(E428="","",E428-F428)
G429: =IF(E429="","",E429-F429)
G430: =IF(E430="","",E430-F430)
G431: =IF(E431="","",E431-F431)
G432: =IF(E432="","",E432-F432)
G433: =IF(E433="","",E433-F433)
G434: =IF(E434="","",E434-F434)
G435: =IF(E435="","",E435-F435)
... G502: =IF(E502="","",E502-F502)
A503: GRAND TOTAL | E503: =SUM(E21:E502) -> 2026772.4 | F503: =SUM(F21:F502) -> 0 | G503: =SUM(G21:G502) -> 2026772.4

Sheet Banks_JAN-2025
A1: BANK SUMMARY - JAN-2025
A3: Bank Name | B3: Opening Balance | C3: Total Received | D3: Bank Charges | E3: Total Payments | F3: Closing Balance | G3: Notes
A4: Alrajhi-1097 | B4: 362308.76 | C4: 1298100.1 | D4: 2042.11 | E4: 1286078.6 | F4: 372288.1
A5: Alrajhi-new | B5: 244226 | C5: 55828.6 | D5: 0 | E5: 0 | F5: 300054.6
A6: SNB Al Ahsa Branch | B6: 464198.07 | C6: 503650.38 | D6: 373.75 | E6: 700000 | F6: 267474.7
A7: Albilad | B7: 284287.2 | C7: 1817003 | D7: 0 | E7: 1900085 | F7: 201205.17
A9: SUB-TOTAL SAR | B9: =SUM(B4:B7) -> 1355020 | C9: =SUM(C4:C7) -> 3674582 | D9: =SUM(D4:D7) -> 2415.86 | E9: =SUM(E4:E7) -> 3886163.6 | F9: =SUM(F4:F7) -> 1141022.6
A11: USD ACCOUNTS
A12: Bank Name | B12: Opening | C12: Amount Received | D12: Bank Charge | E12: Payment | F12: Balance | G12: Notes
A13: Albilad USD | B13: 2679.36 | C13: 172941.33 | D13: 0 | E13: 175015.33 | F13: 605.36
A15: SUB-TOTAL USD | B15: =SUM(B13) -> 2679.36 | C15: =SUM(C13) -> 172941.33 | D15: =SUM(D13) -> 0 | E15: =SUM(E13) -> 175015.33 | F15: =SUM(F13) -> 605.36
A17: GRAND TOTAL (SAR + USD Converted) | B17: =B9+B15*3.75 -> 1365067.6 | C17: =C9+C15*3.75 -> 4323112 | D17: =D9+D15*3.75 -> 2415.86 | E17: =E9+E15*3.75 -> 4542471.1 | F17: =F9+F15*3.75 -> 1143292.7
A19: SUMMARY
A20: Total Bank Balance (SAR): | C20: =F17 -> 1143292.7

Sheet Suspense_JAN-2025
A1: SUSPENSE RECONCILIATION - JAN-2025
A3: OPENING BALANCE | B3: -7420.48 | D3: CLOSING BALANCE | E3: =-17267.64+SUM(E7:E1000)-SUM(F7:F1000) -> -62065.42
A5: UNIDENTIFIED TRANSACTIONS
A6: Date | B6: Journal No | C6: Description | D6: Reference | E6: Debit | F6: Credit | G6: Running Balance
A7: 45778 | B7: JN8160 | C7: BANK TRANSFER-JASEEL | E7: 0 | F7: 459.94 | G7: =IF(AND(E7="",F7=""),"",B3+E7-F7) -> -7880.42
A8: 45778 | B8: JN8352 | C8: BANK POS-THOYYIB QASEEM-4533.21 | E8: 0 | F8: 2652.23 | G8: =IF(AND(E8="",F8=""),"",G7+E8-F8) -> -10532.65
A9: 45839 | B9: JN8379 | C9: BANK POS-SAMIR-HAFAR-2637 | E9: 0 | F9: 702 | G9: =IF(AND(E9="",F9=""),"",G8+E9-F9) -> -11234.65
A10: 45962 | B10: JN8404 | C10: BANK TRANSFER-THOYYIB-QASEEM-5644.15 | E10: 0 | F10: 591.5 | G10: =IF(AND(E10="",F10=""),"",G9+E10-F10) -> -11826.15
A11: 45992 | B11: JN8354 | C11: BANK POS-THOYYIB QASEEM-4533.21 | E11: 0 | F11: 70 | G11: =IF(AND(E11="",F11=""),"",G10+E11-F11) -> -11896.15
A12: 45992 | B12: JN8353 | C12: BANK POS-THOYYIB QASEEM-4533.21 | E12: 0 | F12: 75 | G12: =IF(AND(E12="",F12=""),"",G11+E12-F12) -> -11971.15
A13: 45992 | B13: JN8408 | C13: BANK TRANSFER-NOT IDENTIFIED | E13: 0 | F13: 1800 | G13: =IF(AND(E13="",F13=""),"",G12+E13-F13) -> -13771.15
A14: 13/01/2025 | B14: JN8355 | C14: BANK POS-THOYYIB QASEEM-4533.21 | E14: 0 | F14: 541 | G14: =IF(AND(E14="",F14=""),"",G13+E14-F14) -> -14312.15
A15: 13/01/2025 | B15: JN8405 | C15: BANK TRANSFER-QASEEM THOYYIB-5644.15 | E15: 0 | F15: 1361.8 | G15: =IF(AND(E15="",F15=""),"",G14+E15-F15) -> -15673.95
A16: 14/01/2025 | B16: JN8176 | C16: BANK TRANSFER-NIDHEEESH | E16: 0 | F16: 1 | G16: =IF(AND(E16="",F16=""),"",G15+E16-F16) -> -15674.95
A17: 14/01/2025 | B17: JN8177 | C17: BANK TRANSFER-NIDHEEESH | E17: 0 | F17: 50 | G17: =IF(AND(E17="",F17=""),"",G16+E17-F17) -> -15724.95
A18: 15/01/2025 | B18: JN8356 | C18: BANK POS-THOYYIB QASEEM-4533.21 | E18: 0 | F18: 470.98 | G18: =IF(AND(E18="",F18=""),"",G17+E18-F18) -> -16195.93
A19: 15/01/2025 | B19: JN8357 | C19: BANK POS-THOYYIB QASEEM-4533.21 | E19: 0 | F19: 397 | G19: =IF(AND(E19="",F19=""),"",G18+E19-F19) -> -16592.93
A20: 17/01/2025 | B20: JN8380 | C20: BANK POS-SAMIR-HAFAR-2637 | E20: 0 | F20: 842 | G20: =IF(AND(E20="",F20=""),"",G19+E20-F20) -> -17434.93
A21: 17/01/2025 | B21: JN8384 | C21: BANK POS-KHALID | E21: 0 | F21: 781.97 | G21: =IF(AND(E21="",F21=""),"",G20+E21-F21) -> -18216.9
A22: 17/01/2025 | B22: JN8407 | C22: BANK TRANSFER-SAMIR HAFAR-1817 | E22: 0 | F22: 917 | G22: =IF(AND(E22="",F22=""),"",G21+E22-F22) -> -19133.9
A23: 18/01/2025 | B23: JN8409 | C23: BANK TRANSFER-NOT IDENTIFIED | E23: 0 | F23: 2299 | G23: =IF(AND(E23="",F23=""),"",G22+E23-F23) -> -21432.9
A24: 19/01/2025 | B24: JN8400 | C24: BANK TRANSFER- | E24: 0 | F24: 2550 | G24: =IF(AND(E24="",F24=""),"",G23+E24-F24) -> -23982.9
A25: 19/01/2025 | B25: JN8393 | C25: BANK TRANSFER-THOYYIB QASEEM-5644.15 | E25: 0 | F25: 518 | G25: =IF(AND(E25="",F25=""),"",G24+E25-F25) -> -24500.9
... A53: 30/01/2025 | B53: JN8413 | C53: BANK TRANSFER-NOT IDENTIFIED | E53: 0 | F53: 1312 | G53: =IF(AND(E53="",F53=""),"",G52+E53-F53) -> -31333.39
A54: 30/01/2025 | B54: JN8318 | C54: BANK POS-NIDHEESH | E54: 2100 | G54: =IF(AND(E54="",F54=""),"",G53+E54-F54) -> -29233.39
A55: 30/01/2025 | B55: JN8316 | C55: BANK TRANSFER-JASEEL | E55: 451 | F55: 0 | G55: =IF(AND(E55="",F55=""),"",G54+E55-F55) -> -28782.39
A56: 31/01/2025 | B56: JN8364 | C56: BANK POS-JASEEL | E56: 0 | F56: 1036.98 | G56: =IF(AND(E56="",F56=""),"",G55+E56-F56) -> -29819.37
G57: =IF(AND(E57="",F57=""),"",G56+E57-F57)
G58: =IF(AND(E58="",F58=""),"",G57+E58-F58)
G59: =IF(AND(E59="",F59=""),"",G58+E59-F59)
G60: =IF(AND(E60="",F60=""),"",G59+E60-F60)
G61: =IF(AND(E61="",F61=""),"",G60+E61-F61)
G62: =IF(AND(E62="",F62=""),"",G61+E62-F62)
G63: =IF(AND(E63="",F63=""),"",G62+E63-F63)
G64: =IF(AND(E64="",F64=""),"",G63+E64-F64)
G65: =IF(AND(E65="",F65=""),"",G64+E65-F65)
G66: =IF(AND(E66="",F66=""),"",G65+E66-F66)
G67: =IF(AND(E67="",F67=""),"",G66+E67-F67)
G68: =IF(AND(E68="",F68=""),"",G67+E68-F68)
... G76: =IF(AND(E76="",F76=""),"",G75+E76-F76)
G77: =IF(AND(E77="",F77=""),"",G76+E77-F77) | H77: =IF(B77="","","NEW")
G78: =IF(AND(E78="",F78=""),"",G77+E78-F78) | H78: =IF(B78="","","NEW")
G79: =IF(AND(E79="",F79=""),"",G78+E79-F79) | H79: =IF(B79="","","NEW")
G80: =IF(AND(E80="",F80=""),"",G79+E80-F80) | H80: =IF(B80="","","NEW")
G81: =IF(AND(E81="",F81=""),"",G80+E81-F81) | H81: =IF(B81="","","NEW")
G82: =IF(AND(E82="",F82=""),"",G81+E82-F82) | H82: =IF(B82="","","NEW")
G83: =IF(AND(E83="",F83=""),"",G82+E83-F83) | H83: =IF(B83="","","NEW")
G84: =IF(AND(E84="",F84=""),"",G83+E84-F84) | H84: =IF(B84="","","NEW")
G85: =IF(AND(E85="",F85=""),"",G84+E85-F85) | H85: =IF(B85="","","NEW")
G86: =IF(AND(E86="",F86=""),"",G85+E86-F86) | H86: =IF(B86="","","NEW")
G87: =IF(AND(E87="",F87=""),"",G86+E87-F87) | H87: =IF(B87="","","NEW")
G88: =IF(AND(E88="",F88=""),"",G87+E88-F88) | H88: =IF(B88="","","NEW")
... G100: =IF(AND(E100="",F100=""),"",G99+E100-F100) | H100: =IF(B100="","","NEW")
A102: TOTAL | E102: =SUM(E7:E101) -> 15628 | F102: =SUM(F7:F101) -> 38026.89

Sheet Outstanding_JAN-2025
A1: CUSTOMER OUTSTANDING - JAN-2025
A3: Salesman
A4: Nidheesh | B4: =SUMIF($D$20:$D$503,A4,$G$20:$G$503) -> 42552.35 | C4: =COUNTIF($D$20:$D$503,A4) -> 33 | D4: =IFERROR(B4/C4,0) -> 1289.4652
A5: Jaseel | B5: =SUMIF($D$20:$D$503,A5,$G$20:$G$503) -> 24265.64 | C5: =COUNTIF($D$20:$D$503,A5) -> 19 | D5: =IFERROR(B5/C5,0) -> 1277.1389
A6: Bassam | B6: =SUMIF($D$20:$D$503,A6,$G$20:$G$503) -> 17887.52 | C6: =COUNTIF($D$20:$D$503,A6) -> 11 | D6: =IFERROR(B6/C6,0) -> 1626.1382
A7: akmal | B7: =SUMIF($D$20:$D$503,A7,$G$20:$G$503) -> 575.93 | C7: =COUNTIF($D$20:$D$503,A7) -> 1 | D7: =IFERROR(B7/C7,0) -> 575.93
A8: arshad | B8: =SUMIF($D$20:$D$503,A8,$G$20:$G$503) -> 401746.31 | C8: =COUNTIF($D$20:$D$503,A8) -> 23 | D8: =IFERROR(B8/C8,0) -> 17467.231
A9: Shameer riyadh | B9: =SUMIF($D$21:$D$504,A9,$G$21:$G$504) -> 22083.16 | C9: =COUNTIF($D$20:$D$503,A9) -> 15 | D9: =IFERROR(B9/C9,0) -> 1472.2107
A10: company sales | B10: =SUMIF($D$21:$D$504,A10,$G$21:$G$504) -> 985953.74 | C10: =COUNTIF($D$20:$D$503,A10) -> 14 | D10: =IFERROR(B10/C10,0) -> 70425.267
A11: shafi | B11: =SUMIF($D$21:$D$504,A11,$G$21:$G$504) -> 0 | C11: =COUNTIF($D$20:$D$503,A11) -> 0 | D11: =IFERROR(B11/C11,0) -> 0
A12: dhiya | B12: =SUMIF($D$21:$D$504,A12,$G$21:$G$504) -> 237083.08 | C12: =COUNTIF($D$20:$D$503,A12) -> 20 | D12: =IFERROR(B12/C12,0) -> 11854.154
A13: samir | B13: =SUMIF($D$21:$D$504,A13,$G$21:$G$504) -> 4863 | C13: =COUNTIF($D$20:$D$503,A13) -> 6 | D13: =IFERROR(B13/C13,0) -> 810.5
A14: Khalid | B14: =SUMIF($D$21:$D$504,A14,$G$21:$G$504) -> 55184.18 | C14: =COUNTIF($D$21:$D$504,A14) -> 96 | D14: =IFERROR(B14/C14,0) -> 574.83521
A15: ashik | B15: =SUMIF($D$21:$D$504,A15,$G$21:$G$504) -> 3674.58 | C15: =COUNTIF($D$21:$D$504,A15) -> 11 | D15: =IFERROR(B15/C15,0) -> 334.05273
A16: shareef | B16: =SUMIF($D$20:$D$503,A16,$G$20:$G$503) -> 0 | C16: =COUNTIF($D$21:$D$504,A16) -> 0 | D16: =IFERROR(B16/C16,0) -> 0
A17: TOTAL | B17: =SUM(B4:B16) -> 1795869.5 | C17: =SUM(C5:C16) -> 216 | D17: =SUM(D5:D16) -> 106417.46
A19: CUSTOMER DETAILS
A20: Customer Code | B20: Customer Name | C20: Area | D20: Salesman | E20: Invoice Amount | F20: Paid Amount | G20: Balance | H20: Days
A21: CUST57 | B21: Essa Muhammad al Abbadi | C21: Al Ahsa-2 | D21: Nidheesh | E21: 0 | F21: 0 | G21: 135.97
A22: CUST156 | B22: Al nouri grocery to sell food | C22: Al Ahsa-2 | D22: Nidheesh | E22: 0 | F22: 0 | G22: 1696.8
A23: CUST199 | B23: Thamuniyath wajihath al busthan | C23: Al Ahsa-2 | D23: Nidheesh | E23: 0 | F23: 0 | G23: 969.85
A24: CUST202 | B24: Athareek al mothi | C24: Al Ahsa-2 | D24: Nidheesh | E24: 0 | F24: 0 | G24: 3218.57
A25: CUST285 | B25: Mosasath likuli almujtamae altijaria | C25: Al Ahsa-2 | D25: Nidheesh | E25: 0 | F25: 0 | G25: 837.89
A26: CUST347 | B26: Markaz Darth al shahsi | C26: Al Ahsa-2 | D26: Nidheesh | E26: 0 | F26: 0 | G26: 479.92
A27: CUST349 | B27: Al Amana foodstuff market.. | C27: Al Ahsa-2 | D27: Nidheesh | E27: 0 | F27: 0 | G27: 1027.87
A28: CUST352 | B28: Bakala noorain | C28: Al Ahsa-2 | D28: Nidheesh | E28: 0 | F28: 0 | G28: 1174.83
A29: CUST421 | B29: Nasaem al nada.. | C29: Al Ahsa-2 | D29: Nidheesh | E29: 0 | F29: 0 | G29: 520.92
A30: CUST478 | B30: Sharikath toufirul al Ghada lithijara | C30: Al Ahsa-2 | D30: Nidheesh | E30: 0 | F30: 0 | G30: 3429.55
A31: CUST487 | B31: Althuraya mood limwad alghdhayyt | C31: Al Ahsa-2 | D31: Nidheesh | E31: 0 | F31: 0 | G31: 5061.58
A32: CUST584 | B32: Alemeeshy minimarket | C32: Al Ahsa-2 | D32: Nidheesh | E32: 0 | F32: 0 | G32: 1021.87
... A268: CUST3697 | B268: Mukadhi cold store l.l.c | C268: Dammam wholesale | D268: arshad | E268: 0 | F268: 0 | G268: 8280
B269: Wusta food company stuff | C269: Dammam Retail | D269: akmal | E269: 0 | F269: 0 | G269: 575.93
G270: =IF(E297="","",E297-F297)
G271: =IF(E298="","",E298-F298)
G272: =IF(E299="","",E299-F299)
G273: =IF(E300="","",E300-F300)
G274: =IF(E301="","",E301-F301)
G275: =IF(E302="","",E302-F302)
G276: =IF(E303="","",E303-F303)
G277: =IF(E304="","",E304-F304)
G278: =IF(E305="","",E305-F305)
G279: =IF(E306="","",E306-F306)
G280: =IF(E307="","",E307-F307)
G281: =IF(E308="","",E308-F308)
... G449: =IF(E476="","",E476-F476)
G451: =SUM(G21:G450) -> 1795869.5
A478: GRAND TOTAL | E478: =SUM(E21:E477) -> 0 | F478: =SUM(F21:F477) -> 0

Sheet Banks_FEB-2025
A1: BANK SUMMARY - FEB-2025
A3: Bank Name | B3: Opening Balance | C3: Total Received | D3: Bank Charges | E3: Total Payments | F3: Closing Balance | G3: Notes
A4: Alrajhi-1097 | B4: ='Banks_JAN-2025'!F4 -> 372288.1 | C4: 1027650.8 | D4: 2831.7 | E4: 739763.15 | F4: =B4+C4-D4-E4 -> 657344.05
A5: Alrajhi-new | B5: ='Banks_JAN-2025'!F5 -> 300054.6 | C5: 123136.51 | E5: 0 | F5: =B5+C5-D5-E5 -> 423191.11
A6: SNB Al Ahsa Branch | B6: ='Banks_JAN-2025'!F6 -> 267474.7 | C6: 386449.88 | D6: 345 | E6: 0 | F6: =B6+C6-D6-E6 -> 653579.58
A7: Albilad | B7: ='Banks_JAN-2025'!F7 -> 201205.17 | C7: 1177193.7 | E7: 854088.87 | F7: =B7+C7-D7-E7 -> 524310.03
A9: SUB-TOTAL SAR | B9: =SUM(B4:B7) -> 1141022.6 | C9: =SUM(C4:C7) -> 2714430.9 | D9: =SUM(D4:D7) -> 3176.7 | E9: =SUM(E4:E7) -> 1593852 | F9: =SUM(F4:F7) -> 2258424.8
A11: USD ACCOUNTS
A12: Bank Name | B12: Opening | C12: Amount Received | D12: Bank Charge | E12: Payment | F12: Balance | G12: Notes
A13: Albilad USD | B13: ='Banks_JAN-2025'!F13 -> 605.36 | F13: =B13+C13-D13-E13 -> 605.36
A15: SUB-TOTAL USD | B15: =SUM(B13) -> 605.36 | C15: =SUM(C13) -> 0 | D15: =SUM(D13) -> 0 | E15: =SUM(E13) -> 0 | F15: =SUM(F13) -> 605.36
A17: GRAND TOTAL (SAR + USD Converted) | B17: =B9+B15*3.75 -> 1143292.7 | C17: =C9+C15*3.75 -> 2714430.9 | D17: =D9+D15*3.75 -> 3176.7 | E17: =E9+E15*3.75 -> 1593852 | F17: =F9+F15*3.75 -> 2260694.9
A19: SUMMARY
A20: Total Bank Balance (SAR): | C20: =F17 -> 2260694.9

Sheet Advances_FEB-2025
A1: ADVANCE RECONCILIATION - FEB-2025
A3: OPENING BALANCE | B3: ='Advances_JAN-2025'!E3 -> 479608.52 | D3: CLOSING BALANCE | E3: =164800.84+SUM(E7:E101) -> 489038.28
A5: TRANSACTIONS
A6: Date | B6: Voucher No | C6: Description | D6: Person/Party | E6: Advance Given | F6: Amount Settled | G6: Running Balance
A7: 45447 | B7: EXP3275 | C7: CONSTRUCTION WORK ADVANCE RAJENDHRAN- | E7: 3000 | G7: =IF(E7="","",B$3+IF(H7="C/F",0,E7)-F7) -> 479608.52 | H7: =IF(B7="","",IF(IFERROR(MATCH(B7,'Advances_JAN-2025'!B:B,0),0)>0,"C/F","NEW")) -> C/F
A8: 17/04/2024 | B8: EXP3295 | C8: TANJI BAO PAYMENT TO BE CHARGED TO BOILING POT- | E8: 8625 | G8: =IF(E8="","",G7+IF(H8="C/F",0,E8)-F8) -> 479608.52 | H8: =IF(B8="","",IF(IFERROR(MATCH(B8,'Advances_JAN-2025'!B:B,0),0)>0,"C/F","NEW")) -> C/F
A9: 17/04/2024 | B9: EXP3391 | C9: Shirfan - Cash withdraw -- | E9: 1500 | G9: =IF(E9="","",G8+IF(H9="C/F",0,E9)-F9) -> 479608.52 | H9: =IF(B9="","",IF(IFERROR(MATCH(B9,'Advances_JAN-2025'!B:B,0),0)>0,"C/F","NEW")) -> C/F
A10: 16/05/2024 | B10: EXP3422 | C10: sabari-seeds unloading staff refreshment drink- | E10: 20 | G10: =IF(E10="","",G9+IF(H10="C/F",0,E10)-F10) -> 479608.52 | H10: =IF(B10="","",IF(IFERROR(MATCH(B10,'Advances_JAN-2025'!B:B,0),0)>0,"C/F","NEW")) -> C/F
A11: 27/05/2024 | B11: EXP3462 | C11: THOYYIB VEHICLE WINGE EXP- | E11: 350 | G11: =IF(E11="","",G10+IF(H11="C/F",0,E11)-F11) -> 479608.52 | H11: =IF(B11="","",IF(IFERROR(MATCH(B11,'Advances_JAN-2025'!B:B,0),0)>0,"C/F","NEW")) -> C/F
A12: 27/05/2024 | B12: EXP3462 | C12: ADVANCES -THOYYIBE VEHICLE COMPLAINT- | E12: 143.48 | G12: =IF(E12="","",G11+IF(H12="C/F",0,E12)-F12) -> 479608.52 | H12: =IF(B12="","",IF(IFERROR(MATCH(B12,'Advances_JAN-2025'!B:B,0),0)>0,"C/F","NEW")) -> C/F
A13: 27/05/2024 | B13: EXP3462 | C13: ADVANCES -THOYYIBE VEHICLE COMPLAINT- | E13: 600 | G13: =IF(E13="","",G12+IF(H13="C/F",0,E13)-F13) -> 479608.52 | H13: =IF(B13="","",IF(IFERROR(MATCH(B13,'Advances_JAN-2025'!B:B,0),0)>0,"C/F","NEW")) -> C/F
A14: 45602 | B14: EXP3508 | C14: AMITHFOOD ADVANCE-SABARI- | E14: 15 | G14: =IF(E14="","",G13+IF(H14="C/F",0,E14)-F14) -> 479608.52 | H14: =IF(B14="","",IF(IFERROR(MATCH(B14,'Advances_JAN-2025'!B:B,0),0)>0,"C/F","NEW")) -> C/F
A15: 16/06/2024 | B15: EXP3683 | C15: AIR TRANSPORTAION AIR LANKA- | E15: 2730 | G15: =IF(E15="","",G14+IF(H15="C/F",0,E15)-F15) -> 479608.52 | H15: =IF(B15="","",IF(IFERROR(MATCH(B15,'Advances_JAN-2025'!B:B,0),0)>0,"C/F","NEW")) -> C/F
A16: 16/06/2024 | B16: JN5365 | C16: COLLECTION CASH TAKEN BY HANI | E16: 34000 | G16: =IF(E16="","",G15+IF(H16="C/F",0,E16)-F16) -> 479608.52 | H16: =IF(B16="","",IF(IFERROR(MATCH(B16,'Advances_JAN-2025'!B:B,0),0)>0,"C/F","NEW")) -> C/F
A17: 24/06/2024 | B17: EXP3614 | C17: ADVANCE-SALMANUL FARIZ-RIYADH- | E17: 500 | G17: =IF(E17="","",G16+IF(H17="C/F",0,E17)-F17) -> 479608.52 | H17: =IF(B17="","",IF(IFERROR(MATCH(B17,'Advances_JAN-2025'!B:B,0),0)>0,"C/F","NEW")) -> C/F
A18: 45298 | B18: EXP3645 | C18: ASHIK-ADVANCE- | E18: 4000 | G18: =IF(E18="","",G17+IF(H18="C/F",0,E18)-F18) -> 479608.52 | H18: =IF(B18="","",IF(IFERROR(MATCH(B18,'Advances_JAN-2025'!B:B,0),0)>0,"C/F","NEW")) -> C/F
A19: 45358 | B19: EXP3654 | C19: SIVA RIYADH TRAVELING EXP ADVANCE-- | E19: 2000 | G19: =IF(E19="","",G18+IF(H19="C/F",0,E19)-F19) -> 479608.52 | H19: =IF(B19="","",IF(IFERROR(MATCH(B19,'Advances_JAN-2025'!B:B,0),0)>0,"C/F","NEW")) -> C/F
A20: 45450 | B20: EXP3699 | C20: FT24188664289852 Ben WHITE GRAPHICS-ADVANCE FOR RECEPTION WORK- | E20: 2790 | G20: =IF(E20="","",G19+IF(H20="C/F",0,E20)-F20) -> 479608.52 | H20: =IF(B20="","",IF(IFERROR(MATCH(B20,'Advances_JAN-2025'!B:B,0),0)>0,"C/F","NEW")) -> C/F
A21: 45603 | B21: EXP3749 | C21: FUEL ADVANCE-MUNEESH- | E21: 50 | G21: =IF(E21="","",G20+IF(H21="C/F",0,E21)-F21) -> 479608.52 | H21: =IF(B21="","",IF(IFERROR(MATCH(B21,'Advances_JAN-2025'!B:B,0),0)>0,"C/F","NEW")) -> C/F
A22: 17/07/2024 | B22: EXP4088 | C22: Traffic Violati REF 5366217470-7023706836-TRAFFIC -NIDHEESH- | E22: 113 | G22: =IF(E22="","",G21+IF(H22="C/F",0,E22)-F22) -> 479608.52 | H22: =IF(B22="","",IF(IFERROR(MATCH(B22,'Advances_JAN-2025'!B:B,0),0)>0,"C/F","NEW")) -> C/F
A23: 31/07/2024 | B23: EXP4021 | C23: FUEL-ADVANCE-NASAR- | E23: 100 | G23: =IF(E23="","",G22+IF(H23="C/F",0,E23)-F23) -> 479608.52 | H23: =IF(B23="","",IF(IFERROR(MATCH(B23,'Advances_JAN-2025'!B:B,0),0)>0,"C/F","NEW")) -> C/F
A24: 45573 | B24: EXP4074 | C24: SARIKA TAXI EXP -- | E24: 60 | G24: =IF(E24="","",G23+IF(H24="C/F",0,E24)-F24) -> 479608.52 | H24: =IF(B24="","",IF(IFERROR(MATCH(B24,'Advances_JAN-2025'!B:B,0),0)>0,"C/F","NEW")) -> C/F
A25: 13/08/2024 | B25: EXP4197 | C25: AL JARAHA ADVANCE PAYMENT-METAL DETECTOR AND HIGHSPEED PACKING MACHINE-FT24226303374754- | E25: 74656.7 | G25: =IF(E25="","",G24+IF(H25="C/F",0,E25)-F25) -> 479608.52 | H25: =IF(B25="","",IF(IFERROR(MATCH(B25,'Advances_JAN-2025'!B:B,0),0)>0,"C/F","NEW")) -> C/F
A26: 13/08/2024 | B26: EXP4198 | C26: AL JARAHA ADVANCE PAYMENT-METAL DETECTOR AND HIGHSPEED PACKING MACHINE-FT24226094147820- | E26: 25655.23 | G26: =IF(E26="","",G25+IF(H26="C/F",0,E26)-F26) -> 479608.52 | H26: =IF(B26="","",IF(IFERROR(MATCH(B26,'Advances_JAN-2025'!B:B,0),0)>0,"C/F","NEW")) -> C/F
A27: 27/08/2024 | B27: EXP4327 | C27: FT24240219059921 Ben EGYPTIAN SAUDI IMPORT EXPORT PAPER-DOUBLE TRANSFER-AMOUNT- | E27: 5000 | G27: =IF(E27="","",G26+IF(H27="C/F",0,E27)-F27) -> 479608.52 | H27: =IF(B27="","",IF(IFERROR(MATCH(B27,'Advances_JAN-2025'!B:B,0),0)>0,"C/F","NEW")) -> C/F
A28: 29/08/2024 | B28: EXP4267 | C28: PURCHASE ADVANCE-FAWAS- | E28: 45 | G28: =IF(E28="","",G27+IF(H28="C/F",0,E28)-F28) -> 479608.52 | H28: =IF(B28="","",IF(IFERROR(MATCH(B28,'Advances_JAN-2025'!B:B,0),0)>0,"C/F","NEW")) -> C/F
A29: 45326 | B29: EXP3255 | C29: FUEL EXP MUNEESH- | E29: 30 | G29: =IF(E29="","",G28+IF(H29="C/F",0,E29)-F29) -> 479608.52 | H29: =IF(B29="","",IF(IFERROR(MATCH(B29,'Advances_JAN-2025'!B:B,0),0)>0,"C/F","NEW")) -> C/F
A30: 45605 | B30: EXP4358 | C30: Advances-Muneesh- | E30: 613.5 | G30: =IF(E30="","",G29+IF(H30="C/F",0,E30)-F30) -> 479608.52 | H30: =IF(B30="","",IF(IFERROR(MATCH(B30,'Advances_JAN-2025'!B:B,0),0)>0,"C/F","NEW")) -> C/F
A31: 25/09/2024 | B31: EXP4401 | C31: TRAFFIC-VIOLATIONS- | E31: 113 | G31: =IF(E31="","",G30+IF(H31="C/F",0,E31)-F31) -> 479608.52 | H31: =IF(B31="","",IF(IFERROR(MATCH(B31,'Advances_JAN-2025'!B:B,0),0)>0,"C/F","NEW")) -> C/F
A32: 25/09/2024 | B32: EXP4401 | C32: TRAFFIC-VIOLATIONS- | E32: 75 | G32: =IF(E32="","",G31+IF(H32="C/F",0,E32)-F32) -> 479608.52 | H32: =IF(B32="","",IF(IFERROR(MATCH(B32,'Advances_JAN-2025'!B:B,0),0)>0,"C/F","NEW")) -> C/F
A33: 13/10/2024 | B33: EXP4386 | C33: SHIRFAN ADVANCE FROM NIDHEESH COLLECTION- | E33: 4650 | G33: =IF(E33="","",G32+IF(H33="C/F",0,E33)-F33) -> 479608.52 | H33: =IF(B33="","",IF(IFERROR(MATCH(B33,'Advances_JAN-2025'!B:B,0),0)>0,"C/F","NEW")) -> C/F
A34: 20/10/2024 | B34: EXP4423 | C34: THOYYIB ADVANCE QASEEM NEW ROUTE- | E34: 500 | G34: =IF(E34="","",G33+IF(H34="C/F",0,E34)-F34) -> 479608.52 | H34: =IF(B34="","",IF(IFERROR(MATCH(B34,'Advances_JAN-2025'!B:B,0),0)>0,"C/F","NEW")) -> C/F
A35: 27/10/2024 | B35: EXP4488 | C35: SHIRFAN FROM ARSHADH COLLECTION- | E35: 2000 | G35: =IF(E35="","",G34+IF(H35="C/F",0,E35)-F35) -> 479608.52 | H35: =IF(B35="","",IF(IFERROR(MATCH(B35,'Advances_JAN-2025'!B:B,0),0)>0,"C/F","NEW")) -> C/F
A36: 31/10/2024 | C36: MANAFIZ RENT DMM ROUTE | E36: 16857.45 | G36: =IF(E36="","",G35+IF(H36="C/F",0,E36)-F36) -> 496465.97 | H36: =IF(B36="","",IF(IFERROR(MATCH(B36,'Advances_JAN-2025'!B:B,0),0)>0,"C/F","NEW"))
A37: 31/10/2024 | B37: EXP4499 | C37: SHIRFAN ADVANCE- | E37: 2000 | G37: =IF(E37="","",G36+IF(H37="C/F",0,E37)-F37) -> 496465.97 | H37: =IF(B37="","",IF(IFERROR(MATCH(B37,'Advances_JAN-2025'!B:B,0),0)>0,"C/F","NEW")) -> C/F
A38: 45546 | B38: EXP4569 | C38: SALMAN FARIZ ADVANCE FROM NIDHEESH COLLECTION- | E38: 4450 | G38: =IF(E38="","",G37+IF(H38="C/F",0,E38)-F38) -> 496465.97 | H38: =IF(B38="","",IF(IFERROR(MATCH(B38,'Advances_JAN-2025'!B:B,0),0)>0,"C/F","NEW")) -> C/F
A39: 45637 | B39: EXP4573 | C39: ASLAM ADVANCE TO SALMAN FARIZ- | E39: 80 | G39: =IF(E39="","",G38+IF(H39="C/F",0,E39)-F39) -> 496465.97 | H39: =IF(B39="","",IF(IFERROR(MATCH(B39,'Advances_JAN-2025'!B:B,0),0)>0,"C/F","NEW")) -> C/F
A40: 18/11/2024 | B40: EXP4597 | C40: PURCHASE ADVANCE-FAWAS- | E40: 20 | G40: =IF(E40="","",G39+IF(H40="C/F",0,E40)-F40) -> 496465.97 | H40: =IF(B40="","",IF(IFERROR(MATCH(B40,'Advances_JAN-2025'!B:B,0),0)>0,"C/F","NEW")) -> C/F
A41: 45303 | B41: EXP4637 | C41: SALMAN FARIZ ADVANCE-GAS PURCHASE- | E41: 20.87 | G41: =IF(E41="","",G40+IF(H41="C/F",0,E41)-F41) -> 496465.97 | H41: =IF(B41="","",IF(IFERROR(MATCH(B41,'Advances_JAN-2025'!B:B,0),0)>0,"C/F","NEW")) -> C/F
A42: 45303 | B42: EXP4637 | C42: SHIRFAN ADVANCES-SINGLE SOCKET- | E42: 34.78 | G42: =IF(E42="","",G41+IF(H42="C/F",0,E42)-F42) -> 496465.97 | H42: =IF(B42="","",IF(IFERROR(MATCH(B42,'Advances_JAN-2025'!B:B,0),0)>0,"C/F","NEW")) -> C/F
A43: 45303 | B43: EXP4637 | C43: LED-HALOGEN LAMB- | E43: 60.87 | G43: =IF(E43="","",G42+IF(H43="C/F",0,E43)-F43) -> 496465.97 | H43: =IF(B43="","",IF(IFERROR(MATCH(B43,'Advances_JAN-2025'!B:B,0),0)>0,"C/F","NEW")) -> C/F
A44: 45394 | B44: EXP4685 | C44: NEW STAFF SAFEER BED- | E44: 80.5 | G44: =IF(E44="","",G43+IF(H44="C/F",0,E44)-F44) -> 496465.97 | H44: =IF(B44="","",IF(IFERROR(MATCH(B44,'Advances_JAN-2025'!B:B,0),0)>0,"C/F","NEW")) -> C/F
A45: 45394 | B45: EXP4685 | C45: NEW STAFF SAFEER PILLOW- | E45: 11.5 | G45: =IF(E45="","",G44+IF(H45="C/F",0,E45)-F45) -> 496465.97 | H45: =IF(B45="","",IF(IFERROR(MATCH(B45,'Advances_JAN-2025'!B:B,0),0)>0,"C/F","NEW")) -> C/F
A46: 45577 | B46: EXP4697 | C46: AL JARAHA ADVANCE PAYMENT-METAL DETECTOR AND HIGHSPEED PACKING MACHINE-FT24226094147820- | E46: 49001.48 | G46: =IF(E46="","",G45+IF(H46="C/F",0,E46)-F46) -> 496465.97 | H46: =IF(B46="","",IF(IFERROR(MATCH(B46,'Advances_JAN-2025'!B:B,0),0)>0,"C/F","NEW")) -> C/F
A47: 15/12/2024 | B47: EXP4705 | C47: FOOD EXPENSE ADANCE-shirfan- Nepali man power supply food- | E47: 180 | G47: =IF(E47="","",G46+IF(H47="C/F",0,E47)-F47) -> 496465.97 | H47: =IF(B47="","",IF(IFERROR(MATCH(B47,'Advances_JAN-2025'!B:B,0),0)>0,"C/F","NEW")) -> C/F
A48: 16/12/2024 | B48: JN7768 | C48: CASH COLLCETION SHORT -KHALID | E48: 1337.87 | G48: =IF(E48="","",G47+IF(H48="C/F",0,E48)-F48) -> 496465.97 | H48: =IF(B48="","",IF(IFERROR(MATCH(B48,'Advances_JAN-2025'!B:B,0),0)>0,"C/F","NEW")) -> C/F
A49: 16/12/2024 | B49: EXP4707 | C49: KHALID COLLECTION AMOUNT GIVEN TO AYOOB- | E49: 7500 | G49: =IF(E49="","",G48+IF(H49="C/F",0,E49)-F49) -> 496465.97 | H49: =IF(B49="","",IF(IFERROR(MATCH(B49,'Advances_JAN-2025'!B:B,0),0)>0,"C/F","NEW")) -> C/F
A50: 24/12/2024 | B50: EXP4745 | C50: COINS SHORT-ADVANCE- | E50: 85 | G50: =IF(E50="","",G49+IF(H50="C/F",0,E50)-F50) -> 496465.97 | H50: =IF(B50="","",IF(IFERROR(MATCH(B50,'Advances_JAN-2025'!B:B,0),0)>0,"C/F","NEW")) -> C/F
A51: 25/12/2024 | B51: EXP4747 | C51: SHIRFAN ADVANCE NIDHEESH COLLECTION- | E51: 300 | G51: =IF(E51="","",G50+IF(H51="C/F",0,E51)-F51) -> 496465.97 | H51: =IF(B51="","",IF(IFERROR(MATCH(B51,'Advances_JAN-2025'!B:B,0),0)>0,"C/F","NEW")) -> C/F
A52: 30/12/2024 | B52: EXP4756 | C52: FUEL-ADVANCE-FAWAS- | E52: 150 | G52: =IF(E52="","",G51+IF(H52="C/F",0,E52)-F52) -> 496465.97 | H52: =IF(B52="","",IF(IFERROR(MATCH(B52,'Advances_JAN-2025'!B:B,0),0)>0,"C/F","NEW")) -> C/F
A53: 45901 | B53: EXP4786 | C53: BAB REPAIR DAMAGE CHANGE-DHIYA ADVANCE- | E53: 450 | G53: =IF(E53="","",G52+IF(H53="C/F",0,E53)-F53) -> 496465.97 | H53: =IF(B53="","",IF(IFERROR(MATCH(B53,'Advances_JAN-2025'!B:B,0),0)>0,"C/F","NEW")) -> C/F
A54: 14/01/2025 | B54: EXP4790 | C54: Al jara machinary payment- | E54: 51310.45 | G54: =IF(E54="","",G53+IF(H54="C/F",0,E54)-F54) -> 496465.97 | H54: =IF(B54="","",IF(IFERROR(MATCH(B54,'Advances_JAN-2025'!B:B,0),0)>0,"C/F","NEW")) -> C/F
A55: 16/01/2025 | B55: EXP4794 | C55: PURCHASE ADVANCE SABARI- | E55: 400 | G55: =IF(E55="","",G54+IF(H55="C/F",0,E55)-F55) -> 496465.97 | H55: =IF(B55="","",IF(IFERROR(MATCH(B55,'Advances_JAN-2025'!B:B,0),0)>0,"C/F","NEW")) -> C/F
A56: 45749 | B56: EXP4884 | C56: PURCHASE ADVANCE-ASHOK- | E56: 200 | G56: =IF(E56="","",G55+IF(H56="C/F",0,E56)-F56) -> 496665.97 | H56: =IF(B56="","",IF(IFERROR(MATCH(B56,'Advances_JAN-2025'!B:B,0),0)>0,"C/F","NEW")) -> NEW
A57: 45810 | B57: JN8432 | C57: COLLECTION SHORT-KHALID | E57: 1617.41 | G57: =IF(E57="","",G56+IF(H57="C/F",0,E57)-F57) -> 498283.38 | H57: =IF(B57="","",IF(IFERROR(MATCH(B57,'Advances_JAN-2025'!B:B,0),0)>0,"C/F","NEW")) -> NEW
A58: 45963 | B58: EXP4891 | C58: NEW ROOM BED,IRON BOX,KITCHEN ITEMS,ETC EXP- | E58: 1949.55 | G58: =IF(E58="","",G57+IF(H58="C/F",0,E58)-F58) -> 500232.93 | H58: =IF(B58="","",IF(IFERROR(MATCH(B58,'Advances_JAN-2025'!B:B,0),0)>0,"C/F","NEW")) -> NEW
A59: 13/02/2025 | B59: EXP4905 | C59: SHIRFAN ADVANCES-COLLECTION- | E59: 180 | G59: =IF(E59="","",G58+IF(H59="C/F",0,E59)-F59) -> 500412.93 | H59: =IF(B59="","",IF(IFERROR(MATCH(B59,'Advances_JAN-2025'!B:B,0),0)>0,"C/F","NEW")) -> NEW
A60: 16/02/2025 | B60: EXP4912 | C60: NNA REPAIR EXP-ASLAM- | E60: 334.8 | G60: =IF(E60="","",G59+IF(H60="C/F",0,E60)-F60) -> 500747.73 | H60: =IF(B60="","",IF(IFERROR(MATCH(B60,'Advances_JAN-2025'!B:B,0),0)>0,"C/F","NEW")) -> NEW
A61: 16/02/2025 | B61: EXP4912 | C61: NNA REPAIR EXP-AKMAL- | E61: 300 | G61: =IF(E61="","",G60+IF(H61="C/F",0,E61)-F61) -> 501047.73 | H61: =IF(B61="","",IF(IFERROR(MATCH(B61,'Advances_JAN-2025'!B:B,0),0)>0,"C/F","NEW")) -> NEW
A62: 16/02/2025 | B62: EXP4912 | C62: NNA REPAIR EXP-ASLAM- | E62: 350 | G62: =IF(E62="","",G61+IF(H62="C/F",0,E62)-F62) -> 501397.73 | H62: =IF(B62="","",IF(IFERROR(MATCH(B62,'Advances_JAN-2025'!B:B,0),0)>0,"C/F","NEW")) -> NEW
A63: 20/02/2025 | B63: EXP4938 | C63: PURCHASE ADVANCE-ASLAM- | E63: 50 | G63: =IF(E63="","",G62+IF(H63="C/F",0,E63)-F63) -> 501447.73 | H63: =IF(B63="","",IF(IFERROR(MATCH(B63,'Advances_JAN-2025'!B:B,0),0)>0,"C/F","NEW")) -> NEW
A64: 23/02/2025 | B64: EXP4940 | C64: FUEL-ADVANCE-AKMAL- | E64: 100 | G64: =IF(E64="","",G63+IF(H64="C/F",0,E64)-F64) -> 501547.73 | H64: =IF(B64="","",IF(IFERROR(MATCH(B64,'Advances_JAN-2025'!B:B,0),0)>0,"C/F","NEW")) -> NEW
A65: 27/02/2025 | B65: EXP4983 | C65: PURCHASE ADVANCE -ASLAM- | E65: 2000 | G65: =IF(E65="","",G64+IF(H65="C/F",0,E65)-F65) -> 503547.73 | H65: =IF(B65="","",IF(IFERROR(MATCH(B65,'Advances_JAN-2025'!B:B,0),0)>0,"C/F","NEW")) -> NEW
A66: 27/02/2025 | B66: JN8707 | C66: COINS MARKET-KHUDAIR | E66: 8890 | G66: =IF(E66="","",G65+IF(H66="C/F",0,E66)-F66) -> 512437.73 | H66: =IF(B66="","",IF(IFERROR(MATCH(B66,'Advances_JAN-2025'!B:B,0),0)>0,"C/F","NEW")) -> NEW
G67: =IF(E67="","",G66+IF(H67="C/F",0,E67)-F67) | H67: =IF(B67="","",IF(IFERROR(MATCH(B67,'Advances_JAN-2025'!B:B,0),0)>0,"C/F","NEW"))
G68: =IF(E68="","",G67+IF(H68="C/F",0,E68)-F68) | H68: =IF(B68="","",IF(IFERROR(MATCH(B68,'Advances_JAN-2025'!B:B,0),0)>0,"C/F","NEW"))
G69: =IF(E69="","",G68+IF(H69="C/F",0,E69)-F69) | H69: =IF(B69="","",IF(IFERROR(MATCH(B69,'Advances_JAN-2025'!B:B,0),0)>0,"C/F","NEW"))
G70: =IF(E70="","",G69+IF(H70="C/F",0,E70)-F70) | H70: =IF(B70="","",IF(IFERROR(MATCH(B70,'Advances_JAN-2025'!B:B,0),0)>0,"C/F","NEW"))
G71: =IF(E71="","",G70+IF(H71="C/F",0,E71)-F71) | H71: =IF(B71="","",IF(IFERROR(MATCH(B71,'Advances_JAN-2025'!B:B,0),0)>0,"C/F","NEW"))
G72: =IF(E72="","",G71+IF(H72="C/F",0,E72)-F72) | H72: =IF(B72="","",IF(IFERROR(MATCH(B72,'Advances_JAN-2025'!B:B,0),0)>0,"C/F","NEW"))
G73: =IF(E73="","",G72+IF(H73="C/F",0,E73)-F73) | H73: =IF(B73="","",IF(IFERROR(MATCH(B73,'Advances_JAN-2025'!B:B,0),0)>0,"C/F","NEW"))
G74: =IF(E74="","",G73+IF(H74="C/F",0,E74)-F74) | H74: =IF(B74="","",IF(IFERROR(MATCH(B74,'Advances_JAN-2025'!B:B,0),0)>0,"C/F","NEW"))
G75: =IF(E75="","",G74+IF(H75="C/F",0,E75)-F75) | H75: =IF(B75="","",IF(IFERROR(MATCH(B75,'Advances_JAN-2025'!B:B,0),0)>0,"C/F","NEW"))
G76: =IF(E76="","",G75+IF(H76="C/F",0,E76)-F76) | H76: =IF(B76="","",IF(IFERROR(MATCH(B76,'Advances_JAN-2025'!B:B,0),0)>0,"C/F","NEW"))
G77: =IF(E77="","",G76+IF(H77="C/F",0,E77)-F77) | H77: =IF(B77="","",IF(IFERROR(MATCH(B77,'Advances_JAN-2025'!B:B,0),0)>0,"C/F","NEW"))
G78: =IF(E78="","",G77+IF(H78="C/F",0,E78)-F78) | H78: =IF(B78="","",IF(IFERROR(MATCH(B78,'Advances_JAN-2025'!B:B,0),0)>0,"C/F","NEW"))
... G100: =IF(E100="","",G99+IF(H100="C/F",0,E100)-F100) | H100: =IF(B100="","",IF(IFERROR(MATCH(B100,'Advances_JAN-2025'!B:B,0),0)>0,"C/F","NEW"))
A102: TOTAL | E102: =SUM(E7:E101) -> 324237.44 | F102: =SUM(F7:F101) -> 0
E104: =E3-E102 -> 164800.84

Sheet Suspense_FEB-2025
A1: SUSPENSE RECONCILIATION - FEB-2025
A3: OPENING BALANCE | B3: ='Suspense_JAN-2025'!E3 -> -62065.42 | D3: CLOSING BALANCE | E3: =-17267.64+SUM(E7:E1000)-SUM(F7:F1000) -> -162101.8
A5: UNIDENTIFIED TRANSACTIONS
A6: Date | B6: Journal No | C6: Description | D6: Reference | E6: Debit | F6: Credit | G6: Running Balance
A7: 45992 | B7: JN8408 | C7: BANK TRANSFER-NOT IDENTIFIED | E7: 0 | F7: 1800 | G7: =IF(AND(E7="",F7=""),"",B3+E7-F7) -> -63865.42
A8: 14/01/2025 | B8: JN8176 | C8: BANK TRANSFER-NIDHEEESH | E8: 0 | F8: 1 | G8: =IF(AND(E8="",F8=""),"",G7+E8-F8) -> -63866.42
A9: 19/01/2025 | B9: JN8400 | C9: BANK TRANSFER- | E9: 0 | F9: 2550 | G9: =IF(AND(E9="",F9=""),"",G8+E9-F9) -> -66416.42
A10: 45690 | B10: JN8696 | C10: BANK TRANSFER-NOT IDENTIFIED | E10: 0 | F10: 2500 | G10: =IF(AND(E10="",F10=""),"",G9+E10-F10) -> -68916.42
A11: 45690 | B11: JN8697 | C11: BANK TRANSFER-NOT IDENTIFIED | E11: 0 | F11: 1600 | G11: =IF(AND(E11="",F11=""),"",G10+E11-F11) -> -70516.42
A12: 45810 | B12: JN8432 | C12: BANK TRANSFER-KHALID | E12: 460 | F12: 0 | G12: =IF(AND(E12="",F12=""),"",G11+E12-F12) -> -70056.42
A13: 15/02/2025 | B13: JN8698 | C13: BANK TRANSFER-NOT IDENTIFIED | E13: 0 | F13: 783.9 | G13: =IF(AND(E13="",F13=""),"",G12+E13-F13) -> -70840.32
A14: 17/02/2025 | B14: JN8679 | C14: BANK TRANSFER-NOT IDENTIFIED | E14: 0 | F14: 564.91 | G14: =IF(AND(E14="",F14=""),"",G13+E14-F14) -> -71405.23
A15: 19/02/2025 | B15: JN8699 | C15: BANK TRANSFER-NOT IDENTIFIED | E15: 0 | F15: 969.86 | G15: =IF(AND(E15="",F15=""),"",G14+E15-F15) -> -72375.09
A16: 20/02/2025 | B16: JN8700 | C16: BANK TRANSFER-NOT IDENTIFIED | E16: 0 | F16: 562 | G16: =IF(AND(E16="",F16=""),"",G15+E16-F16) -> -72937.09
A17: 20/02/2025 | B17: JN8680 | C17: BANK POS-QASEEM | E17: 0 | F17: 49.53 | G17: =IF(AND(E17="",F17=""),"",G16+E17-F17) -> -72986.62
A18: 20/02/2025 | B18: JN8681 | C18: BANK POS-QASEEM | E18: 0 | F18: 108.98 | G18: =IF(AND(E18="",F18=""),"",G17+E18-F18) -> -73095.6
A19: 20/02/2025 | B19: JN8682 | C19: BANK POS-SHAREEF | E19: 0 | F19: 4394.06 | G19: =IF(AND(E19="",F19=""),"",G18+E19-F19) -> -77489.66
A20: 22/02/2025 | B20: JN8701 | C20: BANK TRANSFER-NOT IDENTIFIED | E20: 0 | F20: 1022 | G20: =IF(AND(E20="",F20=""),"",G19+E20-F20) -> -78511.66
A21: 23/02/2025 | B21: JN8703 | C21: BANK TRANSFER-NOT IDENTIFIED | E21: 0 | F21: 1125 | G21: =IF(AND(E21="",F21=""),"",G20+E21-F21) -> -79636.66
A22: 23/02/2025 | B22: JN8683 | C22: BANK POS-SHAREEF | E22: 0 | F22: 484.97 | G22: =IF(AND(E22="",F22=""),"",G21+E22-F22) -> -80121.63
A23: 24/02/2025 | B23: JN8684 | C23: BANK POS-SHAREEF | E23: 0 | F23: 664 | G23: =IF(AND(E23="",F23=""),"",G22+E23-F23) -> -80785.63
A24: 24/02/2025 | B24: JN8704 | C24: BANK TRANSFER-NOT IDENTIFIED | E24: 0 | F24: 5008 | G24: =IF(AND(E24="",F24=""),"",G23+E24-F24) -> -85793.63
... A44: 28/02/2025 | B44: EXP4993 | C44: Installment Payment FOR NEW SALES VEHICLE HIACE- | E44: 4308.03 | F44: 0 | G44: =IF(AND(E44="",F44=""),"",G43+E44-F44) -> -142785.62
A45: 28/02/2025 | B45: EXP4993 | C45: Installment Payment FOR NEW SALES VEHICLE HIACE- | E45: 4308.03 | G45: =IF(AND(E45="",F45=""),"",G44+E45-F45) -> -138477.59
A46: 28/02/2025 | B46: EXP4993 | C46: Installment Payment FOR NEW SALES VEHICLE HIACE- | E46: 4308.03 | F46: 0 | G46: =IF(AND(E46="",F46=""),"",G45+E46-F46) -> -134169.56
A47: 45659 | B47: JN8328 | C47: BANK POS-THOYYIB | E47: 183.98 | G47: =IF(AND(E47="",F47=""),"",G46+E47-F47) -> -133985.58
A48: 28/02/2025 | B48: JN8731 | C48: BANK TRANSFER-SADATH | E48: 0 | F48: 278.95 | G48: =IF(AND(E48="",F48=""),"",G47+E48-F48) -> -134264.53
A49: 28/02/2025 | B49: JN8732 | C49: BANK TRANSFER-NOT IDENTIFIED | E49: 0 | F49: 217.97 | G49: =IF(AND(E49="",F49=""),"",G48+E49-F49) -> -134482.5
G50: =IF(AND(E50="",F50=""),"",G49+E50-F50)
G51: =IF(AND(E51="",F51=""),"",G50+E51-F51)
G52: =IF(AND(E52="",F52=""),"",G51+E52-F52)
G53: =IF(AND(E53="",F53=""),"",G52+E53-F53)
G54: =IF(AND(E54="",F54=""),"",G53+E54-F54)
G55: =IF(AND(E55="",F55=""),"",G54+E55-F55)
G56: =IF(AND(E56="",F56=""),"",G55+E56-F56)
G57: =IF(AND(E57="",F57=""),"",G56+E57-F57)
G58: =IF(AND(E58="",F58=""),"",G57+E58-F58)
G59: =IF(AND(E59="",F59=""),"",G58+E59-F59)
G60: =IF(AND(E60="",F60=""),"",G59+E60-F60)
G61: =IF(AND(E61="",F61=""),"",G60+E61-F61)
... G69: =IF(AND(E69="",F69=""),"",G68+E69-F69)
G70: =IF(AND(E70="",F70=""),"",G69+E70-F70) | H70: =IF(B70="","","NEW")
G71: =IF(AND(E71="",F71=""),"",G70+E71-F71) | H71: =IF(B71="","","NEW")
G72: =IF(AND(E72="",F72=""),"",G71+E72-F72) | H72: =IF(B72="","","NEW")
G73: =IF(AND(E73="",F73=""),"",G72+E73-F73) | H73: =IF(B73="","","NEW")
G74: =IF(AND(E74="",F74=""),"",G73+E74-F74) | H74: =IF(B74="","","NEW")
G75: =IF(AND(E75="",F75=""),"",G74+E75-F75) | H75: =IF(B75="","","NEW")
G76: =IF(AND(E76="",F76=""),"",G75+E76-F76) | H76: =IF(B76="","","NEW")
G77: =IF(AND(E77="",F77=""),"",G76+E77-F77) | H77: =IF(B77="","","NEW")
G78: =IF(AND(E78="",F78=""),"",G77+E78-F78) | H78: =IF(B78="","","NEW")
G79: =IF(AND(E79="",F79=""),"",G78+E79-F79) | H79: =IF(B79="","","NEW")
G80: =IF(AND(E80="",F80=""),"",G79+E80-F80) | H80: =IF(B80="","","NEW")
G81: =IF(AND(E81="",F81=""),"",G80+E81-F81) | H81: =IF(B81="","","NEW")
... G100: =IF(AND(E100="",F100=""),"",G99+E100-F100) | H100: =IF(B100="","","NEW")
A102: TOTAL | E102: =SUM(E7:E101) -> 16148.17 | F102: =SUM(F7:F101) -> 88565.25

Sheet Outstanding_FEB-2025
A1: =COUNTIF(D:D,"Ashik") -> 10
A3: Salesman
A4: Nidheesh | B4: =SUMIF($D$21:$D$504,A4,$G$21:$G$504) -> 45063.62 | C4: =COUNTIF($D$21:$D$504,A4) -> 34 | D4: =IFERROR(B4/C4,0) -> 1325.4006
A5: Jaseel | B5: =SUMIF($D$21:$D$504,A5,$G$21:$G$504) -> 25395.4 | C5: =COUNTIF($D$21:$D$504,A5) -> 19 | D5: =IFERROR(B5/C5,0) -> 1336.6
A6: Bassam | B6: =SUMIF($D$21:$D$504,A6,$G$21:$G$504) -> 7652.1 | C6: =COUNTIF($D$21:$D$504,A6) -> 6 | D6: =IFERROR(B6/C6,0) -> 1275.35
A7: akmal | B7: =SUMIF($D$21:$D$504,A7,$G$21:$G$504) -> 837.92 | C7: =COUNTIF($D$21:$D$504,A7) -> 3 | D7: =IFERROR(B7/C7,0) -> 279.30667
A8: arshad | B8: =SUMIF($D$21:$D$504,A8,$G$21:$G$504) -> 386314.4 | C8: =COUNTIF($D$21:$D$504,A8) -> 28 | D8: =IFERROR(B8/C8,0) -> 13796.943
A9: Shameer riyadh | B9: =SUMIF($D$21:$D$504,A9,$G$21:$G$504) -> 45700.21 | C9: =COUNTIF($D$21:$D$504,A9) -> 24 | D9: =IFERROR(B9/C9,0) -> 1904.1754
A10: company sales | B10: =SUMIF($D$21:$D$504,A10,$G$21:$G$504) -> 778183.07 | C10: =COUNTIF($D$21:$D$504,A10) -> 14 | D10: =IFERROR(B10/C10,0) -> 55584.505
A11: shafi | B11: =SUMIF($D$21:$D$504,A11,$G$21:$G$504) -> 0 | C11: =COUNTIF($D$21:$D$504,A11) -> 0 | D11: =IFERROR(B11/C11,0) -> 0
A12: dhiya | B12: =SUMIF($D$21:$D$504,A12,$G$21:$G$504) -> 228497.88 | C12: =COUNTIF($D$21:$D$504,A12) -> 18 | D12: =IFERROR(B12/C12,0) -> 12694.327
A13: samir | B13: =SUMIF($D$21:$D$504,A13,$G$21:$G$504) -> 11134.02 | C13: =COUNTIF($D$21:$D$504,A13) -> 7 | D13: =IFERROR(B13/C13,0) -> 1590.5743
A14: Khalid | B14: =SUMIF($D$22:$D$505,A14,$G$22:$G$505) -> 57646.36 | C14: =COUNTIF($D$22:$D$505,A14) -> 99 | D14: =IFERROR(B14/C14,0) -> 582.28646
A15: Ashik | B15: =SUMIF($D$21:$D$504,A15,$G$21:$G$504) -> 3500.62 | C15: =COUNTIF($D$21:$D$504,A15) -> 10 | D15: =IFERROR(B15/C15,0) -> 350.062
A16: shareef | B16: =SUMIF($D$21:$D$504,A16,$G$21:$G$504) -> 0 | C16: =COUNTIF($D$21:$D$504,A16) -> 0 | D16: =IFERROR(B16/C16,0) -> 0
A17: TOTAL | B17: =SUM(B4:B16) -> 1589925.6 | C17: =SUM(C4:C8) -> 90 | D17: =IFERROR(B17/C17,0) -> 17665.84
A19: CUSTOMER DETAILS
A20: Customer Code | B20: Customer Name | C20: Area | D20: Salesman | E20: Invoice Amount | F20: Paid Amount | G20: Balance | H20: Days
A21: CUST56 | B21: Nour al zahraa supermarket | C21: Al Ahsa-2 | D21: Nidheesh | E21: 553.94 | G21: =IF(E21="","",E21-F21) -> 553.94
A22: CUST57 | B22: Essa Muhammad al Abbadi | C22: Al Ahsa-2 | D22: Nidheesh | E22: 135.97 | G22: =IF(E22="","",E22-F22) -> 135.97
A23: CUST154 | B23: Moona al aila family | C23: Al Ahsa-2 | D23: Nidheesh | E23: 247.95 | G23: =IF(E23="","",E23-F23) -> 247.95
A24: CUST156 | B24: Al nouri grocery to sell food | C24: Al Ahsa-2 | D24: Nidheesh | E24: 1833.85 | G24: =IF(E24="","",E24-F24) -> 1833.85
A25: CUST175 | B25: Red apple supermarket | C25: Al Ahsa-2 | D25: Nidheesh | E25: 578.91 | G25: =IF(E25="","",E25-F25) -> 578.91
A26: CUST199 | B26: Thamuniyath wajihath al busthan | C26: Al Ahsa-2 | D26: Nidheesh | E26: 595.91 | G26: =IF(E26="","",E26-F26) -> 595.91
A27: CUST202 | B27: Athareek al mothi | C27: Al Ahsa-2 | D27: Nidheesh | E27: 1651.78 | G27: =IF(E27="","",E27-F27) -> 1651.78
A28: CUST203 | B28: Al Amana foodstuff market. 2 | C28: Al Ahsa-2 | D28: Nidheesh | E28: 833.87 | G28: =IF(E28="","",E28-F28) -> 833.87
A29: CUST285 | B29: Mosasath likuli almujtamae altijaria | C29: Al Ahsa-2 | D29: Nidheesh | E29: 837.89 | G29: =IF(E29="","",E29-F29) -> 837.89
A30: CUST347 | B30: Markaz Darth al shahsi | C30: Al Ahsa-2 | D30: Nidheesh | E30: 611.94 | G30: =IF(E30="","",E30-F30) -> 611.94
A31: CUST349 | B31: Al Amana foodstuff market.. | C31: Al Ahsa-2 | D31: Nidheesh | E31: 1075.85 | G31: =IF(E31="","",E31-F31) -> 1075.85
A32: CUST421 | B32: Nasaem al nada.. | C32: Al Ahsa-2 | D32: Nidheesh | E32: 782.79 | G32: =IF(E32="","",E32-F32) -> 782.79
... A282: CUST3704 | B282: CITY FLOWER Trading Company | C282: Company Direct Sales | D282: company sales | E282: 82800 | G282: =IF(E282="","",E282-F282) -> 82800
G283: =IF(E283="","",E283-F283)
G284: =IF(E284="","",E284-F284)
G285: =IF(E285="","",E285-F285)
G286: =IF(E286="","",E286-F286)
G287: =IF(E287="","",E287-F287)
G288: =IF(E288="","",E288-F288)
G289: =IF(E289="","",E289-F289)
G290: =IF(E290="","",E290-F290)
G291: =IF(E291="","",E291-F291)
G292: =IF(E292="","",E292-F292)
G293: =IF(E293="","",E293-F293)
G294: =IF(E294="","",E294-F294)
... G503: =IF(E503="","",E503-F503)
A505: GRAND TOTAL | E505: =SUM(E21:E504) -> 1589925.6 | F505: =SUM(F21:F504) -> 0 | G505: =SUM(G21:G504) -> 1589925.6

Sheet Banks_MAR-2025
A1: BANK SUMMARY - MAR-2025
A3: Bank Name | B3: Opening Balance | C3: Total Received | D3: Bank Charges | E3: Total Payments | F3: Closing Balance | G3: Notes
A4: Alrajhi-1097 | B4: 657344.05 | C4: 525105.91 | D4: 2564.75 | E4: 239137.37 | F4: =B4+C4-D4-E4 -> 940747.84
A5: Alrajhi-new | B5: 423191.11 | C5: 202402.29 | D5: 0 | E5: 0 | F5: =B5+C5-D5-E5 -> 625593.4
A6: SNB Al Ahsa Branch | B6: 653579.58 | C6: 369640.72 | D6: 373.75 | E6: 900000 | F6: =B6+C6-D6-E6 -> 122846.55
A7: Albilad | B7: 524310.03 | C7: 1481307 | D7: 0 | E7: 1975557.4 | F7: =B7+C7-D7-E7 -> 30059.63
A9: SUB-TOTAL SAR | B9: =SUM(B4:B7) -> 2258424.8 | C9: =SUM(C4:C7) -> 2578455.9 | D9: =SUM(D4:D7) -> 2938.5 | E9: =SUM(E4:E7) -> 3114694.8 | F9: =SUM(F4:F7) -> 1719247.4
A11: USD ACCOUNTS
A12: Bank Name | B12: Opening | C12: Amount Received | D12: Bank Charge | E12: Payment | F12: Balance | G12: Notes
A13: Albilad USD | B13: 605.36 | C13: 434612.1 | D13: 0 | E13: 434302.82 | F13: =B13+C13-D13-E13 -> 914.64
A15: SUB-TOTAL USD | B15: =SUM(B13) -> 605.36 | C15: =SUM(C13) -> 434612.1 | D15: =SUM(D13) -> 0 | E15: =SUM(E13) -> 434302.82 | F15: =SUM(F13) -> 914.64
A17: GRAND TOTAL (SAR + USD Converted) | B17: =B9+B15*3.75 -> 2260694.9 | C17: =C9+C15*3.75 -> 4208251.3 | D17: =D9+D15*3.75 -> 2938.5 | E17: =E9+E15*3.75 -> 4743330.3 | F17: =F9+F15*3.75 -> 1722677.3
A19: SUMMARY
A20: Total Bank Balance (SAR): | C20: =F17 -> 1722677.3

Sheet Advances_MAR-2025
A1: ADVANCE RECONCILIATION - MAR-2025
A3: OPENING BALANCE | B3: ='Advances_FEB-2025'!E3 -> 489038.28 | D3: CLOSING BALANCE | E3: =164800.84+SUM(E7:E101) -> 491564.28
A5: TRANSACTIONS
A6: Date | B6: Voucher No | C6: Description | D6: Person/Party | E6: Advance Given | F6: Amount Settled | G6: Running Balance
A7: 45447 | B7: EXP3275 | C7: CONSTRUCTION WORK ADVANCE RAJENDHRAN- | E7: 3000 | G7: =IF(E7="","",B$3+IF(H7="C/F",0,E7)-F7) -> 489038.28 | H7: =IF(B7="","",IF(IFERROR(MATCH(B7,'Advances_FEB-2025'!B:B,0),0)>0,"C/F","NEW")) -> C/F
A8: 17/04/2024 | B8: EXP3295 | C8: TANJI BAO PAYMENT TO BE CHARGED TO BOILING POT- | E8: 8625 | G8: =IF(E8="","",G7+IF(H8="C/F",0,E8)-F8) -> 489038.28 | H8: =IF(B8="","",IF(IFERROR(MATCH(B8,'Advances_FEB-2025'!B:B,0),0)>0,"C/F","NEW")) -> C/F
A9: 17/04/2024 | B9: EXP3391 | C9: Shirfan - Cash withdraw -- | E9: 1500 | G9: =IF(E9="","",G8+IF(H9="C/F",0,E9)-F9) -> 489038.28 | H9: =IF(B9="","",IF(IFERROR(MATCH(B9,'Advances_FEB-2025'!B:B,0),0)>0,"C/F","NEW")) -> C/F
A10: 16/05/2024 | B10: EXP3422 | C10: sabari-seeds unloading staff refreshment drink- | E10: 20 | G10: =IF(E10="","",G9+IF(H10="C/F",0,E10)-F10) -> 489038.28 | H10: =IF(B10="","",IF(IFERROR(MATCH(B10,'Advances_FEB-2025'!B:B,0),0)>0,"C/F","NEW")) -> C/F
A11: 27/05/2024 | B11: EXP3462 | C11: THOYYIB VEHICLE WINGE EXP- | E11: 350 | G11: =IF(E11="","",G10+IF(H11="C/F",0,E11)-F11) -> 489038.28 | H11: =IF(B11="","",IF(IFERROR(MATCH(B11,'Advances_FEB-2025'!B:B,0),0)>0,"C/F","NEW")) -> C/F
A12: 27/05/2024 | B12: EXP3462 | C12: ADVANCES -THOYYIBE VEHICLE COMPLAINT- | E12: 143.48 | G12: =IF(E12="","",G11+IF(H12="C/F",0,E12)-F12) -> 489038.28 | H12: =IF(B12="","",IF(IFERROR(MATCH(B12,'Advances_FEB-2025'!B:B,0),0)>0,"C/F","NEW")) -> C/F
A13: 27/05/2024 | B13: EXP3462 | C13: ADVANCES -THOYYIBE VEHICLE COMPLAINT- | E13: 600 | G13: =IF(E13="","",G12+IF(H13="C/F",0,E13)-F13) -> 489038.28 | H13: =IF(B13="","",IF(IFERROR(MATCH(B13,'Advances_FEB-2025'!B:B,0),0)>0,"C/F","NEW")) -> C/F
A14: 45602 | B14: EXP3508 | C14: AMITHFOOD ADVANCE-SABARI- | E14: 15 | G14: =IF(E14="","",G13+IF(H14="C/F",0,E14)-F14) -> 489038.28 | H14: =IF(B14="","",IF(IFERROR(MATCH(B14,'Advances_FEB-2025'!B:B,0),0)>0,"C/F","NEW")) -> C/F
A15: 16/06/2024 | B15: EXP3683 | C15: AIR TRANSPORTAION AIR LANKA- | E15: 2730 | G15: =IF(E15="","",G14+IF(H15="C/F",0,E15)-F15) -> 489038.28 | H15: =IF(B15="","",IF(IFERROR(MATCH(B15,'Advances_FEB-2025'!B:B,0),0)>0,"C/F","NEW")) -> C/F
A16: 16/06/2024 | B16: JN5365 | C16: COLLECTION CASH TAKEN BY HANI | E16: 34000 | G16: =IF(E16="","",G15+IF(H16="C/F",0,E16)-F16) -> 489038.28 | H16: =IF(B16="","",IF(IFERROR(MATCH(B16,'Advances_FEB-2025'!B:B,0),0)>0,"C/F","NEW")) -> C/F
A17: 24/06/2024 | B17: EXP3614 | C17: ADVANCE-SALMANUL FARIZ-RIYADH- | E17: 500 | G17: =IF(E17="","",G16+IF(H17="C/F",0,E17)-F17) -> 489038.28 | H17: =IF(B17="","",IF(IFERROR(MATCH(B17,'Advances_FEB-2025'!B:B,0),0)>0,"C/F","NEW")) -> C/F
A18: 45298 | B18: EXP3645 | C18: ASHIK-ADVANCE- | E18: 4000 | G18: =IF(E18="","",G17+IF(H18="C/F",0,E18)-F18) -> 489038.28 | H18: =IF(B18="","",IF(IFERROR(MATCH(B18,'Advances_FEB-2025'!B:B,0),0)>0,"C/F","NEW")) -> C/F
A19: 45358 | B19: EXP3654 | C19: SIVA RIYADH TRAVELING EXP ADVANCE-- | E19: 2000 | G19: =IF(E19="","",G18+IF(H19="C/F",0,E19)-F19) -> 489038.28 | H19: =IF(B19="","",IF(IFERROR(MATCH(B19,'Advances_FEB-2025'!B:B,0),0)>0,"C/F","NEW")) -> C/F
A20: 45450 | B20: EXP3699 | C20: FT24188664289852 Ben WHITE GRAPHICS-ADVANCE FOR RECEPTION WORK- | E20: 2790 | G20: =IF(E20="","",G19+IF(H20="C/F",0,E20)-F20) -> 489038.28 | H20: =IF(B20="","",IF(IFERROR(MATCH(B20,'Advances_FEB-2025'!B:B,0),0)>0,"C/F","NEW")) -> C/F
A21: 45603 | B21: EXP3749 | C21: FUEL ADVANCE-MUNEESH- | E21: 50 | G21: =IF(E21="","",G20+IF(H21="C/F",0,E21)-F21) -> 489038.28 | H21: =IF(B21="","",IF(IFERROR(MATCH(B21,'Advances_FEB-2025'!B:B,0),0)>0,"C/F","NEW")) -> C/F
A22: 17/07/2024 | B22: EXP4088 | C22: Traffic Violati REF 5366217470-7023706836-TRAFFIC -NIDHEESH- | E22: 113 | G22: =IF(E22="","",G21+IF(H22="C/F",0,E22)-F22) -> 489038.28 | H22: =IF(B22="","",IF(IFERROR(MATCH(B22,'Advances_FEB-2025'!B:B,0),0)>0,"C/F","NEW")) -> C/F
A23: 31/07/2024 | B23: EXP4021 | C23: FUEL-ADVANCE-NASAR- | E23: 100 | G23: =IF(E23="","",G22+IF(H23="C/F",0,E23)-F23) -> 489038.28 | H23: =IF(B23="","",IF(IFERROR(MATCH(B23,'Advances_FEB-2025'!B:B,0),0)>0,"C/F","NEW")) -> C/F
A24: 45573 | B24: EXP4074 | C24: SARIKA TAXI EXP -- | E24: 60 | G24: =IF(E24="","",G23+IF(H24="C/F",0,E24)-F24) -> 489038.28 | H24: =IF(B24="","",IF(IFERROR(MATCH(B24,'Advances_FEB-2025'!B:B,0),0)>0,"C/F","NEW")) -> C/F
A25: 13/08/2024 | B25: EXP4197 | C25: AL JARAHA ADVANCE PAYMENT-METAL DETECTOR AND HIGHSPEED PACKING MACHINE-FT24226303374754- | E25: 74656.7 | G25: =IF(E25="","",G24+IF(H25="C/F",0,E25)-F25) -> 489038.28 | H25: =IF(B25="","",IF(IFERROR(MATCH(B25,'Advances_FEB-2025'!B:B,0),0)>0,"C/F","NEW")) -> C/F
A26: 13/08/2024 | B26: EXP4198 | C26: AL JARAHA ADVANCE PAYMENT-METAL DETECTOR AND HIGHSPEED PACKING MACHINE-FT24226094147820- | E26: 25655.23 | G26: =IF(E26="","",G25+IF(H26="C/F",0,E26)-F26) -> 489038.28 | H26: =IF(B26="","",IF(IFERROR(MATCH(B26,'Advances_FEB-2025'!B:B,0),0)>0,"C/F","NEW")) -> C/F
A27: 27/08/2024 | B27: EXP4327 | C27: FT24240219059921 Ben EGYPTIAN SAUDI IMPORT EXPORT PAPER-DOUBLE TRANSFER-AMOUNT- | E27: 5000 | G27: =IF(E27="","",G26+IF(H27="C/F",0,E27)-F27) -> 489038.28 | H27: =IF(B27="","",IF(IFERROR(MATCH(B27,'Advances_FEB-2025'!B:B,0),0)>0,"C/F","NEW")) -> C/F
A28: 29/08/2024 | B28: EXP4267 | C28: PURCHASE ADVANCE-FAWAS- | E28: 45 | G28: =IF(E28="","",G27+IF(H28="C/F",0,E28)-F28) -> 489038.28 | H28: =IF(B28="","",IF(IFERROR(MATCH(B28,'Advances_FEB-2025'!B:B,0),0)>0,"C/F","NEW")) -> C/F
A29: 45326 | B29: EXP3255 | C29: FUEL EXP MUNEESH- | E29: 30 | G29: =IF(E29="","",G28+IF(H29="C/F",0,E29)-F29) -> 489038.28 | H29: =IF(B29="","",IF(IFERROR(MATCH(B29,'Advances_FEB-2025'!B:B,0),0)>0,"C/F","NEW")) -> C/F
A30: 45605 | B30: EXP4358 | C30: Advances-Muneesh- | E30: 613.5 | G30: =IF(E30="","",G29+IF(H30="C/F",0,E30)-F30) -> 489038.28 | H30: =IF(B30="","",IF(IFERROR(MATCH(B30,'Advances_FEB-2025'!B:B,0),0)>0,"C/F","NEW")) -> C/F
A31: 25/09/2024 | B31: EXP4401 | C31: TRAFFIC-VIOLATIONS- | E31: 113 | G31: =IF(E31="","",G30+IF(H31="C/F",0,E31)-F31) -> 489038.28 | H31: =IF(B31="","",IF(IFERROR(MATCH(B31,'Advances_FEB-2025'!B:B,0),0)>0,"C/F","NEW")) -> C/F
A32: 25/09/2024 | B32: EXP4401 | C32: TRAFFIC-VIOLATIONS- | E32: 75 | G32: =IF(E32="","",G31+IF(H32="C/F",0,E32)-F32) -> 489038.28 | H32: =IF(B32="","",IF(IFERROR(MATCH(B32,'Advances_FEB-2025'!B:B,0),0)>0,"C/F","NEW")) -> C/F
A33: 13/10/2024 | B33: EXP4386 | C33: SHIRFAN ADVANCE FROM NIDHEESH COLLECTION- | E33: 4650 | G33: =IF(E33="","",G32+IF(H33="C/F",0,E33)-F33) -> 489038.28 | H33: =IF(B33="","",IF(IFERROR(MATCH(B33,'Advances_FEB-2025'!B:B,0),0)>0,"C/F","NEW")) -> C/F
A34: 20/10/2024 | B34: EXP4423 | C34: THOYYIB ADVANCE QASEEM NEW ROUTE- | E34: 500 | G34: =IF(E34="","",G33+IF(H34="C/F",0,E34)-F34) -> 489038.28 | H34: =IF(B34="","",IF(IFERROR(MATCH(B34,'Advances_FEB-2025'!B:B,0),0)>0,"C/F","NEW")) -> C/F
A35: 27/10/2024 | B35: EXP4488 | C35: SHIRFAN FROM ARSHADH COLLECTION- | E35: 2000 | G35: =IF(E35="","",G34+IF(H35="C/F",0,E35)-F35) -> 489038.28 | H35: =IF(B35="","",IF(IFERROR(MATCH(B35,'Advances_FEB-2025'!B:B,0),0)>0,"C/F","NEW")) -> C/F
A36: 31/10/2024 | C36: MANAFIZ RENT DMM ROUTE | E36: 16857.45 | G36: =IF(E36="","",G35+IF(H36="C/F",0,E36)-F36) -> 505895.73 | H36: =IF(B36="","",IF(IFERROR(MATCH(B36,'Advances_FEB-2025'!B:B,0),0)>0,"C/F","NEW"))
A37: 31/10/2024 | B37: EXP4499 | C37: SHIRFAN ADVANCE- | E37: 2000 | G37: =IF(E37="","",G36+IF(H37="C/F",0,E37)-F37) -> 505895.73 | H37: =IF(B37="","",IF(IFERROR(MATCH(B37,'Advances_FEB-2025'!B:B,0),0)>0,"C/F","NEW")) -> C/F
A38: 45546 | B38: EXP4569 | C38: SALMAN FARIZ ADVANCE FROM NIDHEESH COLLECTION- | E38: 4450 | G38: =IF(E38="","",G37+IF(H38="C/F",0,E38)-F38) -> 505895.73 | H38: =IF(B38="","",IF(IFERROR(MATCH(B38,'Advances_FEB-2025'!B:B,0),0)>0,"C/F","NEW")) -> C/F
A39: 45637 | B39: EXP4573 | C39: ASLAM ADVANCE TO SALMAN FARIZ- | E39: 80 | G39: =IF(E39="","",G38+IF(H39="C/F",0,E39)-F39) -> 505895.73 | H39: =IF(B39="","",IF(IFERROR(MATCH(B39,'Advances_FEB-2025'!B:B,0),0)>0,"C/F","NEW")) -> C/F
A40: 18/11/2024 | B40: EXP4597 | C40: PURCHASE ADVANCE-FAWAS- | E40: 20 | G40: =IF(E40="","",G39+IF(H40="C/F",0,E40)-F40) -> 505895.73 | H40: =IF(B40="","",IF(IFERROR(MATCH(B40,'Advances_FEB-2025'!B:B,0),0)>0,"C/F","NEW")) -> C/F
A41: 45303 | B41: EXP4637 | C41: SALMAN FARIZ ADVANCE-GAS PURCHASE- | E41: 20.87 | G41: =IF(E41="","",G40+IF(H41="C/F",0,E41)-F41) -> 505895.73 | H41: =IF(B41="","",IF(IFERROR(MATCH(B41,'Advances_FEB-2025'!B:B,0),0)>0,"C/F","NEW")) -> C/F
A42: 45303 | B42: EXP4637 | C42: SHIRFAN ADVANCES-SINGLE SOCKET- | E42: 34.78 | G42: =IF(E42="","",G41+IF(H42="C/F",0,E42)-F42) -> 505895.73 | H42: =IF(B42="","",IF(IFERROR(MATCH(B42,'Advances_FEB-2025'!B:B,0),0)>0,"C/F","NEW")) -> C/F
A43: 45303 | B43: EXP4637 | C43: LED-HALOGEN LAMB- | E43: 60.87 | G43: =IF(E43="","",G42+IF(H43="C/F",0,E43)-F43) -> 505895.73 | H43: =IF(B43="","",IF(IFERROR(MATCH(B43,'Advances_FEB-2025'!B:B,0),0)>0,"C/F","NEW")) -> C/F
A44: 45394 | B44: EXP4685 | C44: NEW STAFF SAFEER BED- | E44: 80.5 | G44: =IF(E44="","",G43+IF(H44="C/F",0,E44)-F44) -> 505895.73 | H44: =IF(B44="","",IF(IFERROR(MATCH(B44,'Advances_FEB-2025'!B:B,0),0)>0,"C/F","NEW")) -> C/F
A45: 45394 | B45: EXP4685 | C45: NEW STAFF SAFEER PILLOW- | E45: 11.5 | G45: =IF(E45="","",G44+IF(H45="C/F",0,E45)-F45) -> 505895.73 | H45: =IF(B45="","",IF(IFERROR(MATCH(B45,'Advances_FEB-2025'!B:B,0),0)>0,"C/F","NEW")) -> C/F
A46: 45577 | B46: EXP4697 | C46: AL JARAHA ADVANCE PAYMENT-METAL DETECTOR AND HIGHSPEED PACKING MACHINE-FT24226094147820- | E46: 49001.48 | G46: =IF(E46="","",G45+IF(H46="C/F",0,E46)-F46) -> 505895.73 | H46: =IF(B46="","",IF(IFERROR(MATCH(B46,'Advances_FEB-2025'!B:B,0),0)>0,"C/F","NEW")) -> C/F
A47: 15/12/2024 | B47: EXP4705 | C47: FOOD EXPENSE ADANCE-shirfan- Nepali man power supply food- | E47: 180 | G47: =IF(E47="","",G46+IF(H47="C/F",0,E47)-F47) -> 505895.73 | H47: =IF(B47="","",IF(IFERROR(MATCH(B47,'Advances_FEB-2025'!B:B,0),0)>0,"C/F","NEW")) -> C/F
A48: 16/12/2024 | B48: JN7768 | C48: CASH COLLCETION SHORT -KHALID | E48: 1337.87 | G48: =IF(E48="","",G47+IF(H48="C/F",0,E48)-F48) -> 505895.73 | H48: =IF(B48="","",IF(IFERROR(MATCH(B48,'Advances_FEB-2025'!B:B,0),0)>0,"C/F","NEW")) -> C/F
A49: 16/12/2024 | B49: EXP4707 | C49: KHALID COLLECTION AMOUNT GIVEN TO AYOOB- | E49: 7500 | G49: =IF(E49="","",G48+IF(H49="C/F",0,E49)-F49) -> 505895.73 | H49: =IF(B49="","",IF(IFERROR(MATCH(B49,'Advances_FEB-2025'!B:B,0),0)>0,"C/F","NEW")) -> C/F
A50: 24/12/2024 | B50: EXP4745 | C50: COINS SHORT-ADVANCE- | E50: 85 | G50: =IF(E50="","",G49+IF(H50="C/F",0,E50)-F50) -> 505895.73 | H50: =IF(B50="","",IF(IFERROR(MATCH(B50,'Advances_FEB-2025'!B:B,0),0)>0,"C/F","NEW")) -> C/F
A51: 25/12/2024 | B51: EXP4747 | C51: SHIRFAN ADVANCE NIDHEESH COLLECTION- | E51: 300 | G51: =IF(E51="","",G50+IF(H51="C/F",0,E51)-F51) -> 505895.73 | H51: =IF(B51="","",IF(IFERROR(MATCH(B51,'Advances_FEB-2025'!B:B,0),0)>0,"C/F","NEW")) -> C/F
A52: 30/12/2024 | B52: EXP4756 | C52: FUEL-ADVANCE-FAWAS- | E52: 150 | G52: =IF(E52="","",G51+IF(H52="C/F",0,E52)-F52) -> 505895.73 | H52: =IF(B52="","",IF(IFERROR(MATCH(B52,'Advances_FEB-2025'!B:B,0),0)>0,"C/F","NEW")) -> C/F
A53: 45901 | B53: EXP4786 | C53: BAB REPAIR DAMAGE CHANGE-DHIYA ADVANCE- | E53: 450 | G53: =IF(E53="","",G52+IF(H53="C/F",0,E53)-F53) -> 505895.73 | H53: =IF(B53="","",IF(IFERROR(MATCH(B53,'Advances_FEB-2025'!B:B,0),0)>0,"C/F","NEW")) -> C/F
A54: 14/01/2025 | B54: EXP4790 | C54: Al jara machinary payment- | E54: 51310.45 | G54: =IF(E54="","",G53+IF(H54="C/F",0,E54)-F54) -> 505895.73 | H54: =IF(B54="","",IF(IFERROR(MATCH(B54,'Advances_FEB-2025'!B:B,0),0)>0,"C/F","NEW")) -> C/F
A55: 16/01/2025 | B55: EXP4794 | C55: PURCHASE ADVANCE SABARI- | E55: 400 | G55: =IF(E55="","",G54+IF(H55="C/F",0,E55)-F55) -> 505895.73 | H55: =IF(B55="","",IF(IFERROR(MATCH(B55,'Advances_FEB-2025'!B:B,0),0)>0,"C/F","NEW")) -> C/F
A56: 45749 | B56: EXP4884 | C56: PURCHASE ADVANCE-ASHOK- | E56: 200 | G56: =IF(E56="","",G55+IF(H56="C/F",0,E56)-F56) -> 505895.73 | H56: =IF(B56="","",IF(IFERROR(MATCH(B56,'Advances_FEB-2025'!B:B,0),0)>0,"C/F","NEW")) -> C/F
A57: 45810 | B57: JN8432 | C57: COLLECTION SHORT-KHALID | E57: 1617.41 | G57: =IF(E57="","",G56+IF(H57="C/F",0,E57)-F57) -> 505895.73 | H57: =IF(B57="","",IF(IFERROR(MATCH(B57,'Advances_FEB-2025'!B:B,0),0)>0,"C/F","NEW")) -> C/F
A58: 45963 | B58: EXP4891 | C58: NEW ROOM BED,IRON BOX,KITCHEN ITEMS,ETC EXP- | E58: 1949.55 | G58: =IF(E58="","",G57+IF(H58="C/F",0,E58)-F58) -> 505895.73 | H58: =IF(B58="","",IF(IFERROR(MATCH(B58,'Advances_FEB-2025'!B:B,0),0)>0,"C/F","NEW")) -> C/F
A59: 13/02/2025 | B59: EXP4905 | C59: SHIRFAN ADVANCES-COLLECTION- | E59: 180 | G59: =IF(E59="","",G58+IF(H59="C/F",0,E59)-F59) -> 505895.73 | H59: =IF(B59="","",IF(IFERROR(MATCH(B59,'Advances_FEB-2025'!B:B,0),0)>0,"C/F","NEW")) -> C/F
A60: 16/02/2025 | B60: EXP4912 | C60: NNA REPAIR EXP-ASLAM- | E60: 334.8 | G60: =IF(E60="","",G59+IF(H60="C/F",0,E60)-F60) -> 505895.73 | H60: =IF(B60="","",IF(IFERROR(MATCH(B60,'Advances_FEB-2025'!B:B,0),0)>0,"C/F","NEW")) -> C/F
A61: 16/02/2025 | B61: EXP4912 | C61: NNA REPAIR EXP-AKMAL- | E61: 300 | G61: =IF(E61="","",G60+IF(H61="C/F",0,E61)-F61) -> 505895.73 | H61: =IF(B61="","",IF(IFERROR(MATCH(B61,'Advances_FEB-2025'!B:B,0),0)>0,"C/F","NEW")) -> C/F
A62: 16/02/2025 | B62: EXP4912 | C62: NNA REPAIR EXP-ASLAM- | E62: 350 | G62: =IF(E62="","",G61+IF(H62="C/F",0,E62)-F62) -> 505895.73 | H62: =IF(B62="","",IF(IFERROR(MATCH(B62,'Advances_FEB-2025'!B:B,0),0)>0,"C/F","NEW")) -> C/F
A63: 20/02/2025 | B63: EXP4938 | C63: PURCHASE ADVANCE-ASLAM- | E63: 50 | G63: =IF(E63="","",G62+IF(H63="C/F",0,E63)-F63) -> 505895.73 | H63: =IF(B63="","",IF(IFERROR(MATCH(B63,'Advances_FEB-2025'!B:B,0),0)>0,"C/F","NEW")) -> C/F
A64: 45872 | B64: EXP5005 | C64: JHOON FOOD ADVANCE- | E64: 11 | G64: =IF(E64="","",G63+IF(H64="C/F",0,E64)-F64) -> 505906.73 | H64: =IF(B64="","",IF(IFERROR(MATCH(B64,'Advances_FEB-2025'!B:B,0),0)>0,"C/F","NEW")) -> NEW
A65: 19/03/2025 | B65: EXP5035 | C65: ADVANCE FOR STORAGE TANK WORK-LOUD CELL-SUSHI- | E65: 10000 | G65: =IF(E65="","",G64+IF(H65="C/F",0,E65)-F65) -> 515906.73 | H65: =IF(B65="","",IF(IFERROR(MATCH(B65,'Advances_FEB-2025'!B:B,0),0)>0,"C/F","NEW")) -> NEW
A66: 20/03/2025 | B66: EXP5036 | C66: PURCHASE ADVANCE-KHUDAIR- | E66: 70 | G66: =IF(E66="","",G65+IF(H66="C/F",0,E66)-F66) -> 515976.73 | H66: =IF(B66="","",IF(IFERROR(MATCH(B66,'Advances_FEB-2025'!B:B,0),0)>0,"C/F","NEW")) -> NEW
A67: 26/03/2025 | B67: EXP5052 | C67: SADATH VEHICLE RIYADH PAINTING WORK- | E67: 900 | G67: =IF(E67="","",G66+IF(H67="C/F",0,E67)-F67) -> 516876.73 | H67: =IF(B67="","",IF(IFERROR(MATCH(B67,'Advances_FEB-2025'!B:B,0),0)>0,"C/F","NEW")) -> NEW
A68: 27/03/2025 | B68: EXP5054 | C68: PURCHASE ADVANCE-ASLAM- | E68: 500 | G68: =IF(E68="","",G67+IF(H68="C/F",0,E68)-F68) -> 517376.73 | H68: =IF(B68="","",IF(IFERROR(MATCH(B68,'Advances_FEB-2025'!B:B,0),0)>0,"C/F","NEW")) -> NEW
A69: 29/03/2025 | B69: EXP5055 | C69: PURCHASE ADVANCE-SABARI- | E69: 1035 | G69: =IF(E69="","",G68+IF(H69="C/F",0,E69)-F69) -> 518411.73 | H69: =IF(B69="","",IF(IFERROR(MATCH(B69,'Advances_FEB-2025'!B:B,0),0)>0,"C/F","NEW")) -> NEW
A70: 29/03/2025 | B70: EXP5055 | C70: COINS CHANGE -BASSAM- | E70: 1000 | G70: =IF(E70="","",G69+IF(H70="C/F",0,E70)-F70) -> 519411.73 | H70: =IF(B70="","",IF(IFERROR(MATCH(B70,'Advances_FEB-2025'!B:B,0),0)>0,"C/F","NEW")) -> NEW
G71: =IF(E71="","",G70+IF(H71="C/F",0,E71)-F71) | H71: =IF(B71="","",IF(IFERROR(MATCH(B71,'Advances_FEB-2025'!B:B,0),0)>0,"C/F","NEW"))
G72: =IF(E72="","",G71+IF(H72="C/F",0,E72)-F72) | H72: =IF(B72="","",IF(IFERROR(MATCH(B72,'Advances_FEB-2025'!B:B,0),0)>0,"C/F","NEW"))
G73: =IF(E73="","",G72+IF(H73="C/F",0,E73)-F73) | H73: =IF(B73="","",IF(IFERROR(MATCH(B73,'Advances_FEB-2025'!B:B,0),0)>0,"C/F","NEW"))
G74: =IF(E74="","",G73+IF(H74="C/F",0,E74)-F74) | H74: =IF(B74="","",IF(IFERROR(MATCH(B74,'Advances_FEB-2025'!B:B,0),0)>0,"C/F","NEW"))
G75: =IF(E75="","",G74+IF(H75="C/F",0,E75)-F75) | H75: =IF(B75="","",IF(IFERROR(MATCH(B75,'Advances_FEB-2025'!B:B,0),0)>0,"C/F","NEW"))
G76: =IF(E76="","",G75+IF(H76="C/F",0,E76)-F76) | H76: =IF(B76="","",IF(IFERROR(MATCH(B76,'Advances_FEB-2025'!B:B,0),0)>0,"C/F","NEW"))
G77: =IF(E77="","",G76+IF(H77="C/F",0,E77)-F77) | H77: =IF(B77="","",IF(IFERROR(MATCH(B77,'Advances_FEB-2025'!B:B,0),0)>0,"C/F","NEW"))
G78: =IF(E78="","",G77+IF(H78="C/F",0,E78)-F78) | H78: =IF(B78="","",IF(IFERROR(MATCH(B78,'Advances_FEB-2025'!B:B,0),0)>0,"C/F","NEW"))
G79: =IF(E79="","",G78+IF(H79="C/F",0,E79)-F79) | H79: =IF(B79="","",IF(IFERROR(MATCH(B79,'Advances_FEB-2025'!B:B,0),0)>0,"C/F","NEW"))
G80: =IF(E80="","",G79+IF(H80="C/F",0,E80)-F80) | H80: =IF(B80="","",IF(IFERROR(MATCH(B80,'Advances_FEB-2025'!B:B,0),0)>0,"C/F","NEW"))
G81: =IF(E81="","",G80+IF(H81="C/F",0,E81)-F81) | H81: =IF(B81="","",IF(IFERROR(MATCH(B81,'Advances_FEB-2025'!B:B,0),0)>0,"C/F","NEW"))
G82: =IF(E82="","",G81+IF(H82="C/F",0,E82)-F82) | H82: =IF(B82="","",IF(IFERROR(MATCH(B82,'Advances_FEB-2025'!B:B,0),0)>0,"C/F","NEW"))
... G100: =IF(E100="","",G99+IF(H100="C/F",0,E100)-F100) | H100: =IF(B100="","",IF(IFERROR(MATCH(B100,'Advances_FEB-2025'!B:B,0),0)>0,"C/F","NEW"))
A102: TOTAL | E102: =SUM(E7:E101) -> 326763.44 | F102: =SUM(F7:F101) -> 0

Sheet Suspense_MAR-2025
A1: SUSPENSE RECONCILIATION - MAR-2025
A3: OPENING BALANCE | B3: ='Suspense_FEB-2025'!E3 -> -162101.8 | D3: CLOSING BALANCE | E3: =-17267.64+SUM(E7:E1000)-SUM(F7:F1000) -> -113303.06
A5: UNIDENTIFIED TRANSACTIONS
A6: Date | B6: Journal No | C6: Description | D6: Reference | E6: Debit | F6: Credit | G6: Running Balance
A7: 14/01/2025 | B7: JN8176 | C7: BANK TRANSFER-NIDHEEESH | E7: 0 | F7: 1 | G7: =IF(AND(E7="",F7=""),"",B3+E7-F7) -> -162102.8
A8: 19/01/2025 | B8: JN8400 | C8: BANK TRANSFER- | E8: 0 | F8: 2550 | G8: =IF(AND(E8="",F8=""),"",G7+E8-F8) -> -164652.8
A9: 45690 | B9: JN8696 | C9: BANK TRANSFER-NOT IDENTIFIED | E9: 0 | F9: 2500 | G9: =IF(AND(E9="",F9=""),"",G8+E9-F9) -> -167152.8
A10: 28/02/2025 | B10: EXP4993 | C10: Installment Payment FOR NEW SALES VEHICLE HIACE- | E10: 4308.03 | F10: 0 | G10: =IF(AND(E10="",F10=""),"",G9+E10-F10) -> -162844.77
A11: 28/02/2025 | B11: EXP4993 | C11: Installment Payment FOR NEW SALES VEHICLE HIACE- | E11: 4308.03 | F11: 0 | G11: =IF(AND(E11="",F11=""),"",G10+E11-F11) -> -158536.74
A12: 28/02/2025 | B12: EXP4993 | C12: Installment Payment FOR NEW SALES VEHICLE HIACE- | E12: 4308.03 | F12: 0 | G12: =IF(AND(E12="",F12=""),"",G11+E12-F12) -> -154228.71
A13: 45659 | B13: JN8328 | C13: BANK POS-THOYYIB | E13: 183.98 | G13: =IF(AND(E13="",F13=""),"",G12+E13-F13) -> -154044.73
A14: 45750 | B14: JN9046 | C14: BANK TRANSFER-NOT IDENTIFIED | E14: 0 | F14: 2000 | G14: =IF(AND(E14="",F14=""),"",G13+E14-F14) -> -156044.73
A15: 45903 | B15: JN9047 | C15: Installment Payment FOR VEHICLE | E15: 1788.76 | F15: 0 | G15: =IF(AND(E15="",F15=""),"",G14+E15-F15) -> -154255.97
A16: 45903 | B16: JN9047 | C16: Installment Payment FOR VEHICLE | E16: 3402.52 | F16: 0 | G16: =IF(AND(E16="",F16=""),"",G15+E16-F16) -> -150853.45
A17: 45964 | B17: JN9151 | C17: BANK TRANSFER-KHALID | E17: 0 | F17: 5508 | G17: =IF(AND(E17="",F17=""),"",G16+E17-F17) -> -156361.45
A18: 45964 | B18: JN9164 | C18: BANK TRANSFER-NOT IDENTIFIFED | E18: 0 | F18: 10000 | G18: =IF(AND(E18="",F18=""),"",G17+E18-F18) -> -166361.45 | J18: 101387.94
A19: 13/03/2025 | C19: BANK TRANSFER-SHAREEF | E19: 201 | F19: 0 | G19: =IF(AND(E19="",F19=""),"",G18+E19-F19) -> -166160.45
A20: 14/03/2025 | B20: JN9056 | C20: BANK POS-SHAREEF | E20: 0 | F20: 562 | G20: =IF(AND(E20="",F20=""),"",G19+E20-F20) -> -166722.45
A21: 15/03/2025 | B21: JN9057 | C21: BANK POS-SHAREEF | E21: 0 | F21: 460 | G21: =IF(AND(E21="",F21=""),"",G20+E21-F21) -> -167182.45
A22: 16/03/2025 | B22: JN9066 | C22: BANK TRANSFER-NIDHEESH | E22: 0 | F22: 425 | G22: =IF(AND(E22="",F22=""),"",G21+E22-F22) -> -167607.45
A23: 16/03/2025 | B23: JN9058 | C23: BANK POS-SHAREEF | E23: 0 | F23: 112.65 | G23: =IF(AND(E23="",F23=""),"",G22+E23-F23) -> -167720.1
A24: 16/03/2025 | B24: JN9059 | C24: BANK POS-SHAREEF | E24: 0 | F24: 57.99 | G24: =IF(AND(E24="",F24=""),"",G23+E24-F24) -> -167778.09
A25: 18/03/2025 | B25: JN9060 | C25: BANK POS-SHAREEF | E25: 0 | F25: 200.98 | G25: =IF(AND(E25="",F25=""),"",G24+E25-F25) -> -167979.07
A26: 19/03/2025 | B26: JN9072 | C26: BANK POS-KHALID | E26: 0 | F26: 108 | G26: =IF(AND(E26="",F26=""),"",G25+E26-F26) -> -168087.07
A27: 19/03/2025 | B27: JN9076 | C27: BANK TRANSFER-DHIYA | E27: 0 | F27: 145.5 | G27: =IF(AND(E27="",F27=""),"",G26+E27-F27) -> -168232.57
A28: 19/03/2025 | B28: JN9166 | C28: BANK TRANSFER NOT IDENTIFIED | E28: 0 | F28: 204 | G28: =IF(AND(E28="",F28=""),"",G27+E28-F28) -> -168436.57
A29: 20/03/2025 | B29: JN9061 | C29: BANK POS-SHAREEF | E29: 0 | F29: 2349.98 | G29: =IF(AND(E29="",F29=""),"",G28+E29-F29) -> -170786.55
A30: 21/03/2025 | B30: JN9079 | C30: BANK TRANSFER-KHALID | E30: 0 | F30: 150 | G30: =IF(AND(E30="",F30=""),"",G29+E30-F30) -> -170936.55
A31: 21/03/2025 | B31: JN9159 | C31: BANK TRANSFER-SHAREEF(8189) | E31: 0 | F31: 1920 | G31: =IF(AND(E31="",F31=""),"",G30+E31-F31) -> -172856.55
... A62: 31/03/2025 | B62: JN9157 | C62: BANK TRANSFER-NIDHEESH | E62: 0 | F62: 1500 | G62: =IF(AND(E62="",F62=""),"",G61+E62-F62) -> -210168.08
C63: BANK CHARGES FOR TRANSFER | E63: 48.57 | F63: 0 | G63: =IF(AND(E63="",F63=""),"",G62+E63-F63) -> -210119.51
G64: =IF(AND(E64="",F64=""),"",G63+E64-F64)
G65: =IF(AND(E65="",F65=""),"",G64+E65-F65)
G66: =IF(AND(E66="",F66=""),"",G65+E66-F66)
G67: =IF(AND(E67="",F67=""),"",G66+E67-F67) | K67: -42884.47
G68: =IF(AND(E68="",F68=""),"",G67+E68-F68) | K68: -92898.78
G69: =IF(AND(E69="",F69=""),"",G68+E69-F69) | K69: =K67-K68 -> 50014.31
G70: =IF(AND(E70="",F70=""),"",G69+E70-F70)
G71: =IF(AND(E71="",F71=""),"",G70+E71-F71)
G72: =IF(AND(E72="",F72=""),"",G71+E72-F72)
G73: =IF(AND(E73="",F73=""),"",G72+E73-F73)
G74: =IF(AND(E74="",F74=""),"",G73+E74-F74)
G75: =IF(AND(E75="",F75=""),"",G74+E75-F75)
G76: =IF(AND(E76="",F76=""),"",G75+E76-F76)
G77: =IF(AND(E77="",F77=""),"",G76+E77-F77)
G78: =IF(AND(E78="",F78=""),"",G77+E78-F78)
G79: =IF(AND(E79="",F79=""),"",G78+E79-F79)
G80: =IF(AND(E80="",F80=""),"",G79+E80-F80)
G81: =IF(AND(E81="",F81=""),"",G80+E81-F81)
G82: =IF(AND(E82="",F82=""),"",G81+E82-F82) | I82: =B3+F82-E82 -> -162101.8 | J82: -42884.47 | K82: =J82+J92 -> -38675.94
G83: =IF(AND(E83="",F83=""),"",G82+E83-F83) | J83: =J82-I82 -> 119217.33
G84: =IF(AND(E84="",F84=""),"",G83+E84-F84) | J84: =K82-E102+F102 -> 9341.77
G85: =IF(AND(E85="",F85=""),"",G84+E85-F85)
G86: =IF(AND(E86="",F86=""),"",G85+E86-F86)
G87: =IF(AND(E87="",F87=""),"",G86+E87-F87) | J87: 68569.17
G88: =IF(AND(E88="",F88=""),"",G87+E88-F88)
G89: =IF(AND(E89="",F89=""),"",G88+E89-F89)
G90: =IF(AND(E90="",F90=""),"",G89+E90-F90)
G91: =IF(AND(E91="",F91=""),"",G90+E91-F91)
G92: =IF(AND(E92="",F92=""),"",G91+E92-F92) | J92: 4208.53
G93: =IF(AND(E93="",F93=""),"",G92+E93-F93) | J93: =J92+F102-E102 -> 52226.24
G94: =IF(AND(E94="",F94=""),"",G93+E94-F94)
G95: =IF(AND(E95="",F95=""),"",G94+E95-F95)
G96: =IF(AND(E96="",F96=""),"",G95+E96-F96)
G97: =IF(AND(E97="",F97=""),"",G96+E97-F97)
G98: =IF(AND(E98="",F98=""),"",G97+E98-F98)
G99: =IF(AND(E99="",F99=""),"",G98+E99-F99)
G100: =IF(AND(E100="",F100=""),"",G99+E100-F100)
A102: TOTAL | E102: =SUM(E7:E101) -> 36642.01 | F102: =SUM(F7:F101) -> 84659.72

Sheet Outstanding_MAR-2025
A1: CUSTOMER OUTSTANDING - MAR-2025
A3: Salesman
A4: Nidheesh | B4: =SUMIF($D$21:$D$504,A4,$G$21:$G$504) -> 57982.29 | C4: =COUNTIF($D$21:$D$504,A4) -> 44 | D4: =IFERROR(B4/C4,0) -> 1317.7793
A5: Jaseel | B5: =SUMIF($D$21:$D$504,A5,$G$21:$G$504) -> 23396.73 | C5: =COUNTIF($D$21:$D$504,A5) -> 18 | D5: =IFERROR(B5/C5,0) -> 1299.8183
A6: Bassam | B6: =SUMIF($D$21:$D$504,A6,$G$21:$G$504) -> 15534.5 | C6: =COUNTIF($D$21:$D$504,A6) -> 12 | D6: =IFERROR(B6/C6,0) -> 1294.5417
A7: akmal | B7: =SUMIF($D$21:$D$504,A7,$G$21:$G$504) -> 15595.44 | C7: =COUNTIF($D$21:$D$504,A7) -> 6 | D7: =IFERROR(B7/C7,0) -> 2599.24
A8: arshad | B8: =SUMIF($D$21:$D$504,A8,$G$21:$G$504) -> 408441.36 | C8: =COUNTIF($D$21:$D$504,A8) -> 24 | D8: =IFERROR(B8/C8,0) -> 17018.39
A9: Shameer riyadh | B9: =SUMIF($D$21:$D$504,A9,$G$21:$G$504) -> 45671.06 | C9: =COUNTIF($D$21:$D$504,A9) -> 28 | D9: =IFERROR(B9/C9,0) -> 1631.1093
A10: company sales | B10: =SUMIF($D$21:$D$504,A10,$G$21:$G$504) -> 650384.77 | C10: =COUNTIF($D$21:$D$504,A10) -> 15 | D10: =IFERROR(B10/C10,0) -> 43358.985
A11: shafi | B11: =SUMIF($D$21:$D$504,A11,$G$21:$G$504) -> 779.99 | C11: =COUNTIF($D$21:$D$504,A11) -> 2 | D11: =IFERROR(B11/C11,0) -> 389.995
A12: dhiya | B12: =SUMIF($D$21:$D$504,A12,$G$21:$G$504) -> 231169.37 | C12: =COUNTIF($D$21:$D$504,A12) -> 18 | D12: =IFERROR(B12/C12,0) -> 12842.743
A13: samir | B13: =SUMIF($D$21:$D$504,A13,$G$21:$G$504) -> 6051.96 | C13: =COUNTIF($D$21:$D$504,A13) -> 9 | D13: =IFERROR(B13/C13,0) -> 672.44
A14: Khalid | B14: =SUMIF($D$21:$D$504,A14,$G$21:$G$504) -> 49421.1 | C14: =COUNTIF($D$21:$D$504,A14) -> 102 | D14: =IFERROR(B14/C14,0) -> 484.52059
A15: Ashik | B15: =SUMIF($D$21:$D$504,A15,$G$21:$G$504) -> 3408.64 | C15: =COUNTIF($D$21:$D$504,A15) -> 10 | D15: =IFERROR(B15/C15,0) -> 340.864
A16: shareef | B16: =SUMIF($D$21:$D$504,A16,$G$21:$G$504) -> 0 | C16: =COUNTIF($D$21:$D$504,A16) -> 0 | D16: =IFERROR(B16/C16,0) -> 0
A17: TOTAL | B17: =SUM(B4:B16) -> 1507837.2 | C17: =SUM(C4:C8) -> 104 | D17: =IFERROR(B17/C17,0) -> 14498.435
A19: CUSTOMER DETAILS
A20: Customer Code | B20: Customer Name | C20: Area | D20: Salesman | E20: Invoice Amount | F20: Paid Amount | G20: Balance | H20: Days
A21: CUST4 | B21: Sharikkath Aswak petro AL markaziyathh | C21: Al Ahsa-2 | D21: Nidheesh | E21: 568.87 | G21: =IF(E21="","",E21-F21) -> 568.87
A22: CUST56 | B22: Nour al zahraa supermarket | C22: Al Ahsa-2 | D22: Nidheesh | E22: 553.94 | G22: =IF(E22="","",E22-F22) -> 553.94
A23: CUST57 | B23: Essa Muhammad al Abbadi | C23: Al Ahsa-2 | D23: Nidheesh | E23: 135.97 | G23: =IF(E23="","",E23-F23) -> 135.97
A24: CUST154 | B24: Moona al aila family | C24: Al Ahsa-2 | D24: Nidheesh | E24: 302.95 | G24: =IF(E24="","",E24-F24) -> 302.95
A25: CUST156 | B25: Al nouri grocery to sell food | C25: Al Ahsa-2 | D25: Nidheesh | E25: 1536.83 | G25: =IF(E25="","",E25-F25) -> 1536.83
A26: CUST175 | B26: Red apple supermarket | C26: Al Ahsa-2 | D26: Nidheesh | E26: 1009.87 | G26: =IF(E26="","",E26-F26) -> 1009.87
A27: CUST199 | B27: Thamuniyath wajihath al busthan | C27: Al Ahsa-2 | D27: Nidheesh | E27: 1191.83 | G27: =IF(E27="","",E27-F27) -> 1191.83
A28: CUST202 | B28: Athareek al mothi | C28: Al Ahsa-2 | D28: Nidheesh | E28: 1343.61 | G28: =IF(E28="","",E28-F28) -> 1343.61
A29: CUST203 | B29: Al Amana foodstuff market. 2 | C29: Al Ahsa-2 | D29: Nidheesh | E29: 1701.73 | G29: =IF(E29="","",E29-F29) -> 1701.73
A30: CUST232 | B30: Customer for food minimarket | C30: Al Ahsa-2 | D30: Nidheesh | E30: 319.95 | G30: =IF(E30="","",E30-F30) -> 319.95
A31: CUST285 | B31: Mosasath likuli almujtamae altijaria | C31: Al Ahsa-2 | D31: Nidheesh | E31: 837.89 | G31: =IF(E31="","",E31-F31) -> 837.89
A32: CUST347 | B32: Markaz Darth al shahsi | C32: Al Ahsa-2 | D32: Nidheesh | E32: 512.94 | G32: =IF(E32="","",E32-F32) -> 512.94
... A308: CUST4261 | B308: Over Consumer Trading | C308: Riyadh | D308: shafi | E308: 217.97 | G308: =IF(E308="","",E308-F308) -> 217.97
G309: =IF(E309="","",E309-F309)
G310: =IF(E310="","",E310-F310)
G311: =IF(E311="","",E311-F311)
G312: =IF(E312="","",E312-F312)
G313: =IF(E313="","",E313-F313)
G314: =IF(E314="","",E314-F314)
G315: =IF(E315="","",E315-F315)
G316: =IF(E316="","",E316-F316)
G317: =IF(E317="","",E317-F317)
G318: =IF(E318="","",E318-F318)
G319: =IF(E319="","",E319-F319)
G320: =IF(E320="","",E320-F320)
... G504: =IF(E504="","",E504-F504)
A506: GRAND TOTAL | E506: =SUM(E21:E504) -> 1507837.2 | F506: =SUM(F21:F504) -> 0 | G506: =SUM(G21:G504) -> 1507837.2

Sheet Banks_APR-2025
A1: BANK SUMMARY - APR-2025
A3: Bank Name | B3: Opening Balance | C3: Total Received | D3: Bank Charges | E3: Total Payments | F3: Closing Balance | G3: Notes
A4: Alrajhi-1097 | B4: 940747.84 | C4: 499753.85 | D4: 2472.57 | E4: 1120348.4 | F4: =B4+C4-D4-E4 -> 317680.71
A5: Alrajhi-new | B5: 625593.4 | C5: 75000 | D5: 0 | E5: 0 | F5: =B5+C5-D5-E5 -> 700593.4
A6: SNB Al Ahsa Branch | B6: 122846.55 | C6: 432946.48 | D6: 345 | F6: =B6+C6-D6-E6 -> 555448.03
A7: Albilad | B7: 30059.63 | C7: 989452.17 | D7: 126.5 | E7: 722221.18 | F7: =B7+C7-D7-E7 -> 297164.12
A9: SUB-TOTAL SAR | B9: =SUM(B4:B7) -> 1719247.4 | C9: =SUM(C4:C7) -> 1997152.5 | D9: =SUM(D4:D7) -> 2944.07 | E9: =SUM(E4:E7) -> 1842569.6 | F9: =SUM(F4:F7) -> 1870886.3
A11: USD ACCOUNTS
A12: Bank Name | B12: Opening | C12: Amount Received | D12: Bank Charge | E12: Payment | F12: Balance | G12: Notes
A13: Albilad USD | B13: 914.64 | C13: 92000 | D13: 74.73 | E13: 91728.63 | F13: =B13+C13-D13-E13 -> 1111.28
A15: SUB-TOTAL USD | B15: =SUM(B13) -> 914.64 | C15: =SUM(C13) -> 92000 | D15: =SUM(D13) -> 74.73 | E15: =SUM(E13) -> 91728.63 | F15: =SUM(F13) -> 1111.28
A17: GRAND TOTAL (SAR + USD Converted) | B17: =B9+B15*3.75 -> 1722677.3 | C17: =C9+C15*3.75 -> 2342152.5 | D17: =D9+D15*3.75 -> 3224.3075 | E17: =E9+E15*3.75 -> 2186552 | F17: =F9+F15*3.75 -> 1875053.6
A19: SUMMARY
A20: Total Bank Balance (SAR): | C20: =F17 -> 1875053.6

Sheet Advances_APR-2025
A1: ADVANCE RECONCILIATION - APR-2025
A3: OPENING BALANCE | B3: ='Advances_MAR-2025'!E3 -> 491564.28 | D3: CLOSING BALANCE | E3: =164800.84+SUM(E7:E101) -> 541048.28
A5: TRANSACTIONS
A6: Date | B6: Voucher No | C6: Description | D6: Person/Party | E6: Advance Given | F6: Amount Settled | G6: Running Balance
A7: 45447 | B7: EXP3275 | C7: CONSTRUCTION WORK ADVANCE RAJENDHRAN- | E7: 3000 | G7: =IF(E7="","",B$3+IF(H7="C/F",0,E7)-F7) -> 491564.28 | H7: =IF(B7="","",IF(IFERROR(MATCH(B7,'Advances_MAR-2025'!B:B,0),0)>0,"C/F","NEW")) -> C/F
A8: 17/04/2024 | B8: EXP3295 | C8: TANJI BAO PAYMENT TO BE CHARGED TO BOILING POT- | E8: 8625 | G8: =IF(E8="","",G7+IF(H8="C/F",0,E8)-F8) -> 491564.28 | H8: =IF(B8="","",IF(IFERROR(MATCH(B8,'Advances_MAR-2025'!B:B,0),0)>0,"C/F","NEW")) -> C/F
A9: 17/04/2024 | B9: EXP3391 | C9: Shirfan - Cash withdraw -- | E9: 1500 | G9: =IF(E9="","",G8+IF(H9="C/F",0,E9)-F9) -> 491564.28 | H9: =IF(B9="","",IF(IFERROR(MATCH(B9,'Advances_MAR-2025'!B:B,0),0)>0,"C/F","NEW")) -> C/F
A10: 16/05/2024 | B10: EXP3422 | C10: sabari-seeds unloading staff refreshment drink- | E10: 20 | G10: =IF(E10="","",G9+IF(H10="C/F",0,E10)-F10) -> 491564.28 | H10: =IF(B10="","",IF(IFERROR(MATCH(B10,'Advances_MAR-2025'!B:B,0),0)>0,"C/F","NEW")) -> C/F
A11: 27/05/2024 | B11: EXP3462 | C11: THOYYIB VEHICLE WINGE EXP- | E11: 350 | G11: =IF(E11="","",G10+IF(H11="C/F",0,E11)-F11) -> 491564.28 | H11: =IF(B11="","",IF(IFERROR(MATCH(B11,'Advances_MAR-2025'!B:B,0),0)>0,"C/F","NEW")) -> C/F
A12: 27/05/2024 | B12: EXP3462 | C12: ADVANCES -THOYYIBE VEHICLE COMPLAINT- | E12: 143.48 | G12: =IF(E12="","",G11+IF(H12="C/F",0,E12)-F12) -> 491564.28 | H12: =IF(B12="","",IF(IFERROR(MATCH(B12,'Advances_MAR-2025'!B:B,0),0)>0,"C/F","NEW")) -> C/F
A13: 27/05/2024 | B13: EXP3462 | C13: ADVANCES -THOYYIBE VEHICLE COMPLAINT- | E13: 600 | G13: =IF(E13="","",G12+IF(H13="C/F",0,E13)-F13) -> 491564.28 | H13: =IF(B13="","",IF(IFERROR(MATCH(B13,'Advances_MAR-2025'!B:B,0),0)>0,"C/F","NEW")) -> C/F
A14: 45602 | B14: EXP3508 | C14: AMITHFOOD ADVANCE-SABARI- | E14: 15 | G14: =IF(E14="","",G13+IF(H14="C/F",0,E14)-F14) -> 491564.28 | H14: =IF(B14="","",IF(IFERROR(MATCH(B14,'Advances_MAR-2025'!B:B,0),0)>0,"C/F","NEW")) -> C/F
A15: 16/06/2024 | B15: EXP3683 | C15: AIR TRANSPORTAION AIR LANKA- | E15: 2730 | G15: =IF(E15="","",G14+IF(H15="C/F",0,E15)-F15) -> 491564.28 | H15: =IF(B15="","",IF(IFERROR(MATCH(B15,'Advances_MAR-2025'!B:B,0),0)>0,"C/F","NEW")) -> C/F
A16: 16/06/2024 | B16: JN5365 | C16: COLLECTION CASH TAKEN BY HANI | E16: 34000 | G16: =IF(E16="","",G15+IF(H16="C/F",0,E16)-F16) -> 491564.28 | H16: =IF(B16="","",IF(IFERROR(MATCH(B16,'Advances_MAR-2025'!B:B,0),0)>0,"C/F","NEW")) -> C/F
A17: 24/06/2024 | B17: EXP3614 | C17: ADVANCE-SALMANUL FARIZ-RIYADH- | E17: 500 | G17: =IF(E17="","",G16+IF(H17="C/F",0,E17)-F17) -> 491564.28 | H17: =IF(B17="","",IF(IFERROR(MATCH(B17,'Advances_MAR-2025'!B:B,0),0)>0,"C/F","NEW")) -> C/F
A18: 45298 | B18: EXP3645 | C18: ASHIK-ADVANCE- | E18: 4000 | G18: =IF(E18="","",G17+IF(H18="C/F",0,E18)-F18) -> 491564.28 | H18: =IF(B18="","",IF(IFERROR(MATCH(B18,'Advances_MAR-2025'!B:B,0),0)>0,"C/F","NEW")) -> C/F
A19: 45358 | B19: EXP3654 | C19: SIVA RIYADH TRAVELING EXP ADVANCE-- | E19: 2000 | G19: =IF(E19="","",G18+IF(H19="C/F",0,E19)-F19) -> 491564.28 | H19: =IF(B19="","",IF(IFERROR(MATCH(B19,'Advances_MAR-2025'!B:B,0),0)>0,"C/F","NEW")) -> C/F
A20: 45450 | B20: EXP3699 | C20: FT24188664289852 Ben WHITE GRAPHICS-ADVANCE FOR RECEPTION WORK- | E20: 2790 | G20: =IF(E20="","",G19+IF(H20="C/F",0,E20)-F20) -> 491564.28 | H20: =IF(B20="","",IF(IFERROR(MATCH(B20,'Advances_MAR-2025'!B:B,0),0)>0,"C/F","NEW")) -> C/F
A21: 45603 | B21: EXP3749 | C21: FUEL ADVANCE-MUNEESH- | E21: 50 | G21: =IF(E21="","",G20+IF(H21="C/F",0,E21)-F21) -> 491564.28 | H21: =IF(B21="","",IF(IFERROR(MATCH(B21,'Advances_MAR-2025'!B:B,0),0)>0,"C/F","NEW")) -> C/F
A22: 17/07/2024 | B22: EXP4088 | C22: Traffic Violati REF 5366217470-7023706836-TRAFFIC -NIDHEESH- | E22: 113 | G22: =IF(E22="","",G21+IF(H22="C/F",0,E22)-F22) -> 491564.28 | H22: =IF(B22="","",IF(IFERROR(MATCH(B22,'Advances_MAR-2025'!B:B,0),0)>0,"C/F","NEW")) -> C/F
A23: 31/07/2024 | B23: EXP4021 | C23: FUEL-ADVANCE-NASAR- | E23: 100 | G23: =IF(E23="","",G22+IF(H23="C/F",0,E23)-F23) -> 491564.28 | H23: =IF(B23="","",IF(IFERROR(MATCH(B23,'Advances_MAR-2025'!B:B,0),0)>0,"C/F","NEW")) -> C/F
